Workbook

Sheet 總覽
A1: aibuddy 生產就緒追蹤
A2: 最後更新：2026-10-15 10:42 · 本頁由 tracker.py 自動生成，請勿手動編輯
A3: 總進度：25/93 已完成（27%） · 目前階段：1 止血定案（10/5–10/16）
A5: 優先級 | B5: 說明 | C5: 總數 | D5: 未開始 | E5: 進行中 | F5: 已完成 | G5: 阻塞 | H5: 不適用 | I5: 完成率
A6: P0 | B6: 安全：真實用戶使用前必須完成 | C6: =COUNTIF('任務清單'!$B:$B,$A6) -> 17 | D6: =COUNTIFS('任務清單'!$B:$B,$A6,'任務清單'!$F:$F,D$5) -> 1 | E6: =COUNTIFS('任務清單'!$B:$B,$A6,'任務清單'!$F:$F,E$5) -> 2 | F6: =COUNTIFS('任務清單'!$B:$B,$A6,'任務清單'!$F:$F,F$5) -> 13 | G6: =COUNTIFS('任務清單'!$B:$B,$A6,'任務清單'!$F:$F,G$5) -> 0 | H6: =COUNTIFS('任務清單'!$B:$B,$A6,'任務清單'!$F:$F,H$5) -> 1 | I6: =IFERROR(F6/(C6-H6),0) -> 0.8125
A7: P1 | B7: 兒童安全與合規：上市前必須完成 | C7: =COUNTIF('任務清單'!$B:$B,$A7) -> 14 | D7: =COUNTIFS('任務清單'!$B:$B,$A7,'任務清單'!$F:$F,D$5) -> 8 | E7: =COUNTIFS('任務清單'!$B:$B,$A7,'任務清單'!$F:$F,E$5) -> 3 | F7: =COUNTIFS('任務清單'!$B:$B,$A7,'任務清單'!$F:$F,F$5) -> 0 | G7: =COUNTIFS('任務清單'!$B:$B,$A7,'任務清單'!$F:$F,G$5) -> 2 | H7: =COUNTIFS('任務清單'!$B:$B,$A7,'任務清單'!$F:$F,H$5) -> 1 | I7: =IFERROR(F7/(C7-H7),0) -> 0
A8: P2 | B8: 工程與運維：規模化前完成 | C8: =COUNTIF('任務清單'!$B:$B,$A8) -> 25 | D8: =COUNTIFS('任務清單'!$B:$B,$A8,'任務清單'!$F:$F,D$5) -> 9 | E8: =COUNTIFS('任務清單'!$B:$B,$A8,'任務清單'!$F:$F,E$5) -> 6 | F8: =COUNTIFS('任務清單'!$B:$B,$A8,'任務清單'!$F:$F,F$5) -> 10 | G8: =COUNTIFS('任務清單'!$B:$B,$A8,'任務清單'!$F:$F,G$5) -> 0 | H8: =COUNTIFS('任務清單'!$B:$B,$A8,'任務清單'!$F:$F,H$5) -> 0 | I8: =IFERROR(F8/(C8-H8),0) -> 0.4
A9: R | B9: 產品與上市：1/15 出廠 3,000 隻（馬會 2,500、政協青年聯會 500）＋AI Buddy 數量未定 | C9: =COUNTIF('任務清單'!$B:$B,$A9) -> 41 | D9: =COUNTIFS('任務清單'!$B:$B,$A9,'任務清單'!$F:$F,D$5) -> 29 | E9: =COUNTIFS('任務清單'!$B:$B,$A9,'任務清單'!$F:$F,E$5) -> 5 | F9: =COUNTIFS('任務清單'!$B:$B,$A9,'任務清單'!$F:$F,F$5) -> 2 | G9: =COUNTIFS('任務清單'!$B:$B,$A9,'任務清單'!$F:$F,G$5) -> 3 | H9: =COUNTIFS('任務清單'!$B:$B,$A9,'任務清單'!$F:$F,H$5) -> 2 | I9: =IFERROR(F9/(C9-H9),0) -> 0.051282051
A10: 合計 | C10: =SUM(C6:C9) -> 97 | D10: =SUM(D6:D9) -> 47 | E10: =SUM(E6:E9) -> 16 | F10: =SUM(F6:F9) -> 25 | G10: =SUM(G6:G9) -> 5 | H10: =SUM(H6:H9) -> 4 | I10: =IFERROR(F10/(C10-H10),0) -> 0.2688172
A12: 階段 | B12: 說明 | C12: 總數 | D12: 未開始 | E12: 進行中 | F12: 已完成 | G12: 阻塞 | H12: 不適用 | I12: 完成率
A13: 1 止血定案 | B13: 10/5–10/16：安全修復、選板（10/16 定案）、角色收窄 | C13: =COUNTIF('任務清單'!$C:$C,$A13) -> 23 | D13: =COUNTIFS('任務清單'!$C:$C,$A13,'任務清單'!$F:$F,D$12) -> 1 | E13: =COUNTIFS('任務清單'!$C:$C,$A13,'任務清單'!$F:$F,E$12) -> 5 | F13: =COUNTIFS('任務清單'!$C:$C,$A13,'任務清單'!$F:$F,F$12) -> 15 | G13: =COUNTIFS('任務清單'!$C:$C,$A13,'任務清單'!$F:$F,G$12) -> 1 | H13: =COUNTIFS('任務清單'!$C:$C,$A13,'任務清單'!$F:$F,H$12) -> 1 | I13: =IFERROR(F13/(C13-H13),0) -> 0.68181818
A14: 2 內測準備 | B14: 10/19–10/30：粵語評測、內容審核、OTA、外殼、上手流程；10/30 CP1 內測就緒檢查 | C14: =COUNTIF('任務清單'!$C:$C,$A14) -> 37 | D14: =COUNTIFS('任務清單'!$C:$C,$A14,'任務清單'!$F:$F,D$12) -> 15 | E14: =COUNTIFS('任務清單'!$C:$C,$A14,'任務清單'!$F:$F,E$12) -> 8 | F14: =COUNTIFS('任務清單'!$C:$C,$A14,'任務清單'!$F:$F,F$12) -> 10 | G14: =COUNTIFS('任務清單'!$C:$C,$A14,'任務清單'!$F:$F,G$12) -> 2 | H14: =COUNTIFS('任務清單'!$C:$C,$A14,'任務清單'!$F:$F,H$12) -> 2 | I14: =IFERROR(F14/(C14-H14),0) -> 0.28571429
A15: 3 封閉內測 | B15: 11/2–11/27：內部測試（10/12 起取代 20 個家庭內測），並行送測認證與合規；11/27 CP2 定品牌 C 數量（R-08） | C15: =COUNTIF('任務清單'!$C:$C,$A15) -> 29 | D15: =COUNTIFS('任務清單'!$C:$C,$A15,'任務清單'!$F:$F,D$12) -> 23 | E15: =COUNTIFS('任務清單'!$C:$C,$A15,'任務清單'!$F:$F,E$12) -> 3 | F15: =COUNTIFS('任務清單'!$C:$C,$A15,'任務清單'!$F:$F,F$12) -> 0 | G15: =COUNTIFS('任務清單'!$C:$C,$A15,'任務清單'!$F:$F,G$12) -> 2 | H15: =COUNTIFS('任務清單'!$C:$C,$A15,'任務清單'!$F:$F,H$12) -> 1 | I15: =IFERROR(F15/(C15-H15),0) -> 0
A16: 4 量產出貨 | B16: 11/30–1/15：量產板到廠、試產 12/7、大貨 12/14–12/31、出廠流程、壓測、售後；1/15 出廠、1/29 送達。每週計劃見 docs/roadmap.md | C16: =COUNTIF('任務清單'!$C:$C,$A16) -> 8 | D16: =COUNTIFS('任務清單'!$C:$C,$A16,'任務清單'!$F:$F,D$12) -> 8 | E16: =COUNTIFS('任務清單'!$C:$C,$A16,'任務清單'!$F:$F,E$12) -> 0 | F16: =COUNTIFS('任務清單'!$C:$C,$A16,'任務清單'!$F:$F,F$12) -> 0 | G16: =COUNTIFS('任務清單'!$C:$C,$A16,'任務清單'!$F:$F,G$12) -> 0 | H16: =COUNTIFS('任務清單'!$C:$C,$A16,'任務清單'!$F:$F,H$12) -> 0 | I16: =IFERROR(F16/(C16-H16),0) -> 0
A17: 合計 | C17: =SUM(C13:C16) -> 97 | D17: =SUM(D13:D16) -> 47 | E17: =SUM(E13:E16) -> 16 | F17: =SUM(F13:F16) -> 25 | G17: =SUM(G13:G16) -> 5 | H17: =SUM(H13:H16) -> 4 | I17: =IFERROR(F17/(C17-H17),0) -> 0.2688172
A19: ⏭ 接下來做什麼
A20: 編號 | B20: 任務 | C20: 階段 | D20: 狀態 | E20: 驗收標準 / 上次測試
A21: P0-07 | B21: 輪換 JWT secret，作廢已發出的 token | C21: 1 止血定案 | D21: 進行中 | E21: ① 生產自架 Supabase 換上新的 JWT secret（app.settings.jwt_secret 一併更新），重發 anon／service_role key，更新到 Supabase 各容器、網頁（anon key 要重新建置 image）和語音伺服器。② 用舊 secret 簽的東西全部失效：舊 anon key、舊 service_role key、舊 secret 簽的無過期用戶 JWT（P0-06 前 MAC 換到的那種）。③ DEVICE_JWT_SECRET 同時輪換；設備不用重新配對（P0-06 之後設備靠 NVS 裡的設備密鑰自動換新 token）。④ 沒有任何運行中的容器還持有舊值；用到 service key 的其他地方（例如 Mac 上的 release_firmware.py）已改用新 key。⑤ 有回滾方法。
A22: P0-11 | B22: 設備認領要求持有證明 | C22: 1 止血定案 | D22: 進行中 | E22: 上次測試：部分通過 — 本機（分支 p0-11-bind-ticket da3709b，localhost:3015 + 本機 Supabase，測試腳本 22/22）：① 只帶 MAC → 401、密鑰 + user_code 當票 → 403 且設備仍無主 ② 票用過（另一台）／過期／本庫沒發過的票（他品牌）→ 403 ③ B 的票交給 A 的設備 → 409 device_owned，A 綁定不變、B 的票未作廢 ④ 有效票但無設備密鑰 → 401、票未作廢 ⑤ 密鑰 + 有效票 → 200 token，user_id 和 claimed_at 寫入；同一台重送同一張票 → 200 ⑥ DEVICE_CLAIM_LIST=False 時設定頁沒有未認領清單和配對碼欄，有未認領設備在線也看不到，12 秒內無輪詢；=True 時開發清單照舊可認領 ⑦ 同帳號並行 10 次取票 → 5×200、5×429，B 不受影響，滿一分鐘後恢復；表只存 SHA-256；authenticated 讀表／呼叫 RPC → 42501。未部署線上。 綁定票（用戶 2026-10-12 決定，經藍牙交付，見 R-21）：① 已登入的 App 向伺服器取綁定票：一次性、5 分鐘有效，綁定該帳號和品牌。② 設備連上 Wi-Fi 後，用設備密鑰加綁定票呼叫伺服器；伺服器在同一個交易裡檢查票有效、設備 user_id 為空、品牌相符，然後寫入 user_id 和 claimed_at，並把票作廢。③ 不再列出全球未認領設備，也不再用手動輸入的配對碼認領（舊流程只在開發模式保留）。④ 已有主人的設備不能被認領：原主在 App 內解綁，聯絡不到原主就由管理員在後台解綁（R-11）。⑤ 第一版一台設備只屬一個帳號。⑥ 取票有頻率上限（每帳號每分鐘 5 次）。
A23: P2-10 | B23: DeepSeek v4 flash 經 OpenRouter 時固定可用的供應商 | C23: 1 止血定案 | D23: 進行中 | E23: 上次測試：部分通過 — ① 16 家供應商各 20 次真實 session prompt（含開場白，串流，order=[x]+allow_fallbacks=false）：建議清單 azure/alibaba/novita/siliconflow/gmicloud 各 20/20，0 空內容 0 特殊 token，首字 p50 1.25/2.33/2.59/2.56/3.25s；只設 order 時 order=[deepinfra] 實際由 Relace 回應（回過 content=None）→ 已改為 allow_fallbacks=false。伺服器端 LLMOutputGuard：pytest 8 項（尾部/跨 chunk 拆開的 token、空回應記警告）全套 203 passed；真實 LLM 串流經 guard 6 角色 12/12 正常、無誤觸發。② 實機 5 次開場白未做 線上用 DeepSeek 時，provider_order 只列實測正常的供應商（例如 StreamLake、SiliconFlow、GMICloud、Novita），並開 reasoning；或線上改用 gemma-4-26b。伺服器遇到空回應或特殊 token 時不把它送去 TTS。
A24: R-01 | B24: 選定量產板子 | C24: 1 止血定案 | D24: 進行中 | E24: 已定案 Spotpear AI Toy（用戶 10/07 決定）；評分表 ①–⑦ 在 Spotpear 上實測並記錄結果，沒有否決性問題（如 2 小時內 OOM 重啟、C3 無法啟用 Secure Boot v2＋Flash 加密、無認證模組）。
A25: R-02 | B25: 角色收窄到 5–8 個粵語陪伴角色 | C25: 1 止血定案 | D25: 進行中 | E25: 上次測試：通過 — 用戶已確認角色陣容。本地 DB：① 未隱藏內建角色只剩 hk_ 6 個 ② localhost:3100 Children 頁只見 6 個、Story 頁只見叮叮兔/咪咪貓 ③ 每角色 10 句粵語，prompt 用伺服器同一套組裝、開場白按 pipecat 以 user 角色送出：gemma-4-26b 65/66 合格（1 句 4 句/2 問）；DeepSeek v4 flash 預設 reasoning 61/66（超標都只多 1–2 句）；全部無簡體、恐怖、拼字 只保留 5–8 個自己設計的粵語陪伴角色，其餘設為 is_hidden；每個角色按 3–6 歲設計：句子短、用詞簡單、一次只問一個問題，不講恐怖、暴力或需要識字的內容。
A26: P1-02 | B26: 日誌移除兒童個人資料 | C26: 2 內測準備 | D26: 進行中 | E26: 上次測試：部分通過 — 本機（分支 p1-02-log-pii）：模擬板子跑 3 輪，孩子名 PROBE小明、性格『鍾意恐龍』、記憶『佢有隻狗叫PROBE豆豆』；把對話、回覆、事實切成 47 段搜日誌 → 預設 INFO 0 段；同一流程 LOG_LEVEL=DEBUG → 27 段（證明搜尋有效）。INFO 日誌也無 token。pytest 245 passed（新增 test_log_privacy 6 項：事實/摘要、PostgREST details、OpenRouter flagged_input、非 JSON 回覆、預設 INFO 與 traceback 無變量值）。未做：部署線上並在生產日誌重跑。 生產日誌只記 ID、長度、類別，不記內容；內容只在 DEBUG 等級輸出，生產不開 DEBUG。
A27: P1-10 | B27: 管理操作審計記錄 | C27: 2 內測準備 | D27: 進行中 | E27: 上次測試：部分通過 — 本機（分支 p1-10-p2-09-audit-usage，migration 已套用到本機 Supabase）：探測腳本 22/22，用 GoTrue 真實登入、只把 42501 當拒絕。① 超管改角色 short_description → 1 筆 update、before/after 只有該欄、actor=該管理員；改 voice_stack → 1 筆含新舊值；不改內容再存 → 0 筆 ② 超管 JWT UPDATE/DELETE → 42501；service role DELETE → 42501；postgres DELETE/TRUNCATE 被觸發器拒絕；內容管理員、家長讀 → []；anon → 42501。網頁實測：IP 加一個活動提示 → 只記 1 筆 ip_modes insert，原樣再存 → 0 筆，清除 → 1 筆 delete；Accounts 建帳號 → account.create（不含密碼）；改匯率 → 1 筆。未做：部署線上。 每個管理操作寫一筆記錄：誰、什麼時間、什麼操作、對象、改之前與改之後的值；記錄只能新增，任何人（包括超級管理員）都不能修改或刪除；超級管理員能在管理端查看。
A28: P1-12 | B28: 設備解綁時的記憶處理：確認、預設保留、可選清除 | C28: 2 內測準備 | D28: 進行中 | E28: 上次測試：部分通過 — 本機（開發板 DEV636 身份的模擬裝置 + 網頁）：TC1/2/5/6/7/8/10/11/13 通過；TC3 重綁後 log『Loaded 2 fact(s)』；TC4 第二台 starts cold、設定頁可切換；TC9 DB 層 B 解綁回 NULL、清除報錯，anon/authenticated 無 EXECUTE；TC10 舊代數寫入三表皆 HTTP 400、清除後 40 秒仍 0 行；TC12 伺服器端 4401 通過；pytest 214 passed。TC14（2026-10-12，rebase 到 main 後的 p1-12-rebased 8d4b9e2，本機 7861）：/ws/nextjs 以網頁 token 對話兩輪，波波熊有回應 → turn_metrics 0→3，memory_facts／memory_segments／conversations 皆 0→0；log 只有 NextJS websocket connected。真機 62:70（2026-10-12，localall 測試版 → 本機 7861/3014，p1-12-rebased）：按住 BOOT 對話 6 輪，conversations 記下『我隻狗叫豆豆…』；TC12：介面解綁（不勾清除）→ 16:06:51 即斷線，之後每次重連都在 auth 前被拒（device token refused），16:07:02 重新取 token 得 202 並顯示配對碼 UKDM7N；facts 1→1、conversations 14→14、segments 1→2（結束時的摘要）、revision 0。TC3：同帳號重綁 → log『Loaded 1 fact(s)』（有一隻3歲嘅狗叫豆豆）＋2 段摘要；真機問『我隻狗叫咩名』的回答未記錄（用戶決定直接部署）。發現：韌體拿到 202 後 websocket 仍每秒重連一次直到被認領，沒有真正停在配對狀態（不屬 P1-12 伺服器端，另開任務）。 ① 按「解綁」先彈出確認對話框，取消則什麼都不改。② 對話框預設保留記憶；「同時清除記憶」要主動勾選，並寫明無法復原。③ 記憶跟設備：鍵是 (user_id, device_id, ip_key)。同一帳號的每台設備各自一份記憶；保留時，同帳號重綁同一台會接著用；換新設備從空白開始（搬記憶交給 R-11）。④ 清除在伺服器端一個交易完成：先刪該設備的 memory_facts、memory_segments、conversations（連帳號的舊 memories），再解綁；任何一步失敗就不解綁，並顯示錯誤。⑤ 其他帳號認領同一台設備，看不到舊記憶（靠 user_id 隔離，不靠刪除成功）。⑥ 設定頁按設備顯示記憶；「清除全部」只清所選設備，連 conversations 一起刪。⑦ 對話中清除，之後的寫入和 consolidation 不會把記憶寫回（devices.memories_revision + trigger）。⑧ 未認領的設備不能對話：/ws/esp32 查到設備沒有 user_id 就在 auth 前以 4401 關閉，即使 24 小時 token 未過期；韌體重新取 token 拿到 202，回到配對狀態。⑨ 解綁時立即中斷該設備正在進行的語音 session。⑩ 網頁語音（playground）沒有設備，不讀也不寫記憶。
A29: P2-09 | B29: 每台設備成本監控 | C29: 2 內測準備 | D29: 進行中 | E29: 上次測試：部分通過 — 本機：pytest 239 passed（新增 8 項：STT/TTS 用量入行、遲到的用量帶到下一行、session 結束寫 usage 行、設備 ID、同一輪多次 LLM 相加、記憶整理的 token 即使回覆解析失敗也記錄並記到該設備）。模擬板子跑 2 輪（本機語音伺服器 7865）：送 2.24s 音訊 → stt_audio_ms=2242（兩輪皆是）；每輪有 tts_chars、token、device_id；session 結束的記憶整理寫成 memory 行（deepseek-v4-flash 946/10 token）。Usage 頁按設備與日期顯示 HK$，改費率即重算並進審計。未做：抽 10 個 session 與 Azure/MiniMax/OpenRouter 帳單對帳（需用戶提供帳單）、部署線上。 每個 session 記錄 STT 秒數、LLM token、TTS 字數並換算成本；admin 頁顯示每台設備的月成本。
A30: P2-13 | B30: Admin 後台改成分組側欄（新頁面先用示例數據預覽） | C30: 2 內測準備 | D30: 進行中 | E30: 上次測試：部分通過 — ① tsc --noEmit 通過 ② 略過登入的測試頁（另一份副本、獨立 .next）：超級管理員 15 頁、內容管理員只見 Characters／IPs；1360px 與 375px 均無橫向捲動（scrollWidth=clientWidth=375）；#audit 直接打開正確；③④ 未做：需真實帳號登入 /admin 6 個現有分頁（Model、Latency、Characters、IPs、Accounts、Admins）在新側欄照常使用，讀寫真實數據；內容管理員只看到 Characters 和 IPs；預覽頁和規劃頁只有超級管理員看到，並有橫幅寫明示例數據、按鈕不能用；每頁有 #hash 可直接打開；手機寬度沒有橫向捲動。
A31: P2-24 | B31: 麥克風上行改用 IMA ADPCM（減少 4 倍頻寬） | C31: 2 內測準備 | D31: 進行中 | E31: 上次測試：部分通過 — ① pytest test_mic_adpcm 10 項：Mac 上編譯 firmware MicAdpcm.cpp，與 audioop 逐 byte 一致（改壞一個表值即失敗）；分塊解碼 = 連續流解碼；掉一塊只損失該塊；人聲段 SNR > 20dB；全套 275 passed ② 伺服器按 X-Mic-Codec 解碼，無 header 照舊 PCM（10:37 1.7.5 → mic=pcm，10:40 1.7.6 → mic=adpcm）③ 62:70 Guest（2026-10-15）：ADPCM 3 輪 Azure zh-HK 辨識通順完整（如『但係點解依家望到外邊係陰天嘅？』），STT 431–526ms，對照同場 PCM 560ms；上行 27,650B/3,370ms 與 16,625B/2,026ms = 8.2 B/ms（PCM 32），發送最長 3ms、最低 heap 55KB ① 新韌體上行用 IMA ADPCM（64 kbps），每幀帶解碼狀態（預測值＋步長索引），掉幀或重連後下一幀即可正確解碼 ② 連線時以 header 聲明編碼；伺服器據此解碼成 16kHz PCM 再交給 STT；沒有聲明的舊韌體照舊當 PCM ③ 韌體編碼與伺服器解碼位元一致（同一算法）④ 編碼 CPU < 2%、不增加延遲 ⑤ 語音辨識品質與 PCM 相當
... A42: R-25 | B42: 網頁的品牌主題系統 | C42: 2 內測準備 | D42: 未開始 | E42: ① 每個品牌一個資料夾：主題 token（顏色、字體、圓角）、logo 和圖示、文案、功能開關；首頁、上手流程、角色頁可以有品牌版本，其餘頁面共用 ② 由部署的環境變數選品牌（每套部署一個品牌，見 R-34），伺服器端渲染的第一屏就是對的主題，不閃爍 ③ 共用元件裡沒有品牌名稱和寫死的品牌顏色 ④ 加一個品牌只需要加資料夾、設定和一套部署，不用改共用元件
A44: ✅ 最近完成與測試效果
A45: 編號 | B45: 任務 | C45: 測試結果 | D45: 完成日期 | E45: 測試證據
A46: P2-21 | B46: P2-16 ⑤ 後台 OTA 頁換成真實數據與操作 | C46: 通過 | D46: 2026-10-15 | E46: 10-14 模擬 20 台全部通過（見上次）；2026-10-15 真機補做：OTA 頁對 1.7.1 白名單加 62:70（UI MAC 欄）→ 存檔確認框 → 『Narrow to Whitelist』確認 → Make current（用戶點）→ 62:70 安裝並確認，頁面顯示 Rolling out · Whitelist、運行 1、回滾 0；每步一筆審計。依賴 P2-14 已完成
A47: P2-16 | B47: OTA 分批推送與後台發佈頁 | C47: 通過 | D47: 2026-10-15 | E47: ④ 真機 62:70（2026-10-15）：USB 刷 1.7.0（開機印 aibuddy-build;kind=dev;…;version=1.7.0）→ release_firmware.py publish --dev 1.7.1 → 後台白名單加 62:70、改白名單階段、設為 current → 按 BOOT 喚醒：取 token 200、下載 12.8s、重開進 app1，09:39:36 連上語音伺服器；09:42 重開 → 『Firmware 1.7.1 on app1』無 probation、Up to date；頁面『Rolling out · Whitelist』運行 1 台、回滾 0；審計 5 筆（發佈、白名單、階段、1.6.2 取消 current、1.7.1 設 current）。①②③⑤ 見 P2-17～P2-21 模擬 20 台
A48: P2-14 | B48: Admin 設備頁：每台玩具的狀態、韌體與基本操作 | C48: 通過 | D48: 2026-10-15 | E48: 真機 62:70（2026-10-15，分支 hw-test-1015 = dev+P2-16，-localall 1.7.0，本機網頁 3230 + 語音 7870）：① 開機 → 設備頁 Online、-67 dBm、1.7.0；板子停在 bootloader 約 38 秒後語音伺服器判離線（uvicorn ping 超時），頁面 0 台在線 ② 重置設備密鑰 → device_secrets 行刪除，板子重開印『Device secret issued and stored』並連上，行恢復 ③ 強制解綁 → 板子拿 202（配對碼 UKDM7N），語音伺服器拒絕連線；兩項審計各 1 筆含操作者與原因 ④ 內容管理員/anon → 42501（10-14 探測腳本）
A49: P2-20 | B49: P2-16 ④ 從後台上傳與發佈韌體（取代手貼 service key） | C49: 通過 | D49: 2026-10-14 | E49: node --test lib/firmwareImage.test.mjs 8/8（合成映像：dev build、無標記、未知板、晶片不符、非映像、截斷/損壞、超 4MB 拒；超 2MB 只警告）。分支 dev server + 本機 Supabase 端到端 16/16（GoTrue 真實登入的 cookie）：超管上傳 9.9.0 release build → 201 草稿（is_current f、rollout 0%），DB SHA-256 = 檔案、storage 原樣；審計 insert 記該超管；設備仍只拿到 current 1.6.2；已有 1.0.2 → 409；localall → 422 dev build；4MB+16 → 422；9MB → 413；PNG → 422；舊 1.6.1 映像（無標記）→ 422 指向 release_firmware.py；內容管理員上傳/刪除 → 403；未登入 → 401；刪 current → 409；超管刪草稿 → 行和映像都刪、審計 delete 記該超管。release_firmware.py list 照常。測試帳號與數據已清除
A50: P2-19 | B50: P2-16 ③ 回滾過多時自動暫停推送 | C50: 通過 | D50: 2026-10-14 | E50: migration 20261014200000 BEGIN/ROLLBACK 套用兩次無錯並已套用本機。模擬 20 台連跑兩次 12/12：1/20 回滾不暫停、其餘 18 台照常；2/20 → 'Auto-paused: 2 of 20 boards rolled back (10%)'，其餘 0 台拿到 ota；已運行的設備記為 running 且不再下發；審計 1 筆 actor 空；恢復後 17 台拿到、保持恢復，第 3 台回滾 → 'Auto-paused: 3 of 20 (15%)'；白名單 2 台中 1 台回滾 → 50% 立即暫停、另一台不再下發；anon 呼叫 ota_maybe_pause → 401/42501。測試數據已清除，spotpear-ai-toy 1.6.2 仍 100% 未暫停
A51: P2-18 | B51: P2-16 ② 按 MAC 雜湊穩定分組決定哪台收到 ota | C51: 通過 | D51: 2026-10-14 | E51: node --test lib/otaRollout.test.mjs 6/6：10,000 隨機 MAC 在 10%/50% 誤差 < 1 個百分點、同 MAC（含大小寫/空白）結果一致、升階段只增不減、白名單各階段都在、不同版本選不同的 10%。tsc --noEmit 通過。分支 dev server（3216）+ 本機 Supabase 模擬 20 台（板型 p218-sim，連跑兩次 9/9）：白名單階段只有 1 台、重複不變；10% 拿到的正是雜湊預測的那組（2–5 台含白名單），重複不變；50% 包含 10% 全部；暫停 → 0 台且下載映像 404，恢復 → 200；100% → 除已更新和已回滾的 2 台外 18 台；每台下發次數與記錄一致；運行中/已回滾正確標記；審計 6 筆對應 6 次變更。真 spotpear-ai-toy（預設 100%）回報 1.6.1 → 仍拿到 1.6.2。測試數據已清除
A52: P2-17 | B52: P2-16 ① 分批推送的數據表：推送階段、白名單、每台安裝結果 | C52: 通過 | D52: 2026-10-14 | E52: migration 20261014190000 BEGIN/ROLLBACK 套用兩次無錯並已套用本機；行為：預設 100%、promote 記 stage_changed_at，7 種壞值（25%、小寫/空字串/NULL MAC、暫停缺原因等）全被 check 擋；ota_note_offer 1→2→3，report 正確標 running/failed、別板型不影響，刪發佈連帶刪記錄；審計 5 筆含 'test-board 9.9.9' 標籤。REST 13/13：超管可讀、內容管理員 0 行、anon 42501，三種身份寫入/改階段/呼叫 ota_note_offer 皆 42501。release_firmware.py promote spotpear-ai-toy 1.6.2 成功，token 查詢仍選 1.6.2，審計記 2 筆（actor 空＝service role）
A53: R-41 | B53: App 顯示玩具電量狀態（低電量提示） | C53: 通過 | D53: 2026-10-14 | E53: ① pytest 33 passed；真 PATCH 本地 Supabase ② 62:70 刷 p212+R-41 強制低電 build（SUPPLY_LOW_RATIO_OVERRIDE=1.05）→ 串口 [WSc] power low:true，本地 DB battery_low=t ③ 刷回正常 1.6.2 → low:false，DB=f ④ App 讀 DB：低電紅標+Please charge+更新時間、72% 充電中、未上報不顯示 ⑤ 他人帳號 0 行、authenticated UPDATE 被拒。62:70 已還原為原 p212 build
A55: ⏳ 等待依賴 / ⛔ 阻塞
A56: 編號 | B56: 任務 | C56: 在等什麼
A57: R-17 | B57: Spotpear 電池耗盡時插電能否正常開機（供電路徑） | C57: 阻塞：[2026-10-08] 2026-10-08 開發板 63:64 插著 USB 時兩次無法解釋的完全斷電重開：09:13:26（崩潰循環中）、10:44:33（閒置、用戶確認沒碰）。都是 USB 先斷線再以 ESP_RST_POWERON 開機，非 brownout；斷電前 6 秒 GPIO0 讀數 99.9% 參考值，屬突然切斷而非緩降（SupplyMonitor 取樣太疏抓不到瞬間）。韌體無法造成 POWERON，指向充電芯片/電池保護/供電路徑，應一併問 Spotpear；放電實測時留意插 USB 閒置時是否也會斷電
A58: P1-01 | B58: 加入內容審核層（輸入與輸出） | C58: 阻塞：[2026-10-14] 2026-10-14 用戶決定：先不定審核服務商，本項暫停。候選：Azure Content Safety（建議，香港區、可在每句回覆說出口前檢查）、OpenRouter 安全模型、OpenAI Moderation、只用本機字詞表。未寫任何程式。
A59: P1-09 | B59: 家長鎖：孩子模式進設定要輸入 PIN | C59: 阻塞：[2026-10-13] 2026-10-13 用戶決定：AI Buddy（品牌 C）延到 1/15 之後，本項不卡 1/15 出廠；AI Buddy 啟動時再開。
A60: R-12 | B60: 家長控制：每日使用上限和休息時段 | C60: 阻塞：[2026-10-13] 2026-10-13 用戶決定：AI Buddy（品牌 C）延到 1/15 之後，本項不卡 1/15 出廠；AI Buddy 啟動時再開。
A61: R-29 | B61: AI Buddy App（品牌 C）頁面 | C61: 阻塞：[2026-10-13] 2026-10-13 用戶決定：AI Buddy（品牌 C）延到 1/15 之後，本項不卡 1/15 出廠；AI Buddy 啟動時再開。
A62: P2-25 | B62: C3 斷線後自救：TLS 握手超時縮短、連續失敗重設 Wi-Fi 或重開、修重試漏記憶體 | C62: 等 P2-24
A63: R-05 | B63: 內測版外殼（3D 打印 20 台） | C63: 等 R-01
A64: R-06 | B64: 家長自助上手流程 | C64: 等 P0-11
A65: R-13 | B65: CP1 內測就緒檢查（10/30） | C65: 等 P0-07、P0-11、P1-01、P1-02、P2-09、R-01、R-02、R-04、R-05、R-06、P1-11
A66: R-18 | B66: 長按 BOOT 重新配網（開 AIBuddy-XXXX 熱點） | C66: 等 R-01
A67: R-19 | B67: 外接按鈕：量產板加 I2C 擴展晶片（TCA9555） | C67: 等 R-01
... A91: R-40 | B91: Admin 客服查詢頁：查帳號、名下設備與最近事件 | C91: 等 P1-10、P1-12
A93: ❓ 待確認問題
A94: 編號 | B94: 問題 | C94: 影響的任務 / 為什麼重要
A95: Q3 | B95: 韌體打算閉源商業銷售嗎？ | C95: P1-06, P1-07：決定 GPL／LGPL 依賴要開源還是替換。
A96: Q11 | B96: 馬會快活的賽馬日版和新春版各多少隻（共 2,500）？ | C96: R-09, R-15：兩款的服裝和配件要分開訂料；11/20 前不知道，PP 樣和大貨單（11/27）會被拖慢。由馬會決定。
A97: Q12 | B97: 快活 App 的「會員綁定」是指甚麼：用我們自己的帳號（email 驗證碼），還是接馬會的會員帳號登入（SSO）？ | C97: P0-11, 快活 App（未入追蹤表）：接馬會 SSO 的話，登入、帳號刪除和資料歸屬都要按馬會的介面重做，工作量和排期要另估，而且 W5（11/9–11/13）就要做快活 App 的綁定；用我們的帳號則和其他品牌共用同一套流程。由馬會決定，要盡早問。
A98: Q13 | B98: 政協青年聯會版的角色、語言和內容由誰提供？什麼時候交？ | C98: 品牌 B 的 App 頁面：品牌 B 的用戶是成人會員，但角色、說話語言、內容規則都還沒有。最遲 11/13 要拿到，才趕得及內部測試和 App 頁面（W6）。
A100: 說明
A101: ・狀態：未開始 → 進行中 → 已完成。只有測試真的跑過而且通過才算已完成；阻塞要在備註寫原因；不再需要的任務標不適用，不要刪。
A102: ・測試結果：未測試 / 通過 / 失敗 / 部分通過。測試證據寫跑了什麼、看到什麼，完整歷史在「更新記錄」。
A103: ・「接下來」按階段排序，同一階段內再按優先級；依賴還沒滿足的任務不會出現在「接下來」。
A104: ・可以手動改：「任務清單」的狀態、測試結果、測試證據、Commit、備註，以及「待確認問題」的回答。其餘欄位和本頁由腳本維護。
A105: ・建議用法：在 Claude Code 對 Claude 說「P0-02 做完了」或輸入 /prod-readiness。Claude 會先跑測試再更新，並寫進「更新記錄」。

Sheet 任務清單
A1: 編號 | B1: 優先級 | C1: 階段 | D1: 類別 | E1: 任務 | F1: 狀態 | G1: 測試結果 | H1: 完成日期 | I1: 問題 / 風險 | J1: 相關位置 | K1: 驗收標準 | L1: 測試方法 | M1: 依賴 | N1: 測試證據 | O1: Commit | P1: 備註
A2: P0-01 | B2: P0 | C2: 1 止血定案 | D2: 安全-驗證 | E2: 確認線上環境的暴露面 | F2: 不適用 | G2: 未測試 | I2: 本機 supabase_db_ElatoAI 已確認 RLS 全開、anon 擁有敏感表的全部權限；線上 elatoai.hkqft.com 尚未驗證，它決定 P0 要多急。 | J2: https://elatoai.hkqft.com/supabase-api frontend-nextjs/app/api/generate_auth_token/route.ts | K2: 取得用戶批准後做只讀探測，逐項記錄 P0-02、P0-03、P0-04、P0-06 在線上是否成立。 | L2: 用 anon key 對 /supabase-api/rest/v1/{conversations,users,devices} 發 HEAD 請求並帶 Prefer: count=exact，只看 Content-Range 的總數，不讀任何內容。 | P2: 探測線上必須先得到用戶在對話中明確批准。 [2026-09-30] Q2：目前沒有真實家庭使用，緊急度已確定；線上驗證改為每項修復部署後各自做。
A3: P0-02 | B3: P0 | C3: 1 止血定案 | D3: 安全-資料庫 | E3: 收緊 conversations 表的 RLS | F3: 已完成 | G3: 通過 | H3: 2026-10-12 | I3: policy「PUBLIC conversations」對所有角色 ALL USING(true)：任何拿到前端 anon key 的人都能讀、改、刪所有孩子的對話記錄。 | J3: supabase/migrations/20250417155518_remote_schema.sql:404 server/fastapi/memory/store.py:310 | K3: 刪除該 policy；authenticated 只能 SELECT／DELETE 自己 user_id 的行；寫入只經 service_role；anon 無任何存取。 | L3: ① 本機 psql 查 pg_policies，conversations 沒有 qual=true 的 policy ② 用 anon key 呼叫 REST 讀取，回傳 0 行 ③ 用戶 A 的 JWT 讀不到用戶 B 的對話 ④ 跑一次語音對話，新行照常寫入 | N3: 線上 2026-10-12（bac24e9）：用網站 bundle 裡的 anon key GET conversations/memory_facts/memory_segments/memories → 42501；10/08 runbook 伺服器端檢查：anon 無授權、無 USING(true)、無管理員 policy 觸及記憶表，25/25 通過；authenticated 分戶隔離沿用本機實測 | O3: e3dfb35 | P3: [2026-10-07] 2026-10-07：migration 20261007130000_lock_down_users_devices_conversations.sql 已寫好並在本機驗證通過，尚未提交。上線順序：先部署新前端（舊前端在新規則下無法建新用戶、無法認領）→ 再在線上 docker exec psql -1 套用 migration → 用線上前端實際的 anon key 重跑 anon GET/PATCH，通過後才標完成。 [2026-10-07] 2026-10-07：用戶決定延後部署，與後續任務合併成一批上線。mygithub/main 與 GHCR :latest 已是新版（da98048 起），主機在跑 runbook 前不可 docker compose pull。
A4: P0-03 | B4: P0 | C4: 1 止血定案 | D4: 安全-資料庫 | E4: 收緊 users 表的 RLS | F4: 已完成 | G4: 通過 | H4: 2026-10-12 | I4: 「Update user table」允許 anon UPDATE 任何用戶；「Enable read access for all users」讓任何人讀取全部用戶（email、孩子姓名、年齡、個性描述）。 | J4: supabase/migrations/20250417155518_remote_schema.sql:392, :408 | K4: 移除 anon UPDATE 與公開 SELECT；用戶只能讀、改自己那一行；service_role 不受影響。 | L4: ① anon GET /rest/v1/users 回傳 0 行 ② anon PATCH 失敗 ③ 用戶 A 讀不到用戶 B ④ Web 設定頁保存孩子資料正常 | N4: 線上 2026-10-12（bac24e9）：anon GET users → 42501；anon PATCH users（不存在的 user_id）→ 42501 permission denied；runbook 伺服器端 anon 無授權、無 USING(true)；分戶讀改沿用本機實測 | O4: e3dfb35 | P4: [2026-10-07] 2026-10-07：migration 20261007130000_lock_down_users_devices_conversations.sql 已寫好並在本機驗證通過，尚未提交。上線順序：先部署新前端（舊前端在新規則下無法建新用戶、無法認領）→ 再在線上 docker exec psql -1 套用 migration → 用線上前端實際的 anon key 重跑 anon GET/PATCH，通過後才標完成。 [2026-10-07] 2026-10-07：用戶決定延後部署，與後續任務合併成一批上線。mygithub/main 與 GHCR :latest 已是新版（da98048 起），主機在跑 runbook 前不可 docker compose pull。
A5: P0-04 | B5: P0 | C5: 1 止血定案 | D5: 安全-資料庫 | E5: 收緊 devices 表的 RLS | F5: 已完成 | G5: 通過 | H5: 2026-10-12 | I5: 任何人可 SELECT 全部設備（含 MAC），也可 UPDATE 任何設備：改掉 user_id 就能把別人的玩具綁到自己帳號。 | J5: supabase/migrations/20250417155518_remote_schema.sql:381, :421 | K5: 只有擁有者可讀自己的設備；認領、解綁改走 server action + service_role；anon 無存取。 | L5: ① anon GET /rest/v1/devices 回傳 0 行 ② anon PATCH user_id 失敗 ③ Web 端認領、解綁、調音量流程正常 | N5: 線上 2026-10-12（bac24e9）：anon GET devices/device_secrets → 42501；anon PATCH devices（不存在的 user_id）→ 42501；認領／解綁網頁流程沿用本機實測 | O5: e3dfb35 | P5: [2026-10-07] 2026-10-07：migration 20261007130000_lock_down_users_devices_conversations.sql 已寫好並在本機驗證通過，尚未提交。上線順序：先部署新前端（舊前端在新規則下無法建新用戶、無法認領）→ 再在線上 docker exec psql -1 套用 migration → 用線上前端實際的 anon key 重跑 anon GET/PATCH，通過後才標完成。 [2026-10-07] 2026-10-07：用戶決定延後部署，與後續任務合併成一批上線。mygithub/main 與 GHCR :latest 已是新版（da98048 起），主機在跑 runbook 前不可 docker compose pull。
A6: P0-05 | B6: P0 | C6: 1 止血定案 | D6: 安全-資料庫 | E6: 撤銷敏感表的多餘授權 | F6: 已完成 | G6: 通過 | H6: 2026-10-12 | I6: anon 與 authenticated 對 users／devices／conversations 擁有 TRUNCATE、DELETE、UPDATE 等全部權限；RLS 只要寫錯一條就全面失守。 | J6: information_schema.role_table_grants（本機已查證） | K6: anon 對這三張表沒有任何權限；authenticated 只保留必要權限，沒有 TRUNCATE。 | L6: psql 查 information_schema.role_table_grants：anon 對三張表沒有記錄，authenticated 沒有 TRUNCATE。 | N6: 線上 2026-10-12（bac24e9）：anon 對 users/devices/conversations 等 10 張私人表 GET 全部 42501（授權層拒絕）；runbook psql：role_table_grants anon=0；authenticated 權限沿用本機 role_table_grants 實測 | O6: e3dfb35 | P6: [2026-10-07] 2026-10-07：migration 20261007130000_lock_down_users_devices_conversations.sql 已寫好並在本機驗證通過，尚未提交。上線順序：先部署新前端（舊前端在新規則下無法建新用戶、無法認領）→ 再在線上 docker exec psql -1 套用 migration → 用線上前端實際的 anon key 重跑 anon GET/PATCH，通過後才標完成。 [2026-10-07] 2026-10-07：用戶決定延後部署，與後續任務合併成一批上線。mygithub/main 與 GHCR :latest 已是新版（da98048 起），主機在跑 runbook 前不可 docker compose pull。
A7: P0-06 | B7: P0 | C7: 1 止血定案 | D7: 安全-認證 | E7: 停止憑 MAC 發放永久用戶 JWT | F7: 已完成 | G7: 通過 | H7: 2026-10-12 | I7: /api/generate_auth_token 只憑 MAC 就發出 role=authenticated、sub=家長 user_id、沒有過期時間的 JWT；配合 P0-04 讀到的 MAC 清單，可以接管所有家長帳號。 | J7: frontend-nextjs/app/api/generate_auth_token/route.ts:195 | K7: 設備首次連線時一次性下發設備密鑰；之後用密鑰換短期（≤24 小時）設備 token，權限只限設備本身，不再是家長 session。 | L7: ① 只知 MAC 的請求拿不到任何 token ② 過期 token 被拒 ③ 設備 token 讀不到 users／conversations ④ 實機配對、對話端到端正常 | N7: 線上 2026-10-12（bac24e9）：POST /api/generate_auth_token 只帶 42:34 的 MAC → 401、帶錯誤密鑰 → 401、GET → 410；42:34 用 NVS 密鑰在線上換 token 並連上語音伺服器（P0-13 10/09 實測） | O7: da98048 | P7: [2026-10-07] 2026-10-07：實作＝device_secrets 表（20261007150000）＋lib/deviceAuth.ts＋generate_auth_token 改 POST＋韌體密鑰存 NVS「device」、token 只放 RAM、斷線時續期。上線必須三者一起：前端、語音伺服器、韌體；兩邊 env 都要先設同一個 DEVICE_JWT_SECRET；雲端已配對的測試板要重燒。NVS 被清的板子要刪 device_secrets 那行才能重新領密鑰。 [2026-10-07] 2026-10-07：本機全部驗收通過（commit da98048），仍保持進行中：線上尚未部署。上線順序：兩邊 env 設同一個 DEVICE_JWT_SECRET → 套用 20261007150000 → 部署前端與語音伺服器 → 重燒雲端測試板。 [2026-10-07] 2026-10-07：用戶決定延後部署，與後續任務合併成一批上線。mygithub/main 與 GHCR :latest 已是新版（da98048 起），主機在跑 runbook 前不可 docker compose pull。
A8: P0-07 | B8: P0 | C8: 1 止血定案 | D8: 安全-認證 | E8: 輪換 JWT secret，作廢已發出的 token | F8: 進行中 | G8: 未測試 | I8: 已發出的 token 永不過期，只能換 secret 作廢；自架 Supabase 的 anon／service_role key 也由同一個 secret 簽發，會一起失效。 | J8: 伺服器上自架 Supabase 的 .env 前端與 FastAPI 的 env | K8: ① 生產自架 Supabase 換上新的 JWT secret（app.settings.jwt_secret 一併更新），重發 anon／service_role key，更新到 Supabase 各容器、網頁（anon key 要重新建置 image）和語音伺服器。② 用舊 secret 簽的東西全部失效：舊 anon key、舊 service_role key、舊 secret 簽的無過期用戶 JWT（P0-06 前 MAC 換到的那種）。③ DEVICE_JWT_SECRET 同時輪換；設備不用重新配對（P0-06 之後設備靠 NVS 裡的設備密鑰自動換新 token）。④ 沒有任何運行中的容器還持有舊值；用到 service key 的其他地方（例如 Mac 上的 release_firmware.py）已改用新 key。⑤ 有回滾方法。 | L8: 照 docs/deploy/rotate-2026-10-jwt-secrets.sh 在伺服器執行，第 6 步自動檢查：① 舊 anon key、舊 service_role key、舊 secret 簽的 canary 用戶 JWT（第 3 步證明輪換前可用）→ 401 ② 新 anon／service key → 200；網站 JS 只含新 anon key；generate_auth_token 新設備 → 202；語音伺服器拒絕舊 device token、接受新的；輪換後已綁定設備自動回來（last_seen_at 更新）③ 運行中容器的環境變數裡沒有任何舊值 ④ 人手：網頁登入、playground 對話、實機對話各一次 | M8: P0-06 | P8: [2026-10-12] 2026-10-12：runbook 已寫好（分支 p0-07-rotate-secrets）。輔助函數本機測試 18/18：自簽 JWT 能被 node jsonwebtoken 驗證、語音伺服器 device_auth.verify 接受新 token、拒絕簽錯的 token、env 檔替換正確。驗收從「所有設備重新配對」改為「設備不用重新配對」，因為 P0-06 之後設備靠設備密鑰自動換 token。下一步：用戶在伺服器跑 STEP=0（只讀）並把結果貼回來。
A9: P0-08 | B9: P0 | C9: 1 止血定案 | D9: 安全-語音伺服器 | E9: 語音伺服器驗證設備身份（/ws/esp32） | F9: 已完成 | G9: 通過 | H9: 2026-10-12 | I9: 只看 X-Device-Mac header，Bearer token 只記進 log、從不驗證；任何人冒充一台玩具就能問出孩子的記憶，並消耗 API 額度。 | J9: server/fastapi/server.py:375 | K9: 驗證設備 token 的簽名與有效期，設備身份取自 token 而不是 header；無效就以 4401 關閉連線。 | L9: ① 偽造 X-Device-Mac、不帶 token 被拒 ② 過期 token 被拒 ③ 真實設備正常對話 ④ 新增 pytest 覆蓋以上情況 | M9: P0-06 | N9: 線上 2026-10-12（bac24e9）：wss /fastapi/ws/esp32 不帶 token、偽造 token＋X-Device-Mac → 均 4401 invalid device token；42:34 以有效 token 連線對話正常（P0-13 10/09） | O9: da98048 | P9: [2026-10-07] 2026-10-07：device_auth.py 用標準庫 hmac 驗 HS256（venv 無 PyJWT），每次呼叫才讀 DEVICE_JWT_SECRET（bot.py 的 load_dotenv 在 import 之後）。未設 secret 時所有設備被拒。 [2026-10-07] 2026-10-07：本機全部驗收通過（commit da98048），仍保持進行中：線上尚未部署。上線順序：兩邊 env 設同一個 DEVICE_JWT_SECRET → 套用 20261007150000 → 部署前端與語音伺服器 → 重燒雲端測試板。 [2026-10-07] 2026-10-07：用戶決定延後部署，與後續任務合併成一批上線。mygithub/main 與 GHCR :latest 已是新版（da98048 起），主機在跑 runbook 前不可 docker compose pull。
A10: P0-09 | B10: P0 | C10: 1 止血定案 | D10: 安全-語音伺服器 | E10: 瀏覽器語音路由改用簽名 token（/ws/nextjs） | F10: 已完成 | G10: 通過 | H10: 2026-10-12 | I10: user_id 和角色 prompt 都取自 query string：知道某個 user_id 就能讀到那個孩子的記憶，也能注入任意角色 prompt。 | J10: server/fastapi/server.py:316 | K10: Next.js 為已登入用戶簽發 ≤5 分鐘的 token，FastAPI 驗證後才取 user_id；角色與 prompt 由伺服器端按帳號讀取。 | L10: ① 改 query 裡的 user_id 無效 ② 不帶 token 被拒 ③ Web 對話與記憶正常 | N10: 線上 2026-10-12（bac24e9）：wss /fastapi/ws/nextjs 只帶 user_id 或 token=bogus → 4401；用戶確認：登入 elatoai.hkqft.com 後網頁 playground 可正常對話 | O10: af99fdf | P10: [2026-10-07] 2026-10-07：沿用 DEVICE_JWT_SECRET，以 aud/typ 區分。網頁與語音伺服器須同時上新版。保持進行中：隨下一批部署後線上複測。
A11: P0-10 | B11: P0 | C11: 1 止血定案 | D11: 安全-語音伺服器 | E11: 生產環境關閉 /browser 測試頁與 /ws/browser | F11: 已完成 | G11: 通過 | H11: 2026-10-12 | I11: 完全開放：任何人都能免費使用你付費的 STT／LLM／TTS。 | J11: server/fastapi/server.py:264, :286 | K11: 預設關閉；只有顯式設定開關（例如 ENABLE_BROWSER_TEST=true）時才註冊這兩個路由。 | L11: 生產配置下 GET /browser 回 404，連線 /ws/browser 被拒。 | N11: 線上 2026-10-12（bac24e9）：GET /fastapi/browser 404、/fastapi/ 404、/fastapi/healthz 200、wss /fastapi/ws/browser → HTTP 403 | O11: d0cfbb8 | P11: [2026-10-07] 2026-10-07：本機 server/fastapi/.env 加 ENABLE_BROWSER_TEST=true 方便開發；線上不設。保持進行中：要隨下一批部署後在線上複測（GET https://elatoai.hkqft.com/fastapi/browser → 404）。
A12: P0-11 | B12: P0 | C12: 1 止血定案 | D12: 安全-認證 | E12: 設備認領要求持有證明 | F12: 進行中 | G12: 部分通過 | I12: 任何登入用戶都能看到全球 10 分鐘內上線的未認領設備並直接認領；202 回應把配對碼交給任何知道 MAC 的人。 | J12: frontend-nextjs/db/devices.ts:62 frontend-nextjs/app/api/generate_auth_token/route.ts:172 | K12: 綁定票（用戶 2026-10-12 決定，經藍牙交付，見 R-21）：① 已登入的 App 向伺服器取綁定票：一次性、5 分鐘有效，綁定該帳號和品牌。② 設備連上 Wi-Fi 後，用設備密鑰加綁定票呼叫伺服器；伺服器在同一個交易裡檢查票有效、設備 user_id 為空、品牌相符，然後寫入 user_id 和 claimed_at，並把票作廢。③ 不再列出全球未認領設備，也不再用手動輸入的配對碼認領（舊流程只在開發模式保留）。④ 已有主人的設備不能被認領：原主在 App 內解綁，聯絡不到原主就由管理員在後台解綁（R-11）。⑤ 第一版一台設備只屬一個帳號。⑥ 取票有頻率上限（每帳號每分鐘 5 次）。 | L12: ① 只知 MAC 或 user_code 不能認領 ② 綁定票過期、用過一次、屬於另一品牌 → 認領被拒 ③ 帳號 B 的票交給 A 已綁定的設備 → 被拒，A 的綁定不變 ④ 沒有設備密鑰只帶票 → 401 ⑤ 正常流程：simulate_device.py 帶有效票 → 200 token，devices.user_id 和 claimed_at 寫入 ⑥ 設定頁不再出現別人的未認領設備 ⑦ 取票超過頻率上限 → 429 | M12: P0-06 | N12: 本機（分支 p0-11-bind-ticket da3709b，localhost:3015 + 本機 Supabase，測試腳本 22/22）：① 只帶 MAC → 401、密鑰 + user_code 當票 → 403 且設備仍無主 ② 票用過（另一台）／過期／本庫沒發過的票（他品牌）→ 403 ③ B 的票交給 A 的設備 → 409 device_owned，A 綁定不變、B 的票未作廢 ④ 有效票但無設備密鑰 → 401、票未作廢 ⑤ 密鑰 + 有效票 → 200 token，user_id 和 claimed_at 寫入；同一台重送同一張票 → 200 ⑥ DEVICE_CLAIM_LIST=False 時設定頁沒有未認領清單和配對碼欄，有未認領設備在線也看不到，12 秒內無輪詢；=True 時開發清單照舊可認領 ⑦ 同帳號並行 10 次取票 → 5×200、5×429，B 不受影響，滿一分鐘後恢復；表只存 SHA-256；authenticated 讀表／呼叫 RPC → 42501。未部署線上。 | O12: da3709b | P12: [2026-10-07] 2026-10-07：addUserToDevice（輸入配對碼）沒有限制 user_id IS NULL，知道配對碼就能把已有主人的設備轉到自己帳號；P0-04 只把它搬到 service_role，行為未改，留給本項處理。 [2026-10-07] 2026-10-07：P0-06 之後配對碼只回給持有設備密鑰的請求（只知 MAC → 401），驗收第一條在本機已成立；仍缺：不再列出全球未認領設備、輸錯上限、addUserToDevice 搶已綁定設備。 [2026-10-12] 2026-10-12 用戶確認綁定設計：Spotpear 沒有螢幕、也不讀出配對碼（韌體只印在序列埠），所以改為配網時綁定；已有主人的設備要原主先解綁，否則找客服；第一版一台設備只屬一個帳號。現況漏洞仍在：設定頁列出全球未認領設備可直接認領（AppSettings.tsx、getUnclaimedDevices）；addUserToDevice 沒有檢查 user_id IS NULL，也不寫 claimed_at。 [2026-10-12] 2026-10-12 再改：用戶決定用藍牙配網（R-21），不用熱點綁定碼。改為「App 取綁定票，經藍牙交給設備，設備自己認領」，本項只管伺服器端，不用等藍牙就能先做和測試。 [2026-10-12] 伺服器端完成並在本機全部通過，未部署。注意：DEVICE_CLAIM_LIST 在生產預設關閉，部署後網頁不能再加新設備，要等 R-21 藍牙配網（或臨時在生產開 DEVICE_CLAIM_LIST）。分支以 mygithub/main（8db9d9c）為基礎；本機 main 落後且沒有 P1-12。 [2026-10-12] 2026-10-12 用戶決定：P0-11 不單獨部署，等 R-21 藍牙配網做好後一起上線，避免生產網頁在中間這段時間不能加新設備。
A13: P0-12 | B13: P0 | C13: 1 止血定案 | D13: 安全-Web | E13: 收緊 Admin 權限與路由保護 | F13: 已完成 | G13: 通過 | H13: 2026-10-12 | I13: 沒設 ADMIN_EMAILS 時所有登入用戶都是管理員，可以改全站模型、讀寫別人孩子的角色 prompt；middleware 的登入保護被註解掉。 | J13: frontend-nextjs/lib/admin.ts:45 frontend-nextjs/utils/supabase/middleware.ts:42 | K13: ① 用 admin_roles 表（user_id、角色、授權人、時間）和資料庫函數 has_role() 取代 ADMIN_EMAILS；v1 只有兩種角色：超級管理員、內容管理員 ② 管理端在 /admin：middleware 擋未授權的路由，每個 server action 再檢查一次角色，資料庫 RLS 也用 has_role() 把關。不要求兩步驗證 ③ 任何管理員角色在資料庫層面都沒有讀取其他家庭 conversations、memory_facts、memory_segments 的權限 ④ 恢復 middleware 對 /home 的登入保護 | L13: ① 普通家長帳號訪問 /admin 被拒；直接呼叫 admin server action 被拒 ② 內容管理員能改角色，不能改模型設定和管理員名單 ③ 用超級管理員的 JWT 查 conversations、memory_facts、memory_segments，讀不到其他家庭的資料 ④ 未登入訪問 /home 跳到 /login | N13: 線上 2026-10-12（bac24e9）：runbook 10/08 檢查 未登入 /admin→/login、/api/admin→401、has_role() 只看角色、無管理員 policy 觸及 conversations/記憶表、超管≥1；未登入 /home、/admin→/login；用戶確認：家長帳號開 /admin 轉回 /home、管理員在 /admin 修改角色保存成功；角色細分權限沿用本機 61/61 | O13: c16e1c2 | P13: [2026-09-30] 權限設計討論後擴大範圍：見 Q7、Q9 [2026-10-07] 2026-10-07 本機驗證通過，未部署。上線前：生產 GoTrue 開 TOTP（GOTRUE_MFA_TOTP_ENROLL/VERIFY_ENABLED=true）、套 20261007140000+180000、手動 INSERT 第一個 super_admin；P0-17（anon key 是否 secret）未解前 ④ 在生產不成立 [2026-10-07] 2026-10-07 用戶決定取消 TOTP：管理員只看帳號角色，登入後可直接進 /admin。has_role() 不再要求 aal2（20261007191000）。 [2026-10-07] 2026-10-07 c16e1c2 取消 TOTP 後重測通過。未部署：上線時 runbook 會套 20261007191000 並檢查 has_role() 不含 aal；生產 GoTrue 不再需要開 TOTP。本機 GoTrue 仍開著 TOTP（config.toml 已改，要 supabase stop/start 才生效），不影響權限
A14: P0-13 | B14: P0 | C14: 2 內測準備 | D14: 安全-韌體 | E14: 讓 OTA 真正可用並能回滾 | F14: 已完成 | G14: 通過 | H14: 2026-10-09 | I14: OTA 的韌體 URL 與伺服器證書仍是佔位符：出貨後無法修補任何漏洞。 | J14: firmware-arduino/src/OTA.cpp:9, :14 | K14: 填入真實 URL 與 CA；新韌體啟動自檢通過才標記有效，否則自動回滾；設備上報韌體版本。 | L14: ① 實機推一次升級成功 ② 推一個會崩潰的韌體，確認自動回滾到舊版 | N14: 生產雲端 HTTPS OTA（2026-10-09）：release_firmware.py publish spotpear-ai-toy --current → 1.0.1 現行；42:34 開機 1.0.0 → token 回應 Installing 1.0.1 (1655776 bytes) → 經 Cloudflare+nginx 下載 100% → 重啟到 app1 on probation → 連上語音伺服器 → 120s 後『Firmware 1.0.1 confirmed』。②崩潰回滾沿用 10-08 開發板實測（1.2.2/1.5.3 回滾、1.5.2 切回舊槽）；本機 63:64 1.5.1→1.6.1 亦確認 | O14: 036c0f9 | P14: [2026-10-08] 2026-10-08 b27cc07（分支 p0-13-ota）。部署時要套 20261008100000_firmware_releases.sql，發佈要用 SUPABASE_URL+service key 跑 tools/release_firmware.py [2026-10-08] 2026-10-08 實機①②通過，未部署。上線要：套 20261008100000、部署前端、用 release_firmware.py 發佈正式 build；生產 HTTPS（同 CF CA）的 1.6MB 下載尚未在線上驗證。開發板現跑 1.2.1 localall。未做：已確認版本日後若崩潰循環不會自動切回舊槽，需 USB 救（可另立任務） [2026-10-08] 2026-10-08 OTA 檢查併入 /api/generate_auth_token（68b9550），開機回到一次 TLS 握手；/api/ota/check 移除。token 路徑 API 11/11（舊韌體無 ota、格式錯仍發 token、回滾版本不再提供）；實機 1.3.0→1.3.1 經 token 回應安裝、試用、播完開場白、120s 確認。第一次升級 1.3.1 被 async_tcp 任務看門狗觸發重啟並正確回滾——是既有韌體 bug，見新任務 [2026-10-08] 2026-10-08 交板前強化（682f3b4）：① 確認後連續崩潰 3 次 → 切回另一槽位（每段崩潰期一次）、立即重新確認、上報失敗 ② 回滾按重啟原因判定：崩潰/看門狗即失敗，斷電等非崩潰原因可重試 2 次（R-17 會自己斷電）。實機 1.5.x：試用期內 EN 重啟 → 重試第 2 次並確認；1.5.2 確認後崩潰 3 次 → 回 1.5.1、重新確認、報失敗；1.5.3 試用期崩潰 → 回滾、reason 4 即報失敗。runbook 已加 20261008100000 與 OTA 檢查（3aa632a）。上線後須用開發板對雲端走一次 HTTPS OTA 再交板 [2026-10-09] 2026-10-09 上線前兩個阻礙已修：① Cloudflare 對 Python-urllib UA 回 403 error 1010 → release_firmware.py 自帶 User-Agent（036c0f9）② 主機 nginx /supabase-api/ 預設 1MB 上限 → 413，已在 /home/jackylee/nginx/conf.d/elatoai.conf 兩段 location 加 client_max_body_size 16m（備份 ~/nginx/elatoai.conf.2026-10-09.bak）。雲端此前沒有任何 Spotpear release。service key 只在伺服器 .env.production
A15: P0-14 | B15: P0 | C15: 3 封閉內測 | D15: 安全-韌體 | E15: 韌體簽章、Secure Boot 與 Flash 加密 | F15: 未開始 | G15: 未測試 | I15: 韌體沒有簽章驗證；NVS 裡的 token、WiFi 密碼可以用 esptool 直接讀出。 | J15: firmware-arduino/platformio.ini firmware-arduino/partition.csv | K15: 啟用 Secure Boot v2、flash encryption、NVS encryption；OTA 只接受簽名映像。 | L15: ① 未簽名映像 OTA 被拒 ② esptool read_flash 讀出的是密文 | M15: P0-13, R-01 | P15: 燒 eFuse 不可逆：先用一片測試板驗證，每一步都要用戶確認。 [2026-09-30] Secure Boot 要在定案的板子上驗證
A16: P1-01 | B16: P1 | C16: 2 內測準備 | D16: 兒童安全 | E16: 加入內容審核層（輸入與輸出） | F16: 阻塞 | G16: 未測試 | I16: 只靠 prompt 裡的「Be appropriate」，沒有審核；模型經 OpenRouter 路由到開源模型；Azure STT 預設 profanity=raw（因為 masked 會誤殺非英語）。 | J16: server/fastapi/bot.py server/fastapi/voice_pipeline.py server/fastapi/models/stt/azure.py:47 | K16: STT 文字與 LLM 輸出都經審核，尺度按 3–6 歲；命中時換成安全回覆並記錄事件，事件只記類別、時間、角色，不記原文（管理員不能看兒童內容，見 Q7）；首字延遲增加 ≤150ms。 | L16: ① 30 條紅隊句子（暴力、性、自殘、索取個人資料、越獄）全部被攔截或得到安全回應 ② 100 條正常兒童對話誤攔率 <2% ③ 用 turn_metrics 比較前後延遲 ④ 事件表裡找不到任何對話原文 | P16: [2026-09-30] Q5：3–6 歲；Q7：事件不記原文 [2026-10-14] 2026-10-14：審核事件的後台頁拆成 P1-14，等本項完成後做。 [2026-10-14] 2026-10-14 用戶決定：先不定審核服務商，本項暫停。候選：Azure Content Safety（建議，香港區、可在每句回覆說出口前檢查）、OpenRouter 安全模型、OpenAI Moderation、只用本機字詞表。未寫任何程式。
A17: P1-02 | B17: P1 | C17: 2 內測準備 | D17: 私隱 | E17: 日誌移除兒童個人資料 | F17: 進行中 | G17: 部分通過 | I17: 記憶事實原文、孩子姓名等被寫進伺服器日誌。 | J17: server/fastapi/memory/session.py:482, :488 server/fastapi/device_registry.py（logger.info） | K17: 生產日誌只記 ID、長度、類別，不記內容；內容只在 DEBUG 等級輸出，生產不開 DEBUG。 | L17: 跑一次含孩子姓名與寵物名的對話，grep 日誌找不到原文。 | N17: 本機（分支 p1-02-log-pii）：模擬板子跑 3 輪，孩子名 PROBE小明、性格『鍾意恐龍』、記憶『佢有隻狗叫PROBE豆豆』；把對話、回覆、事實切成 47 段搜日誌 → 預設 INFO 0 段；同一流程 LOG_LEVEL=DEBUG → 27 段（證明搜尋有效）。INFO 日誌也無 token。pytest 245 passed（新增 test_log_privacy 6 項：事實/摘要、PostgREST details、OpenRouter flagged_input、非 JSON 回覆、預設 INFO 與 traceback 無變量值）。未做：部署線上並在生產日誌重跑。 | O17: 4214b99
A18: P1-03 | B18: P1 | C18: 3 封閉內測 | D18: 私隱 | E18: 資料保留期限與自動清理 | F18: 未開始 | G18: 未測試 | I18: 對話與記憶永久保存；刪帳號後資料可能殘留。 | J18: conversations、memory_facts、memory_segments、turn_metrics | K18: 定義保留期（例如對話 90 天）；定時清理；家長能一鍵刪除全部資料並級聯刪除。 | L18: ① 插入過期測試資料，跑清理後消失 ② 刪除測試帳號後各表沒有殘留 | P18: [2026-10-09] 解綁時選擇保留的記憶（P1-12）沒有設備綁定，也要納入保留期限，例如帳號沒有設備且 12 個月沒活動就清除。 [2026-10-09] 補充（2026-10-09 晚）：記憶改成跟設備後，解綁時保留的記憶掛在已解綁的設備名下，家長在設定頁看不到也清不了；還有 device_id 為 NULL 的舊記憶（沒有設備的帳號）。兩者都要納入保留期限自動清理。
A19: P1-04 | B19: P1 | C19: 3 封閉內測 | D19: 合規 | E19: 家長同意流程與私隱政策 | F19: 未開始 | G19: 未測試 | I19: 沒有可驗證的家長同意，也沒有私隱政策；要符合哪條法規取決於目標市場（Q1）。 | J19: frontend-nextjs 註冊／設定流程 | K19: 綁定設備前取得家長同意，並記錄時間與版本；私隱政策列明收集項目、用途、第三方與保留期。 | L19: ① 未同意的帳號無法綁定設備 ② 法律顧問審閱通過 | M19: Q1
A20: P1-05 | B20: P1 | C20: 3 封閉內測 | D20: 合規 | E20: 第三方資料處理協議與資料流向 | F20: 未開始 | G20: 未測試 | I20: 孩子的語音與文字流向 OpenRouter（及其下游模型供應商）、MiniMax、Azure 等第三方。 | J20: server/fastapi/models/ server/fastapi/env.example | K20: 畫出資料流向圖；每家供應商簽 DPA 或確認條款；OpenRouter 請求只路由到不留存、不用於訓練的供應商。 | L20: ① 文件審閱 ② 抓一次 OpenRouter 請求，確認帶 provider.data_collection="deny" | M20: Q1
A21: P1-06 | B21: P1 | C21: 3 封閉內測 | D21: 授權 | E21: 處理 GPL-3.0 依賴（arduino-audio-tools） | F21: 未開始 | G21: 未測試 | I21: 韌體靜態連結 GPL-3.0 的 arduino-audio-tools：閉源銷售就必須公開整個韌體原始碼。 | J21: firmware-arduino/platformio.ini（lib_deps） | K21: 二選一：韌體以 GPL 開源；或替換成 ESP-IDF I2S 等非 GPL 實作。 | L21: 依賴清單中沒有 GPL 庫，或韌體原始碼已公開。 | M21: Q3
A22: P1-07 | B22: P1 | C22: 3 封閉內測 | D22: 授權 | E22: LGPL 合規與第三方授權聲明 | F22: 未開始 | G22: 未測試 | I22: AsyncTCP、ESPAsyncWebServer（LGPL-3.0）、WebSockets（LGPL-2.1）靜態連結，有讓用戶重新連結的義務；上游 ElatoAI 是 MIT，需要保留聲明。 | J22: firmware-arduino/.pio/libdeps LICENSE | K22: 產出 THIRD_PARTY_NOTICES；提供可重新連結的目標檔，或替換這些庫。 | L22: 文件審閱。 | M22: Q3
A23: P1-08 | B23: P1 | C23: 3 封閉內測 | D23: 硬件 | E23: 硬件認證 | F23: 未開始 | G23: 未測試 | I23: 無線（FCC／CE-RED 等）、玩具安全（EN71／ASTM F963）、電池運輸（UN38.3）都是上市前提，具體取決於目標市場。 | J23: 硬件設計 | K23: 列出目標市場需要的認證清單與時間表，並完成送測。 | L23: 取得認證報告。 | M23: Q1, R-01, R-05 | P23: [2026-09-30] 送測需要定案的板子和外殼樣品
A24: P2-01 | B24: P2 | C24: 1 止血定案 | D24: 測試 | E24: 修好後端測試環境 | F24: 已完成 | G24: 通過 | H24: 2026-10-07 | I24: 129 個測試中 58 個失敗；原因是 dev 依賴缺 pytest-asyncio，不是程式錯誤。 | J24: server/fastapi/pyproject.toml | K24: dev group 加入 pytest 與 pytest-asyncio；全部測試通過。 | L24: cd server/fastapi && .venv/bin/python -m pytest -q 全部通過。 | N24: cd server/fastapi && .venv/bin/python -m pytest -q → 173 passed（原本 60 個 async 測試報「not natively supported」）；pyproject dev group 加 pytest>=9,<10、pytest-asyncio>=1.4,<2，asyncio_mode=auto；pip install --dry-run --group dev 可解析 | O24: 6641fa8 | P24: [2026-10-07] 2026-10-07：pytest-asyncio 其實已裝，問題是 strict 模式略過沒有 marker 的 async 測試。剩 10 個 warning 是 pipecat/fastapi 棄用提示與兩個 memory_processors 測試沒啟動 processor，不影響結果。
A25: P2-02 | B25: P2 | C25: 2 內測準備 | D25: CI/CD | E25: CI 跑測試與靜態檢查 | F25: 未開始 | G25: 未測試 | I25: CI 只 build image，不跑任何測試：壞的程式照樣會發佈。 | J25: .github/workflows/ | K25: 推送與 PR 時跑 pytest、ruff、pyright、next lint、tsc --noEmit、pio run；任何一項失敗就不發佈 image。 | L25: 故意推一個失敗測試到分支：CI 變紅，而且沒有發佈 image。 | M25: P2-01
A26: P2-03 | B26: P2 | C26: 1 止血定案 | D26: 版本管理 | E26: 提交目前未提交的改動 | F26: 已完成 | G26: 通過 | H26: 2026-10-06 | I26: 57 個檔案未提交，包括新板子支援（BoardConfig、Codec、IoExpander、LedRing、Battery），隨時可能遺失。 | J26: git status | K26: 按主題拆成若干 commit 並推到 mygithub。 | L26: git status 乾淨；mygithub 上可以看到這些 commit。 | N26: git status --short → 0 行；3bc7119..b322375 按主題拆成 5 個 commit（50 檔：xmini-c3 電量、facts 記憶層、日期時間天氣、BEAM 評測、進度追蹤）；git ls-remote mygithub main = HEAD = b322375 | O26: b322375 | P26: 推到 mygithub 會觸發部署：推送前先跟用戶確認。
A27: P2-04 | B27: P2 | C27: 2 內測準備 | D27: 部署 | E27: 容器改用非 root 用戶 | F27: 未開始 | G27: 未測試 | I27: FastAPI 與前端容器以 root 運行。 | J27: server/fastapi/Dockerfile frontend-nextjs/Dockerfile | K27: 兩個 Dockerfile 都設定非 root 的 USER。 | L27: docker run --rm <image> id -u 輸出不是 0。
A28: P2-05 | B28: P2 | C28: 4 量產出貨 | D28: 成本/濫用 | E28: 拒絕未知設備並限制用量 | F28: 未開始 | G28: 未測試 | I28: 陌生 MAC 也能拿到預設角色的 session（fail open），可以無限消耗 API。 | J28: server/fastapi/server.py server/fastapi/device_registry.py | K28: 未認證設備拒絕連線；每台設備、每個帳號有每日對話時長上限；每個 IP 有連線限流。 | L28: 超出限額後連線被拒，並留下日誌。 | M28: P0-08
A29: P2-06 | B29: P2 | C29: 3 封閉內測 | D29: 可觀測性 | E29: 錯誤追蹤與告警 | F29: 未開始 | G29: 未測試 | I29: 沒有錯誤追蹤與告警：線上出問題只能靠用戶反映。 | J29: FastAPI、Next.js、韌體（崩潰上報） | K29: 三端接入錯誤追蹤；對健康檢查、錯誤率、延遲 p95 設告警。 | L29: 人為製造一個錯誤，5 分鐘內收到告警。 | P29: [2026-10-12] 2026-10-12：三套獨立部署（R-34），監控集中在一個面板，告警寫明品牌。 [2026-10-14] 2026-10-14：admin 的「系統健康」頁只放摘要和外部監控連結，錯誤追蹤與告警用外部服務，不在後台自己做。
A30: P2-07 | B30: P2 | C30: 3 封閉內測 | D30: 運維 | E30: 資料庫備份與還原演練 | F30: 未開始 | G30: 未測試 | I30: 自架 Supabase，沒看到備份策略：硬碟壞掉就等於失去所有孩子的記憶。 | J30: 伺服器上的自架 Supabase | K30: 每日自動備份到異地，保留 30 天；做過一次完整還原。 | L30: 從備份還原到新實例，核對主要表的行數一致。 | P30: [2026-10-12] 2026-10-12：改為三套獨立部署（R-34），備份和還原演練三套都要做，由同一個腳本循環。
A31: P2-08 | B31: P2 | C31: 4 量產出貨 | D31: 擴展性 | E31: 多實例擴展 | F31: 未開始 | G31: 未測試 | I31: session 登記在進程記憶體裡，只能跑單實例；單機上限未知。 | J31: server/fastapi/server.py:35 server/fastapi/memory/session.py:564 | K31: 壓測得出單機並發上限；需要時按 user_id 做 sticky routing，或把 session registry 移到 Redis。 | L31: ① 壓測報告 ② 兩個實例下，device_refresh 對同一台設備仍然生效 | P31: 優先次序取決於 Q4（第一年設備數量）。
A32: P2-09 | B32: P2 | C32: 2 內測準備 | D32: 成本/濫用 | E32: 每台設備成本監控 | F32: 進行中 | G32: 部分通過 | I32: 不知道每次對話、每台設備每月花多少錢，無法定價。 | J32: turn_metrics 各供應商帳單 | K32: 每個 session 記錄 STT 秒數、LLM token、TTS 字數並換算成本；admin 頁顯示每台設備的月成本。 | L32: 抽 10 個 session 與供應商帳單對帳，誤差 <10%。 | N32: 本機：pytest 239 passed（新增 8 項：STT/TTS 用量入行、遲到的用量帶到下一行、session 結束寫 usage 行、設備 ID、同一輪多次 LLM 相加、記憶整理的 token 即使回覆解析失敗也記錄並記到該設備）。模擬板子跑 2 輪（本機語音伺服器 7865）：送 2.24s 音訊 → stt_audio_ms=2242（兩輪皆是）；每輪有 tts_chars、token、device_id；session 結束的記憶整理寫成 memory 行（deepseek-v4-flash 946/10 token）。Usage 頁按設備與日期顯示 HK$，改費率即重算並進審計。未做：抽 10 個 session 與 Azure/MiniMax/OpenRouter 帳單對帳（需用戶提供帳單）、部署線上。 | O32: 8e3b2c5 | P32: [2026-10-14] 2026-10-14：turn_metrics 目前只記 user_id 和 chat_group_id，沒有設備，也沒有 STT 秒數（只有 transcript_chars／response_chars），要改語音伺服器補上，並加單價表。頁面樣子在 preview/UsagePreview.tsx。內部測試每週要報每台每月成本（R-07），數據只能從開始記錄那天累積，建議 10/30 前做好。 [2026-10-14] 2026-10-14：已合併進 dev（rebase 後 commit 8e3b2c5，原 e438bab）。部署用 docs/deploy/release-2026-10-14-audit-usage.sh：先套兩個 migration，再換語音伺服器和網頁映像；第 5 步自動檢查，第 6 步在跟已綁定的玩具對話後確認用量行。
A33: R-01 | B33: R | C33: 1 止血定案 | D33: 硬件 | E33: 選定量產板子 | F33: 進行中 | G33: 未測試 | I33: 第一批的板子還沒定：Waveshare ESP32-S3-AUDIO-Board 已對線上伺服器跑通完整對話；另一塊類似 xmini-c3 的新板還沒到貨。內測必須用將來量產的那塊板。 | J33: firmware-arduino/BOARDS.md firmware-arduino/src/BoardConfig.h firmware-arduino/src/Config.cpp | K33: 已定案 Spotpear AI Toy（用戶 10/07 決定）；評分表 ①–⑦ 在 Spotpear 上實測並記錄結果，沒有否決性問題（如 2 小時內 OOM 重啟、C3 無法啟用 Secure Boot v2＋Flash 加密、無認證模組）。 | L33: 評分表逐項實測： ① 連續對話 2 小時不重啟、不斷線 ② 對話中最低剩餘 heap 與最大連續塊 ③ 電量讀取與續航（連續對話／待機） ④ 休眠與喚醒 ⑤ 裝殼後喇叭響度、1 米外收音 ⑥ Secure Boot v2＋Flash 加密燒錄流程 ⑦ 500 片價格、交期、FCC／CE 報告、是否已認證模組 ⑧ 加分：螢幕（顯示配對碼）、現成外殼 | P33: 新板到貨前，可先從 xiaozhi-esp32 的 config.h 取腳位預先移植。 [2026-10-05] 2026-10-05：期限由「最遲 10/30」收緊為 10/16，外殼、認證、生產都在等這個決定。 [2026-10-05] 2026-10-05：候選板 toy-ai-core-c3-1.54（ESP32-C3、16MB、無 PSRAM）已到貨並移植，env toy-ai-core-c3，引腳由原廠固件反彙編取得（不在小智官方倉庫），原廠固件已整片備份。實測：開機、ES8311 雙向、喇叭出聲、WS2812 狀態燈、SoftAP；WiFi 開啟後內部 RAM 空閒 73KB／最大塊 53KB（未對話）。評分表尚未測：①②⑤⑥⑦；③原廠固件無電池檢測代碼，可能沒有電池；④本版不休眠；⑧有 1.54 寸 ST7789 屏，本版未驅動。 [2026-10-05] 2026-10-05 補充 toy-ai-core-c3 評分表③：板上已裝電池，但讀不到電量。原廠固件的 GetBatteryLevel 直接 return false；C3 能做 ADC 的腳只有 GPIO0–5，全被屏幕(0/1)、LED(2)、I2C(3/4)、I2S(5) 佔用，所以軟件無法讀電池電壓。要讀電量需改硬件：無屏版可把屏幕的 GPIO0/1 讓出來接分壓電阻，或在現有 I2C 上加電量計（如 MAX17048）。GPIO12/13 尚空，可能接了充電狀態腳，未探測。 [2026-10-05] 2026-10-05：用戶表示 Spotpear AI Toy（即 toy-ai-core-c3-1.54，env 改名 spotpear-ai-toy）大概率就是量產板；已和用戶跑通 app 綁定和完整對話。電池檢測的改板要求另立任務。 [2026-10-07] 2026-10-07：用戶定案 Spotpear AI Toy（toy-ai-core-c3-1.54，env spotpear-ai-toy）為量產板，不再等另一塊板。驗收改為在 Spotpear 上測完評分表，確認沒有否決性問題；仍缺 ①②⑥⑦。
A34: R-02 | B34: R | C34: 1 止血定案 | D34: 內容 | E34: 角色收窄到 5–8 個粵語陪伴角色 | F34: 進行中 | G34: 通過 | I34: 現有 40 多個角色大多來自上游：有侵權風險（Batman、Iron Man、Gandalf、Elsa's Frozen Mystery）、涉及醫療（Blood test pal、Luna the Epilepsy Guardian、Vax Buddy）、語氣不適合兒童（Kai Indiebrew 等），而且多數不是粵語。 | J34: personalities 表（is_hidden） server/fastapi/character_prompt.py supabase/migrations/ | K34: 只保留 5–8 個自己設計的粵語陪伴角色，其餘設為 is_hidden；每個角色按 3–6 歲設計：句子短、用詞簡單、一次只問一個問題，不講恐怖、暴力或需要識字的內容。 | L34: ① 查 personalities 表，未隱藏的只剩選定角色 ② Web 端角色列表只顯示這些 ③ 每個角色用 10 句粵語對話抽查：每次回覆不超過 3 句，用詞 3–6 歲聽得懂，一次只問一個問題 | M34: Q5 | N34: 用戶已確認角色陣容。本地 DB：① 未隱藏內建角色只剩 hk_ 6 個 ② localhost:3100 Children 頁只見 6 個、Story 頁只見叮叮兔/咪咪貓 ③ 每角色 10 句粵語，prompt 用伺服器同一套組裝、開場白按 pipecat 以 user 角色送出：gemma-4-26b 65/66 合格（1 句 4 句/2 問）；DeepSeek v4 flash 預設 reasoning 61/66（超標都只多 1–2 句）；全部無簡體、恐怖、拼字 | O34: f72652b | P34: [2026-09-30] Q5：3–6 歲 [2026-10-07] 每個角色現可按語言設定 MiniMax 聲線（personalities.voices，admin 角色頁有廣東話/普通話欄；commit 9557ce5，per-language-voices branch，未 push、雲端 migration 未 apply）。選定角色時可給每個角色一把不同的 Cantonese_* 聲線；MiniMax 只有 6 把粵語聲（男聲僅 PlayfulMan、ProfessionalHost（M)）。本地 AI Hulk/Iron Man 已設粵語聲並實際合成成功。 [2026-10-07] 未完成：(1) 角色陣容待用戶確認 (2) 線上 LLM 若是 minimax-m2.7 則③不過，需確認雲端 app_settings 的 llm_model（本地是 google/gemma-4-26b-a4b-it）(3) migration 未套到雲端，要加入 release runbook 的 migration 清單 (4) 頭像為佔位扁平圖。另：測試帳號自建的 AI Hulk 是自訂角色（creator_id 非空），不受隱藏影響，但屬 Marvel IP [2026-10-07] 條件：線上 LLM 要用 gemma-4-26b，或 DeepSeek v4 flash 開 reasoning；DeepSeek 關 reasoning（effort=none）只有 49/66，多數 4 句。待辦：migration 20261007170000 未套到雲端，下次發布的 runbook 要列入（連同 140000、160000）。另發現：OpenRouter 上 DeepSeek v4 flash 部分供應商壞——DeepInfra 回傳字面 <｜end▁of▁sentence｜>、Venice/Parasail 回空內容，用 DeepSeek 時要在 app_settings 的 provider_order 固定好的供應商
A35: R-03 | B35: R | C35: 1 止血定案 | D35: 工程 | E35: 移除不用的 Deno／Cloudflare 後端與上游預設主機 | F35: 已完成 | G35: 通過 | H35: 2026-10-07 | I35: 網頁端只連 FastAPI；Deno、Cloudflare 只剩韌體的編譯選項和佔位符，另外還留著上游的 Railway 主機（elato-pyserver-production.up.railway.app）。留著會增加維護面，也可能被誤設成連到別人的伺服器。 | J35: server/deno/ server/cloudflare/ firmware-arduino/src/Config.cpp:48, :67, :93 README.md | K35: 刪除兩個後端目錄；韌體只保留 FastAPI 路線（移除 VOICE_SERVER_DENO／_CLOUDFLARE 分支與 Railway 主機）；README 只描述 FastAPI。 | L35: ① grep 全 repo 找不到 deno.dev、workers.dev、railway.app、VOICE_SERVER_DENO、VOICE_SERVER_CLOUDFLARE ② 各板的 pio run 編譯通過 ③ FastAPI 測試通過 | N35: ① grep deno.dev|workers.dev|railway.app|VOICE_SERVER_DENO|VOICE_SERVER_CLOUDFLARE 全 repo → 只剩 seed.json 的任務描述本身 ② pio run 18 個 env 全 SUCCESS（S3 devkit/Waveshare/xmini-c3/Spotpear 各變體）③ FastAPI pytest 182 passed；另 tsc --noEmit 通過 | O35: c3c5249 | P35: [2026-10-07] 同時移除 ELATO_MODE（Railway + www.elatoai.com 及其證書）；前端 auth callback 原本在 NEXT_PUBLIC_VERCEL_ENV=production 時導去 elatoai.com，改為讀 runtime 的 SITE_URL（預設 localhost:3000）——部署時要在 frontend .env.production 設 SITE_URL
A36: R-04 | B36: R | C36: 2 內測準備 | D36: 體驗 | E36: 粵語質量評測 | F36: 未開始 | G36: 未測試 | I36: 香港市場的核心體驗還沒驗證：LLM 可能輸出書面語而不是口語粵語；Azure 對兒童聲音的識別率未知；中英夾雜（「我今日去咗 playground」）未測。 | J36: server/fastapi/language_profiles.py server/fastapi/models/stt/azure.py OpenRouter 模型設定（admin 頁） | K36: 有一套粵語評測集（兒童錄音＋文字提示）；選定的 STT 與 LLM 達到門檻：兒童語音字錯率 ≤15%、口語粵語回覆 ≥90%、中英夾雜句能正確理解。 | L36: ① 30 段 3–6 歲兒童的粵語錄音（3 歲、4–5 歲、6 歲都要有，含中英夾雜）測 STT 字錯率 ② 50 條提示比較 2–3 個候選 LLM 的口語粵語比例 ③ 結果與腳本放在 server/fastapi/evals/ | P36: 門檻是建議值，可按首輪結果與你討論後調整。 [2026-09-30] Q5：3–6 歲；3 歲發音較不清，字錯率門檻可能要按首輪結果再討論
A37: R-05 | B37: R | C37: 2 內測準備 | D37: 硬件 | E37: 內測版外殼（3D 打印 20 台） | F37: 未開始 | G37: 未測試 | I37: 內測家庭需要能直接給小朋友用的外殼；GPIO0 是唯一能喚醒、也是按住說話的鍵，必須做成小朋友按得到的大按鍵。 | J37: 選定板子的尺寸圖與腳位 | K37: 20 台裝殼完成：大按鍵對應 GPIO0；喇叭與麥克風開孔不影響聲音；能充電、看得到燈號；沒有尖角和可吞食的小零件。 | L37: ① 裝殼前後各測一次喇叭響度與 1 米收音 ② 3 歲、4–5 歲、6 歲各至少一位小朋友試用：按得動大按鍵，並理解「按住說話、放開聽回覆」 ③ 1 米高跌落測試，沒有零件脫落 | M37: R-01 | P37: [2026-09-30] Q5：3–6 歲 [2026-10-12] 2026-10-12：外殼改為玩具廠做毛公仔＋內置機芯盒；內部測試用工廠第二版樣品（W4 約 20 隻）代替 3D 打印外殼。
A38: R-06 | B38: R | C38: 2 內測準備 | D38: 體驗 | E38: 家長自助上手流程 | F38: 未開始 | G38: 未測試 | I38: 內測家庭要自己安裝；配網、認領、選角色的流程從沒讓非開發者試過。 | J38: firmware-arduino/src/WifiManager.cpp（配網） frontend-nextjs 認領與設定頁 | K38: 家長只看盒內說明，10 分鐘內從開箱到第一次對話。 | L38: 找 3 位非團隊成員從零開始，記錄耗時與卡住的步驟；3 人都在 10 分鐘內完成。 | M38: P0-11 | P38: [2026-10-09] 2026-10-09 配網熱點由所有板同名的 ELATO-DEVICE 改為 AIBuddy-XXXX（STA MAC 尾 4 位，22ce0ae），App 的「找不到設備」提示同步改；雲端 1.0.1 已 OTA 推出。62:70 用手機連 AIBuddy-6270 配網成功。家長自助流程本身仍未找非團隊成員測試
A39: R-07 | B39: R | C39: 3 封閉內測 | D39: 內測 | E39: 20 個家庭封閉內測 | F39: 未開始 | G39: 未測試 | I39: 還不知道孩子會不會持續使用，也不知道真實使用量與每台成本。 | J39: turn_metrics admin 頁 | K39: 改為內部測試（2026-10-12 用戶決定，原為 20 個外部家庭）：團隊成員及家人用 20 台至少 4 週，三個品牌（馬會快活、政協青年聯會版、AI Buddy）的角色都要測；每週記錄：每次對話輪數、首字延遲 p95、每台每月成本、安全事件數、崩潰與斷線次數、測試者回饋。 | L39: 第 4 週結束時出一份內部測試報告，上面每個指標都有數據。 | M39: R-13 | P39: 依賴包含第 1、2 階段的全部安全項：P0 沒過不讓真實家庭使用。 [2026-09-30] 新的權限項也要在內測前完成 [2026-10-05] 改為以 CP1（R-13）把關：R-13 已涵蓋原有全部依賴。 [2026-10-12] 2026-10-12 用戶決定 11 月的 20 個家庭內測改為內部測試（標題保留原文）。不再需要外部家庭的內測同意書；代價是上市前沒有真實家庭的留存和兒童語音數據，R-04 用同事孩子的錄音補上，1/29 交付後兩週每天看數據。
A40: R-08 | B40: R | C40: 3 封閉內測 | D40: 決策 | E40: 第 8 週關卡決策 | F40: 未開始 | G40: 未測試 | I40: 批量數量、定價、是否延期都要用內測數據決定，不能事前拍板。 | J40: R-07 內測報告 P2-09 成本數據 | K40: CP2：11/27 前寫下決定及依據：① 品牌 C（AI Buddy 自有 IP）的首批數量，以及是否 1/15 出貨（品牌 A 馬會 2,500、品牌 B 政協青年聯會版 500 已定）② 品牌 C 的一次性售價及包含幾年服務（不收月費；A、B 按合約）③ 是否延期（任何 P0 沒過就不出貨）。同時硬件認證必須已送測（P1-08），量產外殼按決定的數量落單（R-09）。CP2 遲超過 2 週，就要評估新年前交付的風險。 | L40: 決策文件經你確認。 | M40: R-07, P2-09, P1-08 | P40: [2026-10-05] 2026-10-05：定為 CP2；收費方式已定為一次性付款、不收月費。 [2026-10-12] 2026-10-12 用戶確認三個品牌與數量：A 香港賽馬會（快活）2,500 隻、B 政協青年聯會版 500 隻、C 自家 AI Buddy（自有 IP）未定。量產板最遲 11/6 按 3,000 台加備品落單，早於 CP2。 [2026-10-12] 2026-10-12：品牌 B 政協青年聯會版的用戶是成人會員；品牌 C 即現有的 AI Buddy 兒童陪伴版（3–6 歲）。A、B 都是成人，兒童專屬項（P1-09 家長鎖、P1-04 的家長同意部分、R-12 每日上限）只在 C 出貨時才卡出貨。 [2026-10-13] 2026-10-13：1/15 只出快活和政協青年聯會兩個品牌（AI Buddy 延後），Tool call 只做調音量和結束對話，RAG v1 只放馬會第一批資料（答對率 80%，婉拒貼士 100%）。關卡決策按這個範圍做。
A41: R-09 | B41: R | C41: 4 量產出貨 | D41: 硬件 | E41: 量產外殼（真空複模） | F41: 未開始 | G41: 未測試 | I41: 100–500 台的外殼：開注塑模具來不及，真空複模通常 2–3 週交貨。 | J41: R-05 的外殼設計 | K41: 按 R-08 定的數量下單並驗收；尺寸、按鍵手感、開孔與內測版一致或更好。 | L41: 抽檢 10%：裝配、按鍵、聲音、跌落測試。 | M41: R-08, R-05, Q11 | P41: [2026-10-12] 2026-10-12：量產外殼改為玩具廠的毛公仔＋機芯盒（鋁模），不是真空複模。PP 樣 11/27、試產 12/7、大貨 12/14–12/31，見 docs/毛公仔打版與量產時間表_草案v0.2.xlsx。
A42: R-10 | B42: R | C42: 4 量產出貨 | D42: 生產 | E42: 出廠流程 | F42: 未開始 | G42: 未測試 | I42: 每台出廠都要寫入設備密鑰、開啟 Flash 加密、通過自檢；目前沒有這條流程。 | J42: firmware-arduino/src/AudioSelfTest.cpp P0-06 的設備密鑰 P0-14 的 Secure Boot／Flash 加密 | K42: 兩段式出廠流程：① Spotpear 出貨前燒共用出廠韌體（不含密鑰、不分品牌、不含某個 IP，含最終 bootloader、分區表、Secure Boot），附每片 MAC 清單 ② 玩具廠裝機芯盒工位用我方電腦和腳本：經序列埠寫入設備密鑰 → 選品牌和款式 → 自檢（喇叭、麥克風、按鍵、燈、電池、WiFi）→ 經 HTTPS 按 MAC 登記設備，寫入該公仔的 ip_key 和這個 IP 的預設角色（R-38）；每台留一行 QC 記錄；工廠工人照作業指導書即可操作，每台約 1.5 分鐘。 | L42: 用 Spotpear 燒好的板連續處理 10 台，其中至少兩種 IP，全部通過且記錄完整，devices.ip_key 與預設角色正確；混入一台壞板，自檢能攔下；混入一台未燒共用韌體的板，工位能識別並提示；登記失敗（例如斷網）時該台標為不合格、可重做，不會出現已寫密鑰但伺服器沒有記錄的設備。重燒 app 分區後 ip_key 仍在。 | M42: P0-06, P0-14, R-01, P2-12, Q10, R-34, R-35, R-38, R-39 | P42: [2026-10-12] 2026-10-12：燒錄地點未定（Q10），最遲 11/6。設備密鑰、品牌和款式都在出廠時寫入（三個品牌共用一個韌體）。 [2026-10-12] 2026-10-12 Q10 已定（燒共用韌體）。Spotpear 出貨測試第一次通電就會開 Secure Boot 和 Flash 加密，所以 11/27 交 Spotpear 的映像必須是最終版（P0-14 要在 W5 前驗證）；app 之後經 OTA 更新。 [2026-10-12] 2026-10-12：三個品牌分開部署後，出廠工位要把每台設備登記到該品牌那套的伺服器，並寫入該品牌的網址（R-35）。 [2026-10-13] 2026-10-13：工位登記要寫入該公仔的 ip_key 和預設角色（R-38）。IP 不編進共用韌體。 [2026-10-14] 2026-10-14：P2-12 定案後，工位多一步：按品牌寫入資源包（tools/build_assets.py --brand ... → esptool write_flash 0x810000），開機 log『Assets: brand ...crc ok』作自檢一項。 [2026-10-14] 2026-10-14：後台的 MAC 清單匯入、整批指定公仔、QC 結果查看拆成 R-39，與工位腳本一起試產。
A43: R-11 | B43: R | C43: 4 量產出貨 | D43: 營運 | E43: 售後：客服、保修與換機 | F43: 未開始 | G43: 未測試 | I43: 設備到了家長手上之後，沒有報修、換機、遠程診斷的流程。 | J43: admin 頁（設備狀態） | K43: 有客服聯絡方式、常見問題、保修條款、換機流程；admin 頁能看到單台設備的最後上線時間、韌體版本和錯誤，協助診斷。 | L43: 演練一次：模擬家長報修 → 診斷 → 換機，全程有記錄。 | M43: P2-14, R-40 | P43: [2026-09-30] v1 沒有客服角色，售後工具由超級管理員使用（Q9） [2026-10-09] 換機時記憶不用搬：記憶跟帳號，同一帳號認領新設備就會繼續（P1-12 TC4）。 [2026-10-09] 更正（2026-10-09 晚）：記憶改成跟設備（P1-12），換新設備會從空白開始。換機流程要加「把舊設備的記憶搬到新設備」：把 memory_facts、memory_segments、conversations 的 device_id 從舊機改成新機（同一 user_id），並由超級管理員執行。 [2026-10-14] 2026-10-14：admin 端的診斷靠設備頁（P2-14），報修、換機、刪帳號的工具在客服查詢頁（R-40）。
A44: R-12 | B44: R | C44: 3 封閉內測 | D44: 家長控制 | E44: 家長控制：每日使用上限和休息時段 | F44: 阻塞 | G44: 未測試 | I44: 3–6 歲孩子的家長最在意每天用多久、睡覺時間玩具會不會還在說話；目前沒有任何使用時間限制，任何時候按鍵玩具都會回應。 | J44: frontend-nextjs/app/components/Settings/（家長設定頁） server/fastapi/server.py（/ws/esp32 開始 session 處） users 表或新表（設定與每日用量） | K44: 家長在設定頁設定每日上限（分鐘）與休息時段（例如 20:00–07:00），按孩子所在地區的時區計算；由伺服器端執行，韌體繞不過；到了上限或在休息時段內，玩具用一句溫和的話說明（例如「而家係休息時間，聽日再傾啦」）就結束，不進入對話；對話中途到了上限，說完當前這句再溫和收尾；家長看得到今天已用多少分鐘。 | L44: ① 上限設 5 分鐘，超過後新一輪被婉拒，跨過午夜後自動恢復 ② 休息時段內按鍵，玩具只說提示語，沒有任何內容送到 LLM ③ 改了設定不用重開機，下一次按鍵就生效 ④ 直接連 /ws/esp32 也繞不過（檢查在伺服器端） | P44: [2026-09-30] 新增：用戶同意加入。「單按說話」模式暫不加入，等 R-05 的 3 歲試用結果再決定。 [2026-10-13] 2026-10-13 用戶決定：AI Buddy（品牌 C）延到 1/15 之後，本項不卡 1/15 出廠；AI Buddy 啟動時再開。
A45: P0-15 | B45: P0 | C45: 1 止血定案 | D45: 安全-權限 | E45: 角色表權限：只有內容管理員能發佈，關閉家長自建角色 | F45: 已完成 | G45: 通過 | H45: 2026-10-12 | I45: personalities 表的 INSERT policy 是 WITH CHECK (true)，anon 與 authenticated 也有全部表權限：任何登入用戶都能插入一個沒有建立者的角色，它會出現在所有孩子的角色列表。家長也能在 /home/create 自建角色（v1 決定關閉，見 Q6）。 | J45: supabase/migrations/20250417155518_remote_schema.sql:426 frontend-nextjs/db/personalities.ts:44, :81 frontend-nextjs/app/home/create/ | K45: 只有內容管理員或超級管理員（has_role）能新增、修改、下架角色；anon 與家長只能讀取已發佈（is_hidden=false）的內建角色，以及家長自己建立的角色；/home/create 入口撤下，不再接受新的家長自建角色；現有家長自建角色暫時保留可用，資料不動。 | L45: ① 家長 JWT 直接 POST /rest/v1/personalities 被拒 ② anon 與家長讀不到隱藏角色或別人自建的角色 ③ 內容管理員在 /admin 新增、修改、下架角色成功 ④ 訪問 /home/create 回 404 或被轉走 | M45: P0-12 | N45: 線上 2026-10-12：② anon 只見 6 個已發佈 hk_ 內建，查隱藏/醫生/家長自建 → []，anon POST → 401；① authenticated 寫入權限由 20261007140000 REVOKE（runbook 10/08 已套用）；用戶確認：④ 家長登入後 /home/create 轉回 /home ③ 管理員在 /admin 修改角色保存成功 | O45: 1d65398 | P45: [2026-09-30] 新增 [2026-10-07] 分支 lock-character-writes（65ddb31 RLS、f3aafdd 撤 /home/create），未 merge、未套用到生產 [2026-10-07] 2026-10-07 用戶決定：現有家長自建角色暫時保留，不設為隱藏，驗收標準相應修改 [2026-10-07] 2026-10-07 已 merge 進 modes-and-ips（55df0a1）；③ 經 P0-12 本機驗證：內容管理員 aal2 經 /admin 新增、修改、下架內建角色成功。② 仍未做 [2026-10-07] 2026-10-07 migration 20261007190000 已在本機套用，未部署。家長自己建立的角色（含 is_hidden）仍可讀，符合驗收「自己建立的角色」；讀不到的是隱藏內建與別人自建。
A46: P0-16 | B46: P0 | C46: 1 止血定案 | D46: 安全-Web | E46: 移除「醫生」身份與寫死的通關碼 | F46: 已完成 | G46: 通過 | H46: 2026-10-12 | I46: 上游遺留的「醫生」模式：user_info.user_type 設成 doctor 就會顯示醫療角色和不同的首頁，開通方式是一個寫死在程式碼裡、瀏覽器可以呼叫的通關碼檢查。 | J46: frontend-nextjs/app/actions.ts:124 frontend-nextjs/app/components/Playground/PlaygroundComponent.tsx:40 frontend-nextjs/app/components/Settings/AppSettings.tsx:51 frontend-nextjs/app/components/Nav/LeftNavbarButtons.tsx:11 frontend-nextjs/app/components/HomePageSubtitles.tsx:13 | K46: 移除 checkDoctorAction 和所有 doctor 身份的分支；程式碼裡沒有任何通關碼；is_doctor 角色隱藏（配合 R-02）。 | L46: ① grep 找不到 checkDoctorAction，也找不到以 user_type 判斷 doctor 的程式碼 ② 前端 tsc 與 lint 通過 ③ 首頁、設定頁、角色列表正常 | N46: 線上 2026-10-12：生產 commit bac24e9 git grep checkDoctorAction/kiwi-subtle-emu/=== "doctor"/isDoctor → 0；線上 13 個 JS（/、/login、/onboard）grep 通關碼/"doctor"/Santa/patient → 0；anon 讀角色只見 6 個 hk_ 角色、is_doctor 全 false；用戶今日線上登入及 playground 正常 | O46: 3897269 | P46: [2026-09-30] 新增 [2026-10-07] 2026-10-07：P0-04 的 migration 讓 authenticated 仍可改 users.user_info，只因 Onboarding/AppSettings 還在那裡寫 doctor 身份；移除 doctor 後，同時從 GRANT UPDATE 拿掉 user_info。 [2026-10-07] 2026-10-07：專案沒有 ESLint 設定（next lint 會停在互動設定），以臨時 config 只檢查改動檔，正式 lint 屬 P2-02。migration 必須在新前端上線後才套用（舊前端每次保存都寫 user_info）。Santa Claus 原本也被標成 is_doctor，一起隱藏；需要時可在 admin 取消隱藏。保持進行中：隨下一批部署。
A47: P1-09 | B47: P1 | C47: 2 內測準備 | D47: 兒童安全 | E47: 家長鎖：孩子模式進設定要輸入 PIN | F47: 阻塞 | G47: 未測試 | I47: /home 的 playground 是給孩子在家長手機上用的，但設定頁沒有任何阻擋：孩子能自己解綁設備、刪記憶、改家長控制。 | J47: frontend-nextjs/app/home/（playground 與 settings） | K47: 從孩子模式進入設定、家長控制、記憶、設備頁面前，都要先輸入家長 PIN（第一次使用時設定）；連錯 5 次鎖定 5 分鐘；忘記 PIN 可用帳號密碼重設。 | L47: ① 孩子模式下點設定，沒有 PIN 進不去 ② 連錯 5 次後鎖定 ③ 用帳號密碼重設 PIN 成功 | P47: [2026-09-30] 新增：這是防孩子誤觸，不是安全邊界；真正的權限仍在伺服器與資料庫。 [2026-10-13] 2026-10-13 用戶決定：AI Buddy（品牌 C）延到 1/15 之後，本項不卡 1/15 出廠；AI Buddy 啟動時再開。
A48: P1-10 | B48: P1 | C48: 2 內測準備 | D48: 安全-權限 | E48: 管理操作審計記錄 | F48: 進行中 | G48: 部分通過 | I48: 管理員改模型、改角色、動設備都沒有記錄；出了問題查不到是誰、什麼時候、改了什麼。 | J48: 新表 admin_audit_log frontend-nextjs/app/home/admin/actions.ts（之後搬到 /admin） | K48: 每個管理操作寫一筆記錄：誰、什麼時間、什麼操作、對象、改之前與改之後的值；記錄只能新增，任何人（包括超級管理員）都不能修改或刪除；超級管理員能在管理端查看。 | L48: ① 改一個角色、改一次模型設定，審計表各出現一筆，前後值正確 ② 用超級管理員 JWT 嘗試 UPDATE／DELETE 審計記錄被拒 | M48: P0-12 | N48: 本機（分支 p1-10-p2-09-audit-usage，migration 已套用到本機 Supabase）：探測腳本 22/22，用 GoTrue 真實登入、只把 42501 當拒絕。① 超管改角色 short_description → 1 筆 update、before/after 只有該欄、actor=該管理員；改 voice_stack → 1 筆含新舊值；不改內容再存 → 0 筆 ② 超管 JWT UPDATE/DELETE → 42501；service role DELETE → 42501；postgres DELETE/TRUNCATE 被觸發器拒絕；內容管理員、家長讀 → []；anon → 42501。網頁實測：IP 加一個活動提示 → 只記 1 筆 ip_modes insert，原樣再存 → 0 筆，清除 → 1 筆 delete；Accounts 建帳號 → account.create（不含密碼）；改匯率 → 1 筆。未做：部署線上。 | O48: 8e3b2c5 | P48: [2026-09-30] 新增 [2026-10-14] 2026-10-14：admin 改側欄後（P2-13），actions.ts 在 frontend-nextjs/app/admin/actions.ts；審計記錄頁的樣子在 preview/AuditPreview.tsx。建議第一個做：設備頁、客服頁、OTA、出廠的每個動作都要寫審計，先有這張表就不用回頭改。 [2026-10-14] 2026-10-14：已合併進 dev（rebase 後 commit 8e3b2c5，原 e438bab）。部署用 docs/deploy/release-2026-10-14-audit-usage.sh：先套兩個 migration，再換語音伺服器和網頁映像；第 5 步自動檢查，第 6 步在跟已綁定的玩具對話後確認用量行。
A49: P1-11 | B49: P1 | C49: 2 內測準備 | D49: 私隱 | E49: 伺服器與資料庫直接存取的管控 | F49: 未開始 | G49: 未測試 | I49: 網頁管理端看不到兒童資料（Q7），但能 SSH 上伺服器或直連資料庫的人仍然看得到；目前沒有名單，也沒有規則。 | J49: 生產伺服器（elatoai.hkqft.com） 自架 Supabase | K49: 列出誰有 SSH 與資料庫直連權限（越少越好）；service_role key 只存在伺服器的 env；私隱政策寫明這類存取的範圍；每次直接查看生產資料都留記錄。 | L49: ① 名單經你確認 ② 私隱政策有對應段落（配合 P1-04） ③ 前端 bundle 與 repo 裡找不到 service_role key | P49: [2026-09-30] 新增
A50: R-13 | B50: R | C50: 2 內測準備 | D50: 決策 | E50: CP1 內測就緒檢查（10/30） | F50: 未開始 | G50: 未測試 | I50: 內測至少要 4 週才有可信數據；CP1 每遲一週，整條線就遲一週，用掉 12/26 到 1/15 之間約 3 週的緩衝。 | J50: 本追蹤表（R-07 的依賴） | K50: 10/30 前，R-07 所列的全部依賴都已完成並測試通過；寫下 go／no-go 決定。未通過時記錄預計延遲幾週、用掉多少緩衝；延遲超過 1 週要說明如何追回。 | L50: ① tracker status：R-07 的依賴全部為已完成或不適用 ② go／no-go 決定經你確認 | M50: P0-02, P0-03, P0-04, P0-05, P0-06, P0-07, P0-08, P0-09, P0-10, P0-11, P0-12, P0-13, P1-01, P1-02, P2-09, R-01, R-02, R-04, R-05, R-06, P0-15, P0-16, P1-11 | P50: [2026-10-05] 新增：2026-10-05 定：兩個 checkpoint 為 10/30（CP1）與 11/27（CP2＝R-08）；硬底線是農曆新年（2027-02-06）前交付。 [2026-10-14] 2026-10-14 用戶決定：移除 P1-09（家長鎖）。品牌 C 已延到 1/15 之後，P1-09 阻塞，留在依賴裡 CP1 永遠過不了。
A51: R-14 | B51: R | C51: 3 封閉內測 | D51: 內容 | E51: 離線兒歌與故事 | F51: 未開始 | G51: 未測試 | I51: 3–6 歲孩子很多時候只想聽歌、聽故事；放在裝置上播放零雲端成本、斷網也能用。風險：錄音與故事的版權（只用自製或已取得授權的內容）、Flash 容量、播放手勢不能和現有按鍵操作衝突。 | J51: firmware-arduino/src（Audio.cpp、Chime.cpp 的本地播放路徑） firmware-arduino/platformio.ini（分區表） 內容來源與授權記錄 | K51: 裝置上存有至少 10 首粵語兒歌和 5 個粵語故事；斷網也能播放；用一個不和現有操作衝突的按鍵手勢開始、停止、切換；音量鍵照常有效；每項內容都有來源與授權記錄（自製或已授權）。內測期間可經 OTA 加入內測機。 | L51: ① 關掉 Wi-Fi，用手勢逐一播放，全部內容可完整播完 ② 播放中停止、切換、調音量都即時生效 ③ 播放後照常可以按鍵對話 ④ 授權記錄表每項都有來源 ⑤ 內測期間記錄各家庭的播放次數 | M51: R-01 | P51: [2026-10-05] 新增：2026-10-05 決定：V1.0 只加這一項新功能；「家長每日摘要」移到 V1.1，不在本表範圍。
A52: R-15 | B52: R | C52: 4 量產出貨 | D52: 交付 | E52: 農曆新年前交付（生產 1/15、送達 1/29） | F52: 未開始 | G52: 未測試 | I52: 2027 年農曆新年是 2/6，內地工廠一般提前約兩週停工；1 月中生產未完成，就可能拖到 2 月底甚至 3 月，遲幾週會變成遲兩個月。 | J52: R-08 決定的數量 R-09 量產外殼 R-10 出廠流程 | K52: 12/26 為內部目標；R-08 決定的全部數量最遲 1/15 生產完成，1/29 前全部送達家庭。1/15 未能全部完成時，先交付已完成的部分，其餘新年後補發，並通知相關家庭。 | L52: ① 生產記錄：完成日期 ≤ 1/15，數量等於 R-08 決定的數量 ② 送貨或簽收記錄：全部日期 ≤ 1/29 | M52: R-09, R-10 | P52: [2026-10-05] 新增 [2026-10-12] 2026-10-12：首批 A 馬會 2,500＋B 政協青年聯會版 500＝3,000 隻，C 未定。
A53: R-16 | B53: R | C53: 1 止血定案 | D53: 硬件 | E53: Spotpear 量產版加電池電壓檢測（GPIO0 分壓） | F53: 未開始 | G53: 未測試 | I53: Spotpear AI Toy 裝了電池但讀不到電量：C3 能做 ADC 的腳 GPIO0–5 全被佔用，原廠固件也沒有電量代碼。家長不知道何時要充電，評分表③無法通過。量產改板要趁早向廠家提。 | J53: firmware-arduino/BOARDS.md（Battery sense for the production board）；firmware-arduino/src/Config.cpp；firmware-arduino/src/Battery.cpp | K53: Spotpear 書面確認量產版：GPIO1（屏幕 DC；本版不接屏幕，可空出來）接電芯正極（保護 IC 之後）100k/100k 分壓、100nF 濾波，屏幕不接該腳；GPIO0 保留給現有的 VDD 低電提醒；最好另把充電芯片 CHRG 接到 GPIO12 或 13。樣板到手後，固件讀到的電芯電壓與萬用表相差 ≤50mV，App（R-41）顯示百分比與充電中。 | L53: ① 取得 Spotpear 的書面確認或改板原理圖 ② 樣板上 3 個電壓點（約 3.5V、3.8V、4.1V）同時量萬用表與固件 log 的毫伏值，誤差都 ≤50mV ③ 插 USB 充電時讀數仍是電芯電壓，不是 5V | P53: [2026-10-05] 新增 [2026-10-06] 2026-10-06：用戶表示不需要精確電量，快沒電時提醒即可，也無法自行焊接。改為軟件方案：讀芯片自身供電（GPIO0 內部上下拉分壓，SupplyMonitor.cpp），讀數跌破基準 95.5% 就亮紅燈並播廣東話提醒。已用強制低電量測試版驗證：提醒能播出、紅燈正常。本任務（硬件分壓）暫緩，等充滿再放電的實測：若提醒太遲或不觸發才向 Spotpear 提出。 [2026-10-07] 仍按 10/06 決定暫緩：等用戶做充滿再放電測試（與 R-17 同一次），看 VDD 低電提醒在關機前多久觸發；太遲或不觸發才向 Spotpear 提改板。已把分壓改板的問題一併放進給 Spotpear 的草稿，方便同一封發出 [2026-10-14] 2026-10-14：用戶決定 App 要顯示電量，恢復本任務（方案 B），與 R-41（方案 A：先顯示高低兩態）並行。改用 GPIO1：GPIO0 已被 SupplyMonitor 的 VDD 檢測佔用（標題仍寫 GPIO0，以驗收標準為準）。R-41 的上報協議已預留 percent / charging，改板後只需改固件的 Battery 設定。量產板訂單是關鍵路徑，要盡快向 Spotpear 提出。
A54: R-17 | B54: R | C54: 1 止血定案 | D54: 硬件 | E54: Spotpear 電池耗盡時插電能否正常開機（供電路徑） | F54: 阻塞 | G54: 未測試 | I54: 裝著沒電的電池插 USB 時，芯片電壓只有純 USB 供電時的 98–99%，說明系統從電池端取電；電池耗盡時板子要等幾分鐘到半小時才出現在 USB 上，還有一次燒錄寫到一半掉電。家長給沒電的玩具插上充電，玩具卻沒有反應或反覆重啟，會以為壞了。 | J54: firmware-arduino/BOARDS.md（Low-battery reminder without battery sense 的 Power path 一段） | K54: 向 Spotpear 確認充電芯片型號、充電電流，以及有沒有負載分擔（power path）。電池完全耗盡後插上 USB，玩具在 2 分鐘內能正常開機並對話；不行的話，要有改板或固件緩解方案（例如掉電重啟後先深睡充電），並寫進說明書。 | L54: ① 取得 Spotpear 的充電電路說明 ② 把電池用到自動關機，插 USB 計時，看幾分鐘後開機並能對話；串口日誌確認沒有反覆 brownout 重啟 ③ 開機後插著用 30 分鐘，運行記錄讀數持續回升到 100%（證明邊用邊充） | P54: [2026-10-06] 新增 [2026-10-07] 等兩件事：(1) Spotpear 回覆充電芯片型號、充電電流、有沒有 power path（問題已草擬給用戶發送）(2) 用戶做一次實物放電：拔 USB 用到自動關機 → 插 USB 計時到能對話 → 插住用 30 分鐘。與 R-16 的放電測試同一次完成。韌體現況：brownout 重啟會補播低電提醒，運行記錄（開機時 Supply log）會記每次重啟原因，可據此判斷有沒有反覆 brownout；『掉電後先深睡充電』的緩解要等測試證明需要才做 [2026-10-08] 2026-10-08 開發板 63:64 插著 USB 時兩次無法解釋的完全斷電重開：09:13:26（崩潰循環中）、10:44:33（閒置、用戶確認沒碰）。都是 USB 先斷線再以 ESP_RST_POWERON 開機，非 brownout；斷電前 6 秒 GPIO0 讀數 99.9% 參考值，屬突然切斷而非緩降（SupplyMonitor 取樣太疏抓不到瞬間）。韌體無法造成 POWERON，指向充電芯片/電池保護/供電路徑，應一併問 Spotpear；放電實測時留意插 USB 閒置時是否也會斷電
A55: P0-17 | B55: P0 | C55: 1 止血定案 | D55: 安全-設定 | E55: 前端的 anon key 必須是公開 key，不可是 secret／service_role | F55: 已完成 | G55: 通過 | H55: 2026-10-12 | I55: 本機 frontend-nextjs/.env.local 的 NEXT_PUBLIC_SUPABASE_ANON_KEY 是 sb_secret_ 開頭的 secret key（等同 service_role）。NEXT_PUBLIC_ 變數會打包進瀏覽器 JS，若線上也這樣設定，任何人都能從網頁拿到可繞過所有 RLS 的 key，P0-02～P0-05 全部失效。線上 .env.production 尚未查證。 | J55: frontend-nextjs/.env.local；線上 frontend-nextjs/.env.production（host aibuddy-dev） | K55: 本機與線上的 NEXT_PUBLIC_SUPABASE_ANON_KEY 都是 sb_publishable_ 開頭或 role=anon 的 JWT；瀏覽器 JS bundle 裡沒有 sb_secret_，也沒有 role=service_role 的 JWT；若線上曾外洩 secret key，已輪換。 | L55: ① 抓線上首頁引用的 /_next/static JS，grep sb_secret_ 為 0；其中 eyJ 開頭的 key 解碼後 role=anon ② 用 bundle 裡的 key GET /rest/v1/users → 42501 或 0 行 ③ 本機 .env.local 同樣檢查 | N55: 線上 2026-10-12（bac24e9）：/login 引用的 13 個 JS + HTML 無 sb_secret_，唯一 key 為 role=anon 的 JWT；② 用該 key GET /rest/v1/users → 42501；③ 本機 10/07 已換 publishable | P55: [2026-10-07] 新增 [2026-10-07] 2026-10-07：線上沒有外洩 secret key，無需輪換。② 要等 P0-02～P0-05 的 migration 在線上套用後再測。
A56: P2-10 | B56: P2 | C56: 1 止血定案 | D56: 工程 | E56: DeepSeek v4 flash 經 OpenRouter 時固定可用的供應商 | F56: 進行中 | G56: 部分通過 | I56: OpenRouter 按延遲自動挑供應商，2026-10-07 實測 DeepSeek v4 flash：DeepInfra 回傳字面 <｜end▁of▁sentence｜>（玩具會唸出來），Venice、Parasail 回空內容（該輪無聲）。線上若用 DeepSeek，孩子會隨機遇到。 | J56: app_settings.voice_stack（provider_order、reasoning_effort）；server/fastapi/models/llm/openrouter.py | K56: 線上用 DeepSeek 時，provider_order 只列實測正常的供應商（例如 StreamLake、SiliconFlow、GMICloud、Novita），並開 reasoning；或線上改用 gemma-4-26b。伺服器遇到空回應或特殊 token 時不把它送去 TTS。 | L56: ① 對 provider_order 裡每個供應商各發 20 次真實 session prompt（含開場白），0 次空內容、0 次 end▁of▁sentence ② 實機開 5 次對話，開場白都正常播出 | N56: ① 16 家供應商各 20 次真實 session prompt（含開場白，串流，order=[x]+allow_fallbacks=false）：建議清單 azure/alibaba/novita/siliconflow/gmicloud 各 20/20，0 空內容 0 特殊 token，首字 p50 1.25/2.33/2.59/2.56/3.25s；只設 order 時 order=[deepinfra] 實際由 Relace 回應（回過 content=None）→ 已改為 allow_fallbacks=false。伺服器端 LLMOutputGuard：pytest 8 項（尾部/跨 chunk 拆開的 token、空回應記警告）全套 203 passed；真實 LLM 串流經 guard 6 角色 12/12 正常、無誤觸發。② 實機 5 次開場白未做 | O56: 58bc82b | P56: [2026-10-07] 新增 [2026-10-07] 2026-10-07 58bc82b（分支 p2-10-provider-pinning，未合併、未部署）。上線後在管理頁設 provider_order=azure,alibaba,novita,siliconflow,gmicloud（或繼續用 gemma）。Azure 20 次中 1 次把孩子叫成「小柔」（prompt 無此名），屬模型偶發，非供應商問題
A57: P2-11 | B57: P2 | C57: 2 內測準備 | D57: 工程 | E57: C3 播放時 async_tcp 觸發任務看門狗重啟 | F57: 已完成 | G57: 通過 | H57: 2026-10-08 | I57: AsyncTCP 在 ESP32 預設把 async_tcp task 加入 5 秒任務看門狗（CONFIG_ASYNC_TCP_USE_WDT=1）。C3 單核，播開場白時 Opus Decode 連續佔用 CPU，async_tcp 超過 5 秒輪不到 → abort 重啟。2026-10-08 開發板實測出現一次（播開場白第 5 秒）。孩子聽回覆時玩具會突然重啟；落在 OTA 試用期內時，好版本會被回滾並記為失敗 | J57: firmware-arduino/platformio.ini（AsyncTCP 3.5.0）；src/Audio.cpp decodeTask 優先級與讓出 | K57: 排程器暫停期間不可呼叫會阻塞的寫入：只在環形緩衝區放得下最大解碼封包（120ms）時才做 CPU 抽樣；AsyncTCP 看門狗保持開啟以便抓到同類問題 | L57: ① Spotpear 開發板連續開機 30 次並播完開場白，串口 0 次 task_wdt / panic ② 20 輪實際對話，串口 0 次 task_wdt | N57: ① 1.3.4 連續重啟 30 次：開場白 30/30、task_wdt 0、panic 0（修正前 19 次 4 次）② 用戶實際對話 20 輪（10:44–10:50）：20 輪都有回應，3 次未完成皆為用戶插話打斷且隨即恢復，短按合併為單輪；task_wdt 0、panic 0；CPU 抽樣照常（每輪 9–13 個） | O57: 8e8b449 | P57: [2026-10-08] 新增 [2026-10-08] 2026-10-08 查明真正原因：不是 async_tcp 被搶 CPU。decodeTask 每輪在 vTaskSuspendAll() 下解碼一個封包量 CPU，解碼寫入已滿的播放環形緩衝區時 writeArray() 等空位，但排程器已停、揚聲器 task 無法消耗 → 卡死，看門狗報 async_tcp（唯一訂閱者）未回報。原驗收（關 AsyncTCP WDT / SoftAP 測試）按錯誤猜測寫，已改；關 WDT 只會把重啟變成永久卡住
A58: R-18 | B58: R | C58: 2 內測準備 | D58: 體驗 | E58: 長按 BOOT 重新配網（開 AIBuddy-XXXX 熱點） | F58: 未開始 | G58: 未測試 | I58: Spotpear 只有 BOOT 一個鍵，韌體沒有重新配網的操作：舊 WiFi 仍在範圍內時，家長換路由器或改密碼後無法讓設備重新開熱點，只能用瀏覽器開 http://<設備IP>/wifi 或恢復出廠 | J58: firmware-arduino/src/main.cpp（按鍵處理、setupWiFi）；src/WifiManager.cpp runSoftAP() | K58: 長按 BOOT ≥5 秒：燈號提示、開出 AIBuddy-XXXX 熱點並保留已存 WiFi 直到新設定保存；短按行為不變；設備密鑰與綁定不受影響；隨 OTA 推出 | L58: Spotpear 實機：已連 WiFi 時長按 5 秒 → 手機見到 AIBuddy-XXXX → 配新 WiFi → 連上並能對話；長按 3 秒不觸發；配網中途放棄 → 120 秒後回到舊 WiFi；雲端 token 照常（不需重新綁定） | M58: R-01 | P58: [2026-10-09] 新增 [2026-10-12] 2026-10-12：配網改用藍牙（R-21），長按 BOOT 改為開啟藍牙配網，不再開 AIBuddy-XXXX 熱點；熱點只保留給開發和運維。驗收標準待 R-21 的韌體方案定了再改。
A59: P2-12 | B59: P2 | C59: 3 封閉內測 | D59: 韌體 | E59: 量產燒錄前加大 app 分區 | F59: 進行中 | G59: 部分通過 | I59: app0/app1 各 2MB，1.0.1 已用 1.66MB（約 79%，剩約 400KB）；分區表 OTA 改不了，韌體超過 2MB 後所有已出貨設備無法再 OTA。板上有 16MB flash，現分區只用約 7MB | J59: firmware-arduino/partition.csv；R-10 出廠腳本 | K59: 新分區表（例如 app0/app1 各 4MB，保留 nvs/otadata 位置）在出廠前定案並寫入出廠腳本；OTA 與回滾在新分區表上照常 | L59: 用新分區表 USB 燒 Spotpear → 雲端 OTA 一次並確認 → 推崩潰版確認回滾；pio 全 env 編譯通過；release_firmware.py 發佈的映像大小 < 新分區 | N59: 62:70（spotpear-ai-toy-p212 原型，現已併入 spotpear-ai-toy）：① 本機 OTA 1.6.1→1.6.2 寫入新 app1，120s 後 confirmed ② 3 秒 abort 的 1.6.3 → PANIC → 回到 1.6.2，ota_failed_version=1.6.3 ③ 崩潰寫入 coredump 14.8KB ④ 資源分區 9 個聲音 504KB/2MB，開機 CRC 63ms，OTA 後照常；損壞/清空 → 退回內建聲音無崩潰 ⑤ pio 全部 18 個 env 編譯通過，映像都在各自 app 槽內（Spotpear 4 個 1.59–1.60MB / 4MB；其他板仍 2MB 槽）；R-21 藍牙探針版 2,326,128 bytes < 4MB ⑥ release_firmware.py 映像 > app 槽即拒發。未做：雲端 OTA 一次（等上 UAT）、出廠腳本寫入資源包（R-10） | O59: 5e9ffce | P59: [2026-10-09] 新增 [2026-10-12] 2026-10-12：藍牙配網（R-21）會令韌體大約多 300KB，2MB 分區不夠。新分區表要按 app 各 4MB 定，並在 11/13 凍結前把藍牙版本編譯一次確認大小。 [2026-10-14] 2026-10-14：用戶要求把配網提示音放進韌體；7 句 16kHz PCM 約 420KB，編進 app 後映像 2,147,728 bytes 超過 2MB 槽，板子在 bootloader 循環重啟（pio 仍報 Flash 99% SUCCESS）。按路線圖改放品牌資源分區。分區表待用戶確認後才算定案。 [2026-10-14] 2026-10-14 用戶定案 partition_16m.csv：nvs 0x9000/20K、otadata 0xe000/8K（不變）、app0 0x10000/4MB、app1 0x410000/4MB、assets 0x810000/2MB（品牌聲音）、nvs_keys 0xa10000/4K（P0-14）、coredump 0xa20000/64K、media 0xa30000/5.8MB（R-14）。spotpear-ai-toy 全部 env 改用此表；R-21 藍牙探針版映像 2,326,128 bytes，在 4MB 槽內。
A60: R-19 | B60: R | C60: 2 內測準備 | D60: 硬件 | E60: 外接按鈕：量產板加 I2C 擴展晶片（TCA9555） | F60: 未開始 | G60: 未測試 | I60: 後續要外接按鈕，但 Spotpear C3 已無空閒 GPIO（0 電壓檢測、1/20/21 屏幕、2 LED、3/4 I2C、5–8/10 I2S、9 BOOT、11 功放）；硬件出貨後 OTA 補不了，GPIO2/8/9 為開機模式腳不宜接按鈕。用戶不焊接，需 Spotpear 改板 | J60: Spotpear 改板（與 R-16 同一封詢問）；firmware-arduino/src/IoExpander.*、BoardConfig.h（Waveshare 已有 TCA9555 讀鍵程式） | K60: 確定按鈕數量與用途；Spotpear 量產版在 I2C（SDA3/SCL4）加 TCA9555 與按鈕接口並給出報價交期；韌體在 Spotpear 上經擴展晶片讀鍵，按鍵功能之後可經 OTA 調整 | L60: 樣板：I2C 掃描見 0x18 與擴展晶片地址；每個按鈕短按/長按都在 log 出現且觸發對應功能；按住任一按鈕上電仍正常開機；連續對話 30 分鐘音訊無雜音 | M60: R-01 | P60: [2026-10-09] 新增
A61: P1-12 | B61: P1 | C61: 2 內測準備 | D61: 私隱 | E61: 設備解綁時的記憶處理：確認、預設保留、可選清除 | F61: 進行中 | G61: 部分通過 | I61: 解綁一按即生效，沒有確認；記憶在解綁時怎麼處理也沒有定義。家長排除故障時重綁可能誤刪孩子的記憶，想刪時又刪不乾淨（設定頁「清除全部」只刪 memory_facts／memory_segments，conversations 原始對話仍在）。 | J61: frontend-nextjs/app/components/Settings/AppSettings.tsx（handleUnbind）、app/actions.ts（unbindDeviceAction）、db/devices.ts（unbindDevice）、Settings/MemorySection.tsx 與 db/memories.ts（清除全部）、server/fastapi/memory/session.py（session 結束時的 consolidation） | K61: ① 按「解綁」先彈出確認對話框，取消則什麼都不改。② 對話框預設保留記憶；「同時清除記憶」要主動勾選，並寫明無法復原。③ 記憶跟設備：鍵是 (user_id, device_id, ip_key)。同一帳號的每台設備各自一份記憶；保留時，同帳號重綁同一台會接著用；換新設備從空白開始（搬記憶交給 R-11）。④ 清除在伺服器端一個交易完成：先刪該設備的 memory_facts、memory_segments、conversations（連帳號的舊 memories），再解綁；任何一步失敗就不解綁，並顯示錯誤。⑤ 其他帳號認領同一台設備，看不到舊記憶（靠 user_id 隔離，不靠刪除成功）。⑥ 設定頁按設備顯示記憶；「清除全部」只清所選設備，連 conversations 一起刪。⑦ 對話中清除，之後的寫入和 consolidation 不會把記憶寫回（devices.memories_revision + trigger）。⑧ 未認領的設備不能對話：/ws/esp32 查到設備沒有 user_id 就在 auth 前以 4401 關閉，即使 24 小時 token 未過期；韌體重新取 token 拿到 202，回到配對狀態。⑨ 解綁時立即中斷該設備正在進行的語音 session。⑩ 網頁語音（playground）沒有設備，不讀也不寫記憶。 | L61: TC1 取消：點解綁 → 對話框 → 取消 → devices.user_id 不變。 TC2 預設保留：記下該設備 memory_facts／memory_segments／conversations 行數 → 不勾清除並解綁 → 行數不變。 TC3 同機重綁：接 TC2，A 重新認領同一台 → 開始對話時 log『Loaded N fact(s)』的 N 等於解綁前；問玩具解綁前講過的事（例如寵物名），能答對。 TC4 換機／多設備：A 認領第二台設備 → 第二台開始對話時是空白（starts cold），第一台的記憶不受影響；設定頁可切換兩台，各自顯示自己的記憶。 TC5 轉讓隔離：A 解綁（保留）→ B 認領同一台 → B 的 session 載入 0 facts；用 B 的登入 token 查三張表拿不到 A 的行；A 的行仍在。 TC6 勾選清除：A 勾選清除並解綁 → 該設備四張表都是 0 行；重綁後開始對話是空白。 TC7 清除失敗不解綁：讓刪除報錯（例如暫時撤銷 service_role 對 conversations 的 DELETE）→ 介面顯示錯誤，devices.user_id 和 memories_revision 不變，記憶行數不變。 TC8 設定頁清除全部：按「Clear all」→ 所選設備的四張表都是 0 行，代數遞增，設備仍綁定。 TC9 越權：B 呼叫 unbind_device／clear_device_memory 對 A 的設備 → 回傳 NULL／報錯；A 的設備和記憶不受影響；anon、authenticated 沒有 EXECUTE 權限。 TC10 對話中清除：玩具對話中勾選清除並解綁 → 對話被中斷 → 等 consolidation 跑完仍是 0 行；用 store 以舊代數寫入三張表 → 全部被資料庫拒絕（HTTP 400 P0001）。 TC11 回歸：pytest server/fastapi/tests 全過；正常對話記憶照常寫入和載入。 TC12 解綁後不重開機不能對話：設備手上有未過期的 token → 解綁 → 再連 /ws/esp32 → auth 前被 4401 拒絕；真機：串口顯示重新取 token 得到 202，回到配對狀態。 TC13 對話中解綁立即中斷：對話中解綁（保留）→ 數秒內 websocket 被關閉（4001），記憶行數不變。 TC14 網頁語音不開記憶：記下該帳號 memory_facts／memory_segments／conversations／turn_metrics 行數 → 在 playground 對話兩輪 → turn_metrics 有新行（證明真的對話了），三張記憶表行數不變；伺服器 log 有 NextJS websocket connected，沒有建立記憶 session（/ws/nextjs 直接傳 memory=None，所以不會印 running without memory）。 | N61: 本機（開發板 DEV636 身份的模擬裝置 + 網頁）：TC1/2/5/6/7/8/10/11/13 通過；TC3 重綁後 log『Loaded 2 fact(s)』；TC4 第二台 starts cold、設定頁可切換；TC9 DB 層 B 解綁回 NULL、清除報錯，anon/authenticated 無 EXECUTE；TC10 舊代數寫入三表皆 HTTP 400、清除後 40 秒仍 0 行；TC12 伺服器端 4401 通過；pytest 214 passed。TC14（2026-10-12，rebase 到 main 後的 p1-12-rebased 8d4b9e2，本機 7861）：/ws/nextjs 以網頁 token 對話兩輪，波波熊有回應 → turn_metrics 0→3，memory_facts／memory_segments／conversations 皆 0→0；log 只有 NextJS websocket connected。真機 62:70（2026-10-12，localall 測試版 → 本機 7861/3014，p1-12-rebased）：按住 BOOT 對話 6 輪，conversations 記下『我隻狗叫豆豆…』；TC12：介面解綁（不勾清除）→ 16:06:51 即斷線，之後每次重連都在 auth 前被拒（device token refused），16:07:02 重新取 token 得 202 並顯示配對碼 UKDM7N；facts 1→1、conversations 14→14、segments 1→2（結束時的摘要）、revision 0。TC3：同帳號重綁 → log『Loaded 1 fact(s)』（有一隻3歲嘅狗叫豆豆）＋2 段摘要；真機問『我隻狗叫咩名』的回答未記錄（用戶決定直接部署）。發現：韌體拿到 202 後 websocket 仍每秒重連一次直到被認領，沒有真正停在配對狀態（不屬 P1-12 伺服器端，另開任務）。 | O61: 8db9d9c | P61: [2026-10-09] 新增：決定（2026-10-09）：記憶跟帳號，不跟 device_id。目前一個帳號只有一個孩子、一台設備，user_id 就是孩子；以後支援一個家長多個孩子時，再加 child_profiles，devices.child_id 指向孩子，記憶鍵改 (child_id, ip_key)，一對一回填。解綁時保留下來的記憶，由 P1-03 的保留期限兜底清理。 [2026-10-09] 補充 ⑧⑨ 和 TC12、TC13（2026-10-09）：現在 /ws/esp32 只驗 token 簽名，不查是否已認領；token 存在玩具 RAM 裡 24 小時不會重新檢查，所以解綁後不重開機仍能以預設角色、無記憶對話。要改 server/fastapi/server.py（/ws/esp32 與解綁時斷線）和 unbindDeviceAction（通知語音伺服器）。本機開發模式（NEXT_PUBLIC_SKIP_DEVICE_REGISTRATION=True）允許未認領設備對話，⑧ 要對這個模式保留同樣的例外。 [2026-10-09] 決定改變（2026-10-09 晚）：用戶決定記憶跟設備，不跟帳號（一個帳號可綁多台，多數是一個孩子一台）。網頁語音不開記憶；舊資料歸到帳號最早認領的設備。分支 p1-12-unbind-memory（建在 multi-device-binding 9c8e106 上），commit 8bb9fb8 + 98faef9，未 push、未部署。 [2026-10-12] 2026-10-12：p1-12-unbind-memory rebase 到 main（0eaa1bf，含多設備與註冊），新分支 p1-12-rebased，worktree ~/project/aibuddy-p112；pytest 214 passed、tsc 通過。TC14 的測試方法改成看 turn_metrics 與三張表，因為 /ws/nextjs 直接傳 memory=None，不會印 running without memory。 [2026-10-12] 2026-10-12：用戶決定不再補測，直接部署。發布分支 p1-12-rebased（main 0eaa1bf ＋ zh-HK 默認 90b6b8a ＋ P1-12 三個 commit ＋ runbook 8db9d9c），runbook docs/deploy/release-2026-10-12-p1-12.sh（取代 multi-device 那份）。 [2026-10-12] 2026-10-12：已部署到生產（8db9d9c，release-2026-10-12-p1-12.sh 第 7 步 19 項自動檢查全過：users.device_id 已刪、三表 device_id/memories_revision 與 trigger、unbind_device/clear_device_memory 只有 service_role 可呼叫、網頁→語音伺服器 /internal 200）。回填：生產 conversations 670/670 掛到設備，memory_facts 0。真機問答（TC3 最後一步）仍待在生產上補問一次。
A62: R-20 | B62: R | C62: 2 內測準備 | D62: 產品 | E62: 孩子資料與角色改成每台設備一份 | F62: 未開始 | G62: 未測試 | I62: 記憶已改成每台設備一份（P1-12），但孩子的名字、年齡、性格，以及角色，仍是每個帳號一份（users.supervisee_*、users.personality_id）。兄弟姊妹各一隻玩具時，其中一隻會叫錯名字、用錯年齡。 | J62: users.supervisee_name／supervisee_age／supervisee_persona／personality_id、server/fastapi/device_registry.py（_ACCOUNT_SELECT）、frontend-nextjs 設定頁的 My Info 與角色選擇 | K62: 每台設備可以設定自己的孩子名字、年齡、性格和角色；沒設定時沿用帳號的預設值。語音伺服器按設備讀取。設定頁每台設備各自編輯。 | L62: ① 帳號綁兩台設備，分別設孩子 A／B → 兩台開場時分別叫 A 和 B。② 只設一台時，另一台沿用帳號預設。③ 換角色只影響所選設備。 | M62: P1-12 | P62: [2026-10-09] 新增：2026-10-09 實作 P1-12 時發現；beta 家庭若有兄弟姊妹各一隻，要在 R-07 前完成。
A63: R-21 | B63: R | C63: 2 內測準備 | D63: 體驗 | E63: 藍牙配網與綁定（取代熱點配網） | F63: 進行中 | G63: 未測試 | I63: 現在配網要手機連 AIBuddy-XXXX 熱點、開 192.168.4.1 網頁，家長體驗差，也不能在 App 裡完成綁定。用戶 2026-10-12 決定改為：App 用藍牙找到設備 → 在 App 裡選 Wi-Fi、填密碼 → 同時綁定；解綁也在 App 裡做。WebView（iOS WKWebView、Android WebView）都不支援 Web Bluetooth，所以藍牙要由原生殼做，網頁經橋接調用。C3 沒有 PSRAM，藍牙協定棧佔約 50–70KB RAM，不能和語音同時開；韌體也會大約 300KB，app 分區已用 79%（P2-12）。 | J63: firmware-arduino/src/WifiManager.cpp（配網）、main.cpp（按鍵、開機流程）；frontend-nextjs 綁定頁；原生殼橋接清單（同事）；partition.csv | K63: ① 設備在「未配網、Wi-Fi 連不上、未綁定、長按 BOOT」時以 AIBuddy-XXXX 名稱廣播藍牙，廣播資料帶品牌，品牌 App 只列出自己品牌的設備。② 設備經藍牙回傳它掃描到的 2.4GHz Wi-Fi 清單，App 讓用戶選擇並填密碼。③ App 經藍牙把 SSID、密碼和綁定票（P0-11）一起交給設備；藍牙通道加密（ESP 標準配網協定 security 1/2 或同等）。④ 設備連上 Wi-Fi 後自己完成認領，App 顯示綁定成功或失敗原因（密碼錯、設備已有主人、票過期）。⑤ 配網期間不啟動音訊；完成後釋放藍牙記憶體再開語音（必要時重開機），對話中最低 heap 不比現在差。⑥ 解綁在 App 內完成（P1-12），解綁後設備進入藍牙待綁定狀態。⑦ SoftAP 熱點配網保留給開發和運維（隱藏觸發方式或編譯開關），量產用戶流程不出現。 | L63: ① Spotpear 實機：iPhone 和 Android 各一部，用 App 從開箱到能對話，不用離開 App、不用手動輸入任何碼 ② 輸錯 Wi-Fi 密碼 → App 顯示錯誤並可重試 ③ 已綁定的設備長按 BOOT 改 Wi-Fi → 綁定不變 ④ 別的帳號在旁邊掃到已綁定的設備 → 不能綁走 ⑤ 解綁後另一帳號可經藍牙綁定 ⑥ 對話 10 分鐘的最低 heap 與改動前對比 ⑦ SoftAP 開發入口仍能配網 | M63: P0-11, P2-12 | P63: [2026-10-12] 新增：2026-10-12 用戶決定。綁定的持有證明由「在藍牙範圍內」提供，取代上一版的熱點綁定碼。橋接清單要改：原生配網由 NEHotspotConfiguration／WifiNetworkSpecifier 改為藍牙（例如 Capacitor BLE 插件或 Espressif 的 ESP Provisioning iOS/Android 庫）。iOS 要 NSBluetoothAlwaysUsageDescription。純瀏覽器只有桌面和 Android 的 Chrome 有 Web Bluetooth，iPhone Safari 沒有，所以網頁版不能配網。 [2026-10-12] 2026-10-12（路線圖）：用戶第一次設定時設備還沒有 Wi-Fi，藍牙配網不能經 OTA 補上，所以必須包含在 11/27 交 Spotpear 量產燒錄的共用出廠韌體裡；藍牙佔用的分區大小要在 11/13 分區表凍結（P2-12）前確定。趕不上的話，量產機只能用 SoftAP 熱點配網，或在玩具廠工位經工廠 Wi-Fi 做一次 OTA。 [2026-10-13] 2026-10-13 量度（分支 r-21-ble-provisioning，測試版 spotpear-ai-toy-bleprobe，Espressif wifi_provisioning BLE + security 1）：韌體 1,585,162 → 2,254,868 bytes（+670KB，超出 2MB app 分區，P2-12 必須改 4MB，partition_4m.csv 已編譯通過）；靜態 RAM 57,0→78,1KB（+21KB）。62:70 實機：開 WiFi STA 後 heap 153.8KB，藍牙廣播中 89.2KB（最大塊 69.6KB）。仍未量：藍牙開著時連 WiFi + HTTPS 的最低 heap（決定綁定結果經藍牙回傳還是由 App 查伺服器）。協定選 Espressif 標準，Neo 可用官方 ESP Provisioning iOS/Android 庫，綁定票走自訂 endpoint。 [2026-10-13] 更正上一條：靜態 RAM 56,988 → 78,092 bytes（+21KB）。
A64: R-22 | B64: R | C64: 2 內測準備 | D64: 多品牌 | E64: 多品牌資料模型：brands 表與設備的品牌 | F64: 不適用 | G64: 未測試 | I64: 三個品牌（馬會快活、政協青年聯會版、AI Buddy）共用一套平台，但資料庫和語音伺服器沒有「品牌」的概念：設備不知道自己屬於哪個客戶，安全規則、語言、資料保留期都不能按客戶設定。 | J64: supabase/migrations（新 migration）；devices 表；server/fastapi/device_registry.py（_ACCOUNT_SELECT）；server/fastapi/language_profiles.py；ips 表（20261007120000_add_ips_modes_styles.sql）；R-10 出廠工位寫入品牌 | K64: ① 新增 brands 表：品牌代號、名稱、允許的 IP、允許的語言、安全規則類型（兒童／成人）、資料保留天數、私隱政策網址、客服聯絡、App 網址；三筆資料：馬會快活、政協青年聯會版、AI Buddy ② devices.brand_key 必填，現有設備回填為 AI Buddy ③ 語音伺服器開 session 時按設備的品牌載入安全規則類型和語言；設備沒有品牌或品牌不存在時以 4401 關閉 ④ anon／authenticated 只能讀 brands 的公開欄位，只有超級管理員能改 | L64: ① 本機 DB 用 BEGIN/ROLLBACK 套 migration：現有設備全部回填，brand_key 沒有 NULL ② pytest：三個品牌各一台模擬設備，log 顯示載入的品牌和規則類型；把設備 brand_key 改成不存在的值 → 4401 ③ authenticated 寫 brands → 42501；內容管理員寫 brands → 拒絕 | P64: [2026-10-12] 新增 [2026-10-12] 2026-10-12 用戶決定三個品牌各自一套獨立部署（資料庫、網頁、語音伺服器都分開，先放同一台伺服器），不再在一個資料庫裡用 brands 表區分品牌。品牌設定改為每套部署的環境變數和品牌包，併入 R-34。
A65: R-23 | B65: R | C65: 3 封閉內測 | D65: 多品牌 | E65: 認領和顯示按品牌分開 | F65: 不適用 | G65: 未測試 | I65: 同一個人可能有兩個品牌的玩具。快活的設備如果能在 AI Buddy App 裡認領，或 App 列出其他品牌的設備，客戶會看到不屬於他們的品牌和角色。 | J65: frontend-nextjs/db/devices.ts（認領）、app/actions.ts、components/Settings/*、middleware（按網址判斷品牌）；R-21 藍牙廣播帶品牌 | K65: ① 網頁按網址判斷品牌（每個品牌一個網址），在伺服器端判斷，不信任前端傳來的品牌 ② 認領時設備的 brand_key 必須等於目前網址的品牌，否則不認領，並提示「這部玩具要用 XX App 設定」；R-21 的藍牙清單已按品牌過濾，伺服器端再檢查一次 ③ 設定頁、記憶頁只列出目前品牌的設備 ④ 帳號共用：同一個 email 在不同品牌的 App 都能登入，各自只看到自己品牌的設備 | L65: ① 快活設備在 AI Buddy 網址認領 → 被拒並顯示提示；在快活網址 → 成功 ② 一個帳號綁兩個品牌各一台：兩個網址各只看到一台 ③ 直接呼叫認領 action 並帶別的品牌參數 → 無效 | M65: R-22 | P65: [2026-10-12] 新增 [2026-10-12] 2026-10-12：每套部署只有自己品牌的帳號和設備，認領和顯示自然分開。保留的防呆（設備品牌和本套不符就拒絕）併入 R-34 ⑧，綁定隔離由 R-35 ② 驗證。
A66: R-24 | B66: R | C66: 3 封閉內測 | D66: 多品牌 | E66: 設備只能用自己品牌的角色 | F66: 未開始 | G66: 未測試 | I66: 多 IP 第一期所有 IP 都可切換。但快活是馬會授權產品：快活的設備不能切到其他品牌的角色，其他品牌也不能用快活的角色。 | J66: brands 表的允許 IP；personalities.ip_key；server/fastapi（session 載入角色處）；設定頁角色選擇；admin 頁 | K66: ① 每套部署只上架本品牌允許的 IP 下的角色（允許的 IP 來自品牌設定，R-34）② 伺服器端檢查：設備的角色不屬於本品牌允許的 IP 時，改用本品牌的預設角色並記警告 ③ 快活的設備鎖定快活 IP，不能切換 | L66: ① 快活那套的角色頁只見快活角色 ② 直接改資料庫把快活設備的角色設成其他 IP 的角色，下一個 session 用回快活預設角色並有警告 log ③ 快活 App 沒有切換 IP 的入口 | M66: R-34 | P66: [2026-10-12] 新增 [2026-10-12] 2026-10-12：改為按部署分開（R-34），不再依賴 brands 表。
A67: R-25 | B67: R | C67: 2 內測準備 | D67: App | E67: 網頁的品牌主題系統 | F67: 未開始 | G67: 未測試 | I67: 三個客戶要不同的 UI，但後面要共用。如果品牌名稱和顏色寫死在元件裡，每加一個品牌都要改程式碼，三個 App 會分叉。 | J67: frontend-nextjs/app/globals.css（CSS 變數）、tailwind.config.ts、app/layout.tsx；新增 frontend-nextjs/brands/<品牌>/（主題、圖示、文案、功能開關） | K67: ① 每個品牌一個資料夾：主題 token（顏色、字體、圓角）、logo 和圖示、文案、功能開關；首頁、上手流程、角色頁可以有品牌版本，其餘頁面共用 ② 由部署的環境變數選品牌（每套部署一個品牌，見 R-34），伺服器端渲染的第一屏就是對的主題，不閃爍 ③ 共用元件裡沒有品牌名稱和寫死的品牌顏色 ④ 加一個品牌只需要加資料夾、設定和一套部署，不用改共用元件 | L67: ① 本機用三個品牌的環境變數各啟動一次：顏色、logo、文案、頁面標題都對 ② grep 共用元件：沒有「快活」「AI Buddy」等品牌字眼，也沒有寫死的品牌顏色 ③ 複製一個測試品牌資料夾，不改程式碼就能顯示 ④ tsc 和 next build 通過 | P67: [2026-10-12] 新增 [2026-10-12] 2026-10-12：品牌改由部署的環境變數決定，不再按網址判斷（三套分開部署，R-34）。
A68: R-26 | B68: R | C68: 2 內測準備 | D68: App | E68: 原生殼與網頁的橋接清單 | F68: 未開始 | G68: 未測試 | I68: 殼由同事做，我們不控制殼的程式碼。網頁需要的原生能力如果沒有先講好介面，雙方會各做各的，到送審前才發現對不上。 | J68: 新增 docs/app-bridge.md；frontend-nextjs（呼叫殼的 JS 介面，以及普通瀏覽器裡的替代做法） | K68: ① docs/app-bridge.md 列出每項能力的 JS 介面、參數、回傳和錯誤：藍牙配網與綁定（R-21：掃描、Wi-Fi 清單、送 SSID／密碼／綁定票）、原生 Google／Apple 登入回傳 id token、推送 token 登記、麥克風權限、App 內刪除帳號入口、深層連結、殼告訴網頁自己的品牌和版本 ② 做殼的同事確認 ③ 偵測不到殼時（普通瀏覽器），每項都有替代做法或明確提示 | L68: ① 同事書面確認（用戶確認） ② 普通瀏覽器打開：每項功能有替代或提示，console 沒有錯誤 ③ 在頁面注入假的殼介面，逐項跑成功和失敗兩條路徑 | P68: [2026-10-12] 新增
A69: R-27 | B69: R | C69: 2 內測準備 | D69: App | E69: App 內登入：驗證碼、原生社交登入、刪除帳號 | F69: 未開始 | G69: 未測試 | I69: WebView 裡 Google 不允許 OAuth（disallowed_useragent）；確認信和重設密碼的連結會開到系統瀏覽器，回不到 App；Apple 規定有 Google 登入就要有同等的私隱登入（4.8），能註冊就要能在 App 內刪除帳號（5.1.1(v)）。 | J69: frontend-nextjs/app/(auth-pages)/login、components/GoogleLoginButton.tsx（現在用 signInWithOAuth）、app/actions.ts；Supabase Auth 設定（Email OTP、Apple provider） | K69: ① email 註冊、登入、重設密碼都改用 App 內輸入驗證碼，不靠郵件連結 ② 在殼裡，Google 和 Apple 登入由殼原生完成，網頁用 signInWithIdToken 換 session；普通瀏覽器保留現有做法 ③ 提供 Sign in with Apple ④ 設定頁可以刪除帳號：解綁全部設備並清除記憶（沿用 P1-12 的清除流程）、刪除帳號資料，完成後登出 | L69: ① iOS 和 Android 殼內：email 驗證碼註冊、登入、重設密碼，全程不離開 App ② 殼內 Google、Apple 登入成功並拿到 session ③ 刪除帳號後：auth 用戶不存在，設備變回未認領，該帳號的 memory_facts／memory_segments／conversations 都是 0 行 ④ 普通瀏覽器登入照常 | M69: R-26 | P69: [2026-10-12] 新增：signup-admin-accounts／release-multi-device 分支正在改註冊和登入（Split sign-up from login），這項要等它們合併後再做，避免衝突。
A70: R-28 | B70: R | C70: 3 封閉內測 | D70: App | E70: 三個 App 的殼：品牌版本與測試版 | F70: 未開始 | G70: 未測試 | I70: 三個 App 要同時交付。殼由同事做，要追蹤三個版本的名稱、圖示、bundle id、推送和藍牙權限，並發出 TestFlight 和 Google 內部測試版。 | J70: 殼的專案（同事負責）；frontend-nextjs/brands/<品牌>/ 的圖示和名稱；docs/app-bridge.md | K70: ① 一個殼專案出三個 App：名稱、圖示、啟動畫面、bundle id 各自不同，各自打開自己品牌的網址 ② 推送通知可用（至少：設備第一次上線、低電提醒） ③ iOS 寫好藍牙和麥克風的權限說明（NSBluetoothAlwaysUsageDescription 等） ④ TestFlight 和 Google 內部測試都有三個 App 的測試版 | L70: ① 同一部手機同時裝三個 App，各自顯示正確品牌 ② 每個 App 收到一則推送 ③ 測試人員從 TestFlight 和 Google 內部測試安裝成功（用戶確認） | M70: R-25, R-26 | P70: [2026-10-12] 新增
A71: R-29 | B71: R | C71: 3 封閉內測 | D71: App | E71: AI Buddy App（品牌 C）頁面 | F71: 阻塞 | G71: 未測試 | I71: W4 開始的內部測試要用它。由現有網頁改成品牌 C；兒童版還要有家長控制的入口。 | J71: frontend-nextjs/app/home、components/Settings、components/Onboarding；frontend-nextjs/brands/<AI Buddy>/ | K71: 用品牌 C 主題完成：註冊登入、藍牙配網與綁定（R-21）、選角色、孩子資料（R-20）、記憶、家長鎖（P1-09）和每日上限（R-12）的入口；所有頁面在手機寬度可用 | L71: ① 新帳號在殼內從註冊到第一次對話走一遍 ② 每個頁面 375px 寬沒有橫向捲動 ③ 內部測試第一週回報的阻塞問題全部處理 | M71: R-25, R-34 | P71: [2026-10-12] 新增 [2026-10-13] 2026-10-13 用戶決定：AI Buddy（品牌 C）延到 1/15 之後，本項不卡 1/15 出廠；AI Buddy 啟動時再開。
A72: R-30 | B72: R | C72: 3 封閉內測 | D72: App | E72: 快活 App（品牌 A）頁面 | F72: 未開始 | G72: 未測試 | I72: 快活提案向馬會承諾了「綁定會員」「記得甚麼，看得見」「一鍵忘記」和三語，這些頁面現在都沒有。會員綁定用我們的帳號還是馬會 SSO 未定（Q12）。 | J72: frontend-nextjs（品牌 A 的首頁、上手流程、記憶頁）；frontend-nextjs/brands/<快活>/；components/Settings/MemorySection.tsx | K72: ① 上手流程：開機 → 藍牙配網 → 綁定會員（稱呼、生日、語言、喜好） ② 記憶頁列出快活記住的每一項，每項可單獨刪除，另有「全部忘記」 ③ 語言可選粵語、普通話、英文，下一句對話就換語言 ④ 用快活主題，頁面沒有兒童版字眼（家長、孩子） | L72: ① 綁定會員後，開場白用對稱呼和語言 ② 刪除一項記憶後，再問相關問題不再提起；「全部忘記」後該設備的 memory_facts 0 行 ③ 三種語言各對話一輪 ④ grep 品牌 A 的頁面和文案：沒有「家長」「孩子」 | M72: R-25, R-34, Q12 | P72: [2026-10-12] 新增
A73: R-31 | B73: R | C73: 3 封閉內測 | D73: App | E73: 政協青年聯會版 App（品牌 B）頁面 | F73: 未開始 | G73: 未測試 | I73: 用戶是成人會員；角色、語言、內容都還沒有，要客戶提供（Q13）。 | J73: frontend-nextjs（品牌 B 頁面）；frontend-nextjs/brands/<政協青年聯會>/ | K73: ① 用品牌 B 主題完成：註冊登入、藍牙配網與綁定、綁定會員、角色、記憶查看與刪除、語言 ② 頁面沒有兒童版字眼 ③ 角色和內容按客戶提供的資料設定 | L73: ① 新帳號從註冊到第一次對話走一遍 ② 客戶看過頁面和角色後確認（用戶代為確認） ③ grep 品牌 B 的頁面和文案：沒有「家長」「孩子」 | M73: R-25, R-34, Q13 | P73: [2026-10-12] 新增 [2026-10-13] 2026-10-13 用戶決定：政協青年聯會版沿用快活的成人版流程，只換外觀和角色，不另寫頁面。
A74: R-32 | B74: R | C74: 2 內測準備 | D74: App | E74: 開發者帳號：馬會、政協青年聯會、AI Buddy | F74: 未開始 | G74: 未測試 | I74: Apple 不接受同一個開發者上架三個同模板的 App（4.2.6、4.3），馬會和政協青年聯會要用自己的機構帳號。申請 D-U-N-S 再加 Apple 審核要 1–3 週，所以 W1 就要開始。 | J74: Apple Developer Program、Google Play Console；各品牌的 D-U-N-S 編碼 | K74: ① Apple 和 Google Play 各三個機構帳號都開好（AI Buddy 用我們自己的） ② 我方以開發成員身份加入馬會和政協青年聯會的帳號，權限足夠上傳和送審 ③ 各品牌的私隱政策網址和客服聯絡已經提供 | L74: 用戶確認：六個帳號都能登入，我方成員能在每個帳號建立 App 記錄 | P74: [2026-10-12] 新增：W1 就要通知馬會和政協青年聯會開始申請；最遲 11/13（W5）完成。
A75: R-33 | B75: R | C75: 4 量產出貨 | D75: App | E75: 三個 App 送審並通過 | F75: 未開始 | G75: 未測試 | I75: 純網頁殼會被拒（4.2）；聖誕前後審核變慢；被拒要預留 1–2 輪修改。殼過審之後介面在網頁裡，再改介面不用重新送審。 | J75: App Store Connect、Google Play Console；上架資料（截圖、私隱標籤、審核說明） | K75: 12/11 前三個 App 在 Apple 和 Google 都審核通過（先不公開，分階段發佈）；審核說明附測試帳號和設備使用說明；私隱標籤和實際收集的資料一致 | L75: ① App Store Connect 和 Play Console 三個 App 都是已核准（截圖或用戶確認） ② 私隱標籤逐項對照資料流向（P1-05） | M75: R-27, R-21, R-28, R-29, R-30, R-31, R-32 | P75: [2026-10-12] 新增
A76: R-34 | B76: R | C76: 3 封閉內測 | D76: 多品牌 | E76: 每個品牌一套獨立部署（資料庫、網頁、語音伺服器） | F76: 未開始 | G76: 未測試 | I76: 三個 B2B 品牌要求資料分開，現在只有一套（elatoai.hkqft.com）。分開後運維變三倍：migration、備份、升級、監控都要做三次，漏一套就會版本不一致；三套 Supabase 放同一台伺服器，記憶體可能不夠。 | J76: server/fastapi/docker-compose.ghcr.yml、frontend-nextjs/docker-compose.ghcr.yml、伺服器上的自建 Supabase compose；docs/deploy/ 的 runbook；DNS | K76: ① 三套放在同一台伺服器：每套有自己的 Supabase（資料庫、帳號、儲存）、網頁和管理後台、語音伺服器，以及各自的容器、資料卷、內部網絡、子網域和密鑰（JWT secret、service key、DEVICE_JWT_SECRET、AI 供應商 API key）② 現有 elatoai.hkqft.com 改為品牌 C AI Buddy，現有帳號、設備、資料不變；馬會快活、政協青年聯會版各開一套新的 ③ 三套用同一組映像、同一個版本；品牌只由環境變數和品牌包決定（取代 R-22 的 brands 表）：品牌代號、名稱、允許的 IP、語言、安全規則類型（兒童／成人）、資料保留天數、私隱政策網址、客服、App 網址；程式碼裡沒有按品牌名稱分支的判斷 ④ 每套的設定由同一個模板生成，密鑰集中保存 ⑤ 一個腳本按品牌循環做 migration、部署、冒煙測試（登入、語音對話、OTA 檢查），三套一次跑完；發佈順序固定為先 AI Buddy，觀察一天後再上另外兩套 ⑥ 三套各自備份，監控集中在一個面板，告警寫明品牌 ⑦ 關掉三套都用不到的 Supabase 服務 ⑧ 防呆：設備記錄的品牌和本套不符時，語音伺服器以 4401 拒絕 | L76: ① 腳本部署三套後，三個子網域的網頁、/healthz、登入、冒煙測試全部通過 ② 三個資料庫的 migration 版本一致 ③ 用品牌 A 的設備 token 連品牌 B 的語音伺服器 → 4401；用品牌 B 的 key 讀不到品牌 A 的資料 ④ 在品牌 C 建的帳號，在品牌 A 的網頁登入不了 ⑤ 停掉其中一套，另外兩套照常對話 ⑥ 三套同時運行時記錄伺服器的記憶體和 CPU，留有餘量 ⑦ grep 程式碼沒有寫死的品牌名稱判斷 | P76: [2026-10-12] 新增：2026-10-12 用戶決定：資料庫、網頁、語音伺服器都按品牌分開；三套先放同一台伺服器；現有線上環境變成 AI Buddy 那套。
A77: R-35 | B77: R | C77: 3 封閉內測 | D77: 韌體 | E77: 韌體按品牌連線：伺服器網址在出廠時寫入 | F77: 未開始 | G77: 未測試 | I77: 伺服器網址現在寫死在韌體裡（Config.cpp 的 elatoai.hkqft.com）。三個品牌各自一套伺服器後，同一個韌體要按品牌連到不同網址；設備第一次連網前沒有機會 OTA，所以這段必須進 11/27 交給 Spotpear 的出廠映像。 | J77: firmware-arduino/src/Config.cpp（ws_server、backend_server）；出廠工位腳本（R-10） | K77: ① 韌體從 NVS 讀語音伺服器和後端網址，取 token、OTA、藍牙綁定後的認領、/ws 全部用它；出廠工位寫入品牌時一併寫入該品牌的網址 ② NVS 沒有網址時不連任何正式伺服器，停在出廠模式並在序列埠提示 ③ 網址用我們控制的固定子網域，以後搬機房只改 DNS ④ 用戶改不了網址：只有出廠工位經序列埠寫入 ⑤ 開發用的 -localws／-localall 環境照常可用 | L77: ① 兩片板分別寫入品牌 A、C 的網址，各自連上自己那套，完成對話和 OTA 檢查 ② 寫入 A 網址的板，用 C 的 App 綁定失敗 ③ 清空 NVS 後開機停在出廠模式，不連正式伺服器 ④ 記錄 11/27 交 Spotpear 的映像版本，確認包含這段 | M77: R-34 | P77: [2026-10-12] 新增：2026-10-12 新增：三個品牌分開部署（R-34）的直接結果。
A78: R-36 | B78: R | C78: 2 內測準備 | D78: 體驗 | E78: 未認領的設備停在配對狀態，不再每秒重連 websocket | F78: 進行中 | G78: 部分通過 | I78: 解綁或從未認領的設備拿到 202 後，fetchDeviceToken 只回傳 false，但 websocket 已啟動、帶著舊 token 每秒自動重連，每次都在 auth 前被 4401 拒絕，直到被認領（P1-12 真機 62:70 2026-10-12 發現）。浪費電和流量、伺服器 log 被洗版，C3 上每次重連都做一次 TLS。藍牙配網（R-21）也需要設備有一個明確的「待綁定」狀態。 | J78: firmware-arduino/src/WifiManager.cpp:102（202 分支）、startSessionIfReady()；src/Audio.cpp:1374（authTokenRejected） | K78: ① 拿到 202 或 websocket 被 4401 拒絕後，設備停掉 websocket 自動重連，進入待綁定狀態（燈號可分辨）。② 待綁定時只按退避（5 秒起、上限 PROVISION_BACKOFF_MAX）呼叫 generate_auth_token，不開 websocket。③ 被認領後下一次輪詢拿到 200，在 10 秒內（加退避）自動開 websocket 並能對話，不用重開機。④ 已綁定設備網絡斷線重連的行為不變。⑤ 隨 OTA 推出。 | L78: 真機 62:70（localall）：① 介面解綁 → 序列埠 60 秒內沒有 websocket 連線嘗試，語音伺服器 log 沒有連續 4401；只見 generate_auth_token 按退避重試 ② 重新認領 → 不按鍵、不重開機，設備自動連上並可對話 ③ 已綁定時拔掉路由器 30 秒再接回 → 照常重連 ④ 對照改動前，待綁定 5 分鐘的伺服器請求數 | M78: P1-12 | N78: 補充 2026-10-15（1.7.5，含 R-36）：已綁定時兩次 Wi-Fi 切換各斷網 9–11 秒，都自動重連並重新 auth，沒有停在暫停狀態；30 秒斷網仍未做 | O78: 1bd85ac | P78: [2026-10-12] 新增：2026-10-12 從 P1-12 真機測試拆出。 [2026-10-12] 2026-10-12 韌體已改（分支 r-36-unclaimed-idle，以 mygithub/main 為基礎）：token 在 auth 前被拒就暫停 websocket（networkTask 不再呼叫 webSocket.loop），只有 startSessionIfReady 拿到新 token 才恢復；202 時清掉舊 token、標記未認領，閒置時 LED 慢閃洋紅（有螢幕的板顯示 NOT PAIRED）。spotpear-ai-toy 和 -localall 都編譯通過（Flash 75.6%）。真機測試未做：62:70 未接上，Mac 當時不在公司網絡。 [2026-10-15] rebase 衝突在 networkTask：R-36 的暫停條件和 R-41 的 reportPower() 都保留（reportPower 自己檢查連線）。分支未推送。
A79: R-37 | B79: R | C79: 3 封閉內測 | D79: 體驗 | E79: 網頁設定玩具的 Wi-Fi：查看、新增、刪除 | F79: 進行中 | G79: 部分通過 | I79: 玩具連上 Wi-Fi 後設定熱點就關閉，用戶沒有入口再加第二個 Wi-Fi（例如手機熱點、親戚家）；現在只能在同一網絡打開 http://<板子IP>/wifi，而且那一頁不用登入。用戶 2026-10-13 參考競品的 Network Management 頁，要在網頁做。 | J79: firmware-arduino/src/WifiManager.cpp、Audio.cpp（websocket 訊息）；server/fastapi/server.py（/ws/esp32 轉送）；frontend-nextjs 設定頁 | K79: ① 設定頁顯示玩具在線／離線、目前 Wi-Fi 和訊號、已記住的 Wi-Fi 清單（只有名稱，不顯示密碼）② 在線時可新增 Wi-Fi（輸入或從玩具掃描到的清單選）、刪除 Wi-Fi；不能刪除正在使用的那個 ③ 經 /ws/esp32 轉送：伺服器先確認是設備主人；密碼不寫入資料庫、不寫入日誌 ④ 新增不自動切換網絡；目前 Wi-Fi 消失時按訊號選，或由家長按「改用這個」（⑦）；清單標示「連過／未連過」⑤ 上限 8 個 ⑥ 韌體改動經 OTA 推出 ⑦ 已記住、未在使用的 Wi-Fi 可按「改用這個」：玩具斷開目前網絡改連它，最多 20 秒，要連上我們的伺服器才算成功；失敗就自動連回原網絡，頁面顯示「連不上 X，已回到 Y」；切換中頁面顯示切換中，玩具重新連上後刷新；成功後標示連過 | L79: ① 網頁新增 Wi-Fi B，關掉 A → 玩具自動改連 B ② B 密碼打錯 → 玩具留在 A，B 標示未連過 ③ 嘗試刪除目前 Wi-Fi → 被拒 ④ 另一帳號呼叫同一接口 → 403 ⑤ 搜尋資料庫和伺服器日誌，找不到測試密碼 ⑥ 玩具離線時頁面顯示離線，新增按鈕停用 ⑦ 62:70：對已存的手機熱點按「改用這個」→ 玩具改連熱點並在 30 秒內重新在線、頁面顯示熱點為目前 Wi-Fi；熱點關掉時按「改用這個」→ 20 秒後回到原網絡、頁面顯示失敗原因；對目前 Wi-Fi、未存的 SSID、別人的設備 → 被拒 | N79: 62:70（1.7.4/1.7.5，2026-10-15）：① 熱點關掉後醒來改連 HKQF - Guest 並上線（發生在醒來重開時）⑦ Use 按鈕、確認框、『Moving to…』；熱點關著時按 Use → 11 秒內頁面顯示『couldn't find lee’s iPhone nearby. It's back on HKQF - Guest』，串口 not_found → Back on Guest → 重連。過程中發現並修正：驅動殘留上一次的『找不到』令連回原網絡立即失敗並掉進 SoftAP（joinFor 6 秒內不信失敗，tryConnect 同用）。pytest 272 passed | O79: 3c180cd | P79: [2026-10-13] 新增：時間表（project-schedule.xlsx「Jacky 開發與測試」）排在 W4 11/2–11/6，和快活網頁核心一起；內部測試的家庭要加家裡的 Wi-Fi。 [2026-10-13] 2026-10-13 應 Jacky 要求從 W4 提前開始。韌體：上限 8 個、NVS apOk%d 記錄連過、經 /ws/esp32 收 status/add/delete/scan、不刪不改目前 Wi-Fi、Wi-Fi 指令不印串口、修 delWifi 計數 bug。伺服器：device_wifi.py＋/internal/device_wifi（含 peek），密碼只轉送不留存。網頁：我 > 裝置 > Network > Wi-Fi（Figma C4），deviceWifiAction 檢查擁有者。剩真機測試 ①②（需 62:70 刷 -localall＋兩個真實網絡）與 OTA。 [2026-10-15] 2026-10-15 用戶決定：加「改用這個 Wi-Fi」（⑦），④ 改為新增不自動切換、可由家長手動切換。起因：62:70 實測加了 iPhone 熱點也無法讓玩具改用。另：離線一律顯示「睡著了」會誤導（63:64 已 6 天未上線仍叫人按按鈕），待改為按上次上線時間分開提示。 [2026-10-15] 測試中修了原有 bug（a4 之後第二個 commit）：驅動在沒連上的網絡斷開時不發事件，WiFi.status() 留著上次的『找不到』，新嘗試一開始就被當失敗；1.7.4 切換失敗後連不回 Guest 並掉進 SoftAP，tryConnect() 也同樣。joinFor() 改為 6 秒後才相信失敗，tryConnect() 共用。雲端韌體同樣有這 bug。另：開機時 tryConnect() 挑最強的網絡但不檢查能否到伺服器，62:70 開機連上到不了 Mac 的熱點後一直卡著（見 P2-22 ④ 或另開任務）。分支 r-37-wifi-switch 未推送。 [2026-10-15] 更正上一條備註：stale『找不到』的修正是 22d7674（切換功能本身是 3c180cd）。 [2026-10-15] 2026-10-15：⑦ 的成功切換在本機測不到（熱點到不了 Mac 上的伺服器），留到部署上 UAT 或雲端後用 iPhone 熱點測一次。 [2026-10-15] 未做：⑦ 熱點開著但到不了伺服器（no_internet）→ 退回；⑦ 成功切換（需第二個能到 Mac 的網絡）；② 密碼打錯。發現：開機挑最強訊號、不檢查能否到伺服器，62:70 開機時連上 iPhone 熱點就一直取不到 token（本機伺服器到不了），建議併入 P2-22 ④ 或另開。分支 r-37-wifi-switch（3c180cd + 修正）未合併、未推送。
A80: R-38 | B80: R | C80: 3 封閉內測 | D80: 產品 | E80: 公仔出廠鎖死所屬 IP，綁定時顯示該 IP 頭像 | F80: 未開始 | G80: 未測試 | I80: 同一個 App 會同時賣兩種以上鎖死的公仔。若 IP 只靠這套部署裡有哪些角色來區分，一個帳號上的兩隻公仔會共用同一個角色，其中一隻會說成另一個 IP 的人。 | J80: supabase：devices.ip_key、devices.personality_id\nserver/fastapi/device_registry.py\nfrontend-nextjs 認領、My Devices、Playground\nadmin 的 IP image_url\n出廠登記（R-10） | K80: 共用韌體映像不含某個 IP。出廠工位按 MAC 把 ip_key 和該 IP 的預設角色寫進 devices；板子不報 IP，解綁不清這欄，家長和 App 改不了。ip_key 為空的開發板維持現在的行為。認領前和 My Devices 用 ips.image_url 顯示這隻公仔的頭像；帳號上的 Current Character 仍是角色圖。角色在 devices.personality_id，資料庫拒絕把別的 IP 的角色寫到這台上。一個帳號可以同時綁兩種 IP 的公仔，各說各的角色；Playground 從某台進去，只列該 IP 的角色。語音伺服器讀這台自己的角色。孩子資料仍在帳號。記憶仍是（帳號、設備、ip_key），另一隻聽不到。 | L80: ① 登記兩塊 MAC，分別寫入 IP-A、IP-B 和各自的預設角色。兩塊板燒的是同一份韌體。查 devices，ip_key 和 personality_id 正確。 ② 認領清單在按下認領前顯示該 IP 的名稱和 image_url；image_url 為空時用佔位圖。認領後 My Devices 卡片是這張圖，Current Character 仍是角色圖。 ③ 同一帳號再認領另一 IP 的板。兩台設備卡片各顯示自己的 IP 頭像。 ④ 用家長身份更新 devices.ip_key，被拒絕。把 personality_id 改成另一個 IP 的角色，被外鍵拒絕。 ⑤ 從 IP-A 的設備進 Playground，只看到 A 的角色，沒有換到 B 的入口。A 的板開 session，用的是 A 的角色；B 的板不受影響。 ⑥ 解綁 A 再被另一個帳號認領，ip_key 仍是 A，頭像不變。A 的記憶不會出現在 B 的 session。 ⑦ ip_key 為空的開發板仍可選任何角色，session 照現在的帳號角色走。 ⑧ 只更新韌體（OTA 或重燒 app），devices.ip_key 不變。 | M80: P0-11 | P80: [2026-10-13] 新增：2026-10-13 定案：同一個 App 裡兩種鎖死公仔是一定的。IP 在出廠登記時按 MAC 寫入，不編進韌體。
A81: P2-13 | B81: P2 | C81: 2 內測準備 | D81: 運維-後台 | E81: Admin 後台改成分組側欄（新頁面先用示例數據預覽） | F81: 進行中 | G81: 部分通過 | I81: 原本頂部膠囊分頁只放得下 6 頁，之後要加設備、客服、OTA、出廠、用量、審計等頁面放不下；新頁面要先有固定位置和樣子，再逐頁接上真實數據。 | J81: frontend-nextjs/app/components/Admin/AdminDashboard.tsx frontend-nextjs/app/components/Admin/adminPages.ts frontend-nextjs/app/components/Admin/preview/（示例數據在 previewData.ts） | K81: 6 個現有分頁（Model、Latency、Characters、IPs、Accounts、Admins）在新側欄照常使用，讀寫真實數據；內容管理員只看到 Characters 和 IPs；預覽頁和規劃頁只有超級管理員看到，並有橫幅寫明示例數據、按鈕不能用；每頁有 #hash 可直接打開；手機寬度沒有橫向捲動。 | L81: ① tsc 通過 ② 用略過登入的測試頁檢查超級管理員和內容管理員兩種視角、桌面和手機寬度、#hash 直接打開 ③ 用真實超級管理員帳號登入 /admin，逐頁確認讀到真實數據（Model 讀到 OpenRouter 模型目錄、Latency 有記錄、Characters 可編輯並保存）④ 用內容管理員帳號登入，側欄只有 Characters、IPs | N81: ① tsc --noEmit 通過 ② 略過登入的測試頁（另一份副本、獨立 .next）：超級管理員 15 頁、內容管理員只見 Characters／IPs；1360px 與 375px 均無橫向捲動（scrollWidth=clientWidth=375）；#audit 直接打開正確；③④ 未做：需真實帳號登入 /admin | O81: 77fc4f7 | P81: [2026-10-14] 新增
A82: P1-13 | B82: P1 | C82: 2 內測準備 | D82: 安全-權限 | E82: PLACEHOLDER | F82: 不適用 | G82: 未測試 | I82: x | P82: [2026-10-14] 新增 [2026-10-14] 2026-10-14 新增任務時指令打錯而誤建的空白行，沒有內容，不代表任何工作。
A83: P2-14 | B83: P2 | C83: 2 內測準備 | D83: 運維-後台 | E83: Admin 設備頁：每台玩具的狀態、韌體與基本操作 | F83: 已完成 | G83: 通過 | H83: 2026-10-15 | I83: 內部測試有 20 台在外面，玩具連不上時只能直接查資料庫或靠家長描述；NVS 被清空後要手動刪 device_secrets 那一行。數據大多已在 devices 表（last_seen_at、firmware_version、ota_failed_*、claimed_at），只是沒有地方顯示。 | J83: frontend-nextjs/app/components/Admin/preview/DevicesPreview.tsx（換成真實數據） devices、device_secrets 表 server/fastapi/server.py（在線狀態：device_wifi.snapshot 已有 online，需開一個只讀的內部接口） | K83: 列出全部設備，可按 MAC、設備名、家長 email 搜尋，按狀態和韌體篩選；顯示在線／離線（取自語音伺服器）、上次上線、韌體版本、OTA 失敗版本、綁定帳號與時間、出廠鎖定的 IP；單台詳情可做「重置設備密鑰」「強制解綁」，兩者都要填原因並寫入審計記錄（P1-10）；不顯示任何對話、記憶或孩子資料（Q7）；只有超級管理員能讀。 | L83: ① 開發板 62:70 開機 → 1 分鐘內顯示在線；拔電 → 顯示離線 ② 對開發板「重置設備密鑰」→ device_secrets 該行刪除，板子重開後重新登記成功 ③「強制解綁」一台測試設備 → 設備回到配對狀態，審計表多一筆含原因 ④ 用內容管理員 JWT 讀 devices 管理接口被拒 | M83: P1-10, P2-13 | N83: 真機 62:70（2026-10-15，分支 hw-test-1015 = dev+P2-16，-localall 1.7.0，本機網頁 3230 + 語音 7870）：① 開機 → 設備頁 Online、-67 dBm、1.7.0；板子停在 bootloader 約 38 秒後語音伺服器判離線（uvicorn ping 超時），頁面 0 台在線 ② 重置設備密鑰 → device_secrets 行刪除，板子重開印『Device secret issued and stored』並連上，行恢復 ③ 強制解綁 → 板子拿 202（配對碼 UKDM7N），語音伺服器拒絕連線；兩項審計各 1 筆含操作者與原因 ④ 內容管理員/anon → 42501（10-14 探測腳本） | O83: 1d31bb0 | P83: [2026-10-14] 新增 [2026-10-14] devices.ip_key 未有（R-38），IP 欄暫顯示「未鎖定」。部署要三件一起：migration、語音伺服器（/internal/devices_presence）、網頁。在線只代表有語音連線，睡眠和關機都算離線。 [2026-10-15] 頁面在分頁不可見時不輪詢（設計如此），可見時立即刷新。測完已用 SQL 把 62:70 綁回 multi-device-test@example.test。
A84: P2-15 | B84: P2 | C84: 3 封閉內測 | D84: 運維-後台 | E84: Admin 總覽頁：在線、用量、成本與待處理事項 | F84: 未開始 | G84: 未測試 | I84: 每天要逐頁看才知道有沒有問題；內部測試期間需要一眼看到在線數、今日成本和要處理的設備。 | J84: frontend-nextjs/app/components/Admin/preview/OverviewPreview.tsx（換成真實數據） | K84: 顯示：在線玩具／已綁定、今日對話輪數、今日成本與每台成本、待處理數；近 14 天活躍設備與輪數趨勢；韌體版本分佈；待處理清單（OTA 回滾、用量異常、供應商錯誤率），每項可跳到對應頁；最近管理操作取自審計記錄。所有數字與設備頁、用量頁一致。 | L84: 用 SQL 直接算同一天的在線數、輪數、成本和韌體分佈，與總覽頁數字逐項對照一致；製造一台 OTA 回滾（ota_failed_version）→ 出現在待處理並能跳到該設備 | M84: P2-14, P2-09 | P84: [2026-10-14] 新增
A85: P2-16 | B85: P2 | C85: 2 內測準備 | D85: 運維-OTA | E85: OTA 分批推送與後台發佈頁 | F85: 已完成 | G85: 通過 | H85: 2026-10-15 | I85: 現在設為 current 的版本會一次推給該板型的所有設備；3,000 台出貨後，一個壞版本會同時推給全部設備。發佈只能在 Mac 上用 release_firmware.py，要手動貼 service key。分批推送只改伺服器決定哪台收到 ota，不用改韌體，所以不受 11/27 韌體定版的時限限制，但必須在出貨後第一次 OTA 之前完成。 | J85: frontend-nextjs/app/components/Admin/preview/OtaPreview.tsx（換成真實數據） frontend-nextjs/app/api/generate_auth_token/route.ts（回傳 ota 的地方） firmware_releases 表、firmware-arduino/tools/release_firmware.py | K85: 後台可上傳韌體（伺服器算 SHA-256、寫 firmware_releases）、填說明、設為 current；推送分階段：白名單 MAC → 10% → 50% → 100%，按 MAC 雜湊穩定分組；回滾率超過 5% 即自動暫停（2026-10-14 拿走「同一台重啟 3 次」，見 P2-19）；顯示每個版本已更新、回滾台數與回滾設備清單；顯示 app 分區用量（P2-12）；每個發佈操作寫入審計記錄。 | L85: 本機 Supabase 模擬 20 台：① 10% 階段只有約 2 台拿到 ota，重複請求結果不變 ② 讓 2 台回報 failed_version → 自動暫停，其餘不再拿到 ota ③ 推到 100% 全部拿到 ④ 開發板 62:70 實機走一次白名單階段並確認新版本 ⑤ 審計表有每次階段變更 | M85: P0-13, P2-14, P1-10, P2-17, P2-18, P2-19, P2-20, P2-21 | N85: ④ 真機 62:70（2026-10-15）：USB 刷 1.7.0（開機印 aibuddy-build;kind=dev;…;version=1.7.0）→ release_firmware.py publish --dev 1.7.1 → 後台白名單加 62:70、改白名單階段、設為 current → 按 BOOT 喚醒：取 token 200、下載 12.8s、重開進 app1，09:39:36 連上語音伺服器；09:42 重開 → 『Firmware 1.7.1 on app1』無 probation、Up to date；頁面『Rolling out · Whitelist』運行 1 台、回滾 0；審計 5 筆（發佈、白名單、階段、1.6.2 取消 current、1.7.1 設 current）。①②③⑤ 見 P2-17～P2-21 模擬 20 台 | O85: e0d7ac6 | P85: [2026-10-14] 新增 [2026-10-14] 2026-10-14 開分支 p2-16-ota-rollout（worktree ../aibuddy-p216，從 dev cac98aa）；拆成 P2-17～P2-21 五項子任務，本項的測試方法即整體驗收（含 62:70 實機白名單）。 [2026-10-14] 2026-10-14 用戶決定提前到第 2 階段，現在開始做 [2026-10-14] 2026-10-14 用戶決定拿走「同一台重啟 3 次即暫停」，原因見 P2-19 [2026-10-14] 部署清單：① migrations 20261014190000、200000、210000、220000（依序，在 10-14 release 的 7 個之後）② 網頁 image ③ nginx 網頁 location 加 client_max_body_size 16m，curl 上傳 2MB 不得 413 ④ 韌體 BUILD_INFO 隨下一版韌體出，之前的版本仍用 release_firmware.py 發佈。分支 p2-16-ota-rollout 6 個 commit，未合併 dev、未推送 [2026-10-15] 附帶：一開始本機 current 是 1.6.2（以舊 IP/端口編譯），1.7.0 開機就被推 1.6.2，裝上後連不上，試用期內重開即回到 1.7.0（非崩潰，判定會再試），回滾路徑實機正常。之後用 SQL 暫停 1.6.2。用腳本發佈的新版本要重新載入 OTA 頁才出現。
A86: R-39 | B86: R | C86: 3 封閉內測 | D86: 生產 | E86: Admin 出廠登記頁：匯入 MAC 清單、指定公仔、查看自檢結果 | F86: 未開始 | G86: 未測試 | I86: 3,000 台的 MAC、公仔和 IP 不可能逐台手動改資料庫；工位登記結果（R-10）要有地方看，才知道哪批哪台沒通過。要在 12/14 量產前跟工位腳本一起用小批量試產跑通。 | J86: frontend-nextjs/app/components/Admin/preview/FactoryPreview.tsx（換成真實數據） 新表：出廠批次與每台 QC 記錄 R-10 工位腳本的登記接口 | K86: 可匯入 Spotpear 的 MAC 清單 CSV（MAC、批次、日期），重複或格式錯誤的行跳過並列出；每批顯示已匯入、已寫密鑰、自檢通過、自檢失敗、未開始的數量；可整批為未寫密鑰的板子指定公仔（IP）；顯示工位回傳的每台自檢結果（咪、喇叭、燈、按鍵、Wi-Fi）與失敗原因；寫入密鑰後公仔鎖定，只有超級管理員能在此改，家長端不能改（R-38）；可匯出失敗清單；只看到分配給本部署的板子；匯入和指定都寫入審計記錄。 | L86: ① 匯入 300 行 CSV，其中 3 行重複、1 行格式錯 → 新增 296 行並列出 4 行 ② 為 20 台指定公仔後，工位腳本處理其中 10 台 → 進度與 QC 記錄正確，已寫密鑰的不能再改公仔 ③ 匯出失敗清單內容與 QC 記錄一致 | M86: R-38, P1-10 | P86: [2026-10-14] 新增
A87: R-40 | B87: R | C87: 4 量產出貨 | D87: 營運 | E87: Admin 客服查詢頁：查帳號、名下設備與最近事件 | F87: 未開始 | G87: 未測試 | I87: 家長來電時要能用一個搜尋找到帳號和玩具；R-11 要求的報修、診斷、換機流程現在沒有工具，只能直接改資料庫。 | J87: frontend-nextjs/app/components/Admin/preview/SupportPreview.tsx（換成真實數據） auth.users（service role，只在伺服器端讀） devices、users 表 | K87: 可用 email、MAC 或設備名稱後四位查到帳號；顯示註冊時間、登入方式、家長鎖與使用上限設定、名下設備（狀態、韌體、上次上線）和最近的系統事件（連線失敗、OTA、綁定、Wi-Fi 變更）；動作：解綁、換機（解綁舊機、綁新機、記憶搬到新設備，按 P1-12 的定案）、重發登入驗證碼、刪除帳號及資料；每個動作要填原因並寫入審計記錄；不顯示對話、記憶、孩子的性格描述（Q7）。 | L87: 按 R-11 演練一次：用測試帳號模擬家長報修 → 在客服頁找到帳號和設備、看到事件 → 換機到另一台測試設備，新設備保留記憶 → 審計表有每一步；刪除測試帳號後，其對話、記憶和綁定都已刪除 | M87: P2-14, P1-10, P1-12 | P87: [2026-10-14] 新增
A88: P1-14 | B88: P1 | C88: 3 封閉內測 | D88: 兒童安全 | E88: Admin 內容安全頁：審核事件只按類別統計 | F88: 未開始 | G88: 未測試 | I88: P1-01 審核層會記錄攔截事件，但沒有地方看；某台設備或某個角色攔截突然變多時沒人知道。 | J88: frontend-nextjs/app/components/Admin/adminPages.ts（目前是規劃頁 safety） P1-01 的審核事件表 | K88: 按日顯示輸入和回覆被攔截的次數，只按類別（暴力、性、個人資料、自我傷害等），不顯示原文（Q7）；可按角色和設備看攔截率；單台設備單日攔截數超過門檻時出現在總覽的待處理；只有超級管理員能讀。 | L88: 在測試設備上觸發每個類別各 3 次 → 頁面計數與審核事件表一致；資料庫和頁面回應中都找不到觸發用的原文 | M88: P1-01, P2-13 | P88: [2026-10-14] 新增
A89: R-41 | B89: R | C89: 2 內測準備 | D89: 產品 | E89: App 顯示玩具電量狀態（低電量提示） | F89: 已完成 | G89: 通過 | H89: 2026-10-14 | I89: 家長在 App 看不到玩具快沒電，只能靠玩具自己播提醒；玩具多數時間休眠，伺服器記憶體裡的狀態一重啟就沒了。 | J89: firmware-arduino/src/Audio.cpp（reportPower）；server/fastapi/device_power.py；supabase/migrations（devices.battery_*）；frontend-nextjs 設備頁 | K89: 玩具每次連上語音伺服器並收到 auth 後上報一次電量狀態，狀態改變時再報；伺服器寫入 devices.battery_low / battery_percent / battery_charging / battery_at；App 設備頁顯示「電量正常／電量低，請充電」和最後更新時間，玩具離線時仍顯示最後已知狀態；沒有電量檢測的板不顯示電量。Spotpear 板只有高低兩態（R-16 改板後才有百分比）。 | L89: ① 單元測試：伺服器只接受 power 訊息的合法欄位並寫入對應 MAC 的 devices 行 ② 62:70 用 SUPPLY_LOW_RATIO_OVERRIDE 強制低電量：本地 DB battery_low=true、App 顯示電量低 ③ 改回正常固件重連：battery_low=false、App 顯示正常 ④ 玩具斷線後 App 仍顯示最後狀態和時間 ⑤ 其他用戶讀不到這幾欄（RLS） | N89: ① pytest 33 passed；真 PATCH 本地 Supabase ② 62:70 刷 p212+R-41 強制低電 build（SUPPLY_LOW_RATIO_OVERRIDE=1.05）→ 串口 [WSc] power low:true，本地 DB battery_low=t ③ 刷回正常 1.6.2 → low:false，DB=f ④ App 讀 DB：低電紅標+Please charge+更新時間、72% 充電中、未上報不顯示 ⑤ 他人帳號 0 行、authenticated UPDATE 被拒。62:70 已還原為原 p212 build | O89: 42b4437 | P89: [2026-10-14] 新增 [2026-10-14] 2026-10-14：rebase 後合併入 dev（42b4437）。migration 改名 20261014153000_device_battery.sql，避開同時間戳的 admin_accounts；powerSent 重置改到收到 auth 時。未部署。
A90: P2-17 | B90: P2 | C90: 2 內測準備 | D90: 運維-OTA | E90: P2-16 ① 分批推送的數據表：推送階段、白名單、每台安裝結果 | F90: 已完成 | G90: 通過 | H90: 2026-10-14 | I90: firmware_releases 只有 is_current 一個開關，沒地方記推到哪個階段、是否暫停，也沒有每台對每個版本的安裝記錄，自動暫停和後台統計都無從算起。 | J90: supabase/migrations/（新 migration）、firmware_releases、devices | K90: firmware_releases 加推送狀態（階段：白名單／10%／50%／100%、白名單 MAC、暫停與原因、階段變更時間）；新表記錄每台對每個版本：首次下發、下發次數、確認（回報版本＝該版）、回滾（failed_version＝該版）；只有超級管理員能讀，寫入只經 service role 或帶審計的 admin RPC；舊的 is_current 發佈照常可用（視為 100%）。 | L90: 本機 Supabase BEGIN/ROLLBACK 套用兩次無錯；經 REST 用 GoTrue 真實登入：anon 讀新表 → 42501，內容管理員讀新表 → 0 行（RLS，與 firmware_releases 一致），anon／內容管理員／超管寫新表、改發佈階段、呼叫 ota_note_* → 42501，超管可讀；現有 release_firmware.py promote 後 current 版本照常被 token 路徑的查詢選中 | M90: P0-13 | N90: migration 20261014190000 BEGIN/ROLLBACK 套用兩次無錯並已套用本機；行為：預設 100%、promote 記 stage_changed_at，7 種壞值（25%、小寫/空字串/NULL MAC、暫停缺原因等）全被 check 擋；ota_note_offer 1→2→3，report 正確標 running/failed、別板型不影響，刪發佈連帶刪記錄；審計 5 筆含 'test-board 9.9.9' 標籤。REST 13/13：超管可讀、內容管理員 0 行、anon 42501，三種身份寫入/改階段/呼叫 ota_note_offer 皆 42501。release_firmware.py promote spotpear-ai-toy 1.6.2 成功，token 查詢仍選 1.6.2，審計記 2 筆（actor 空＝service role） | O90: c510e02 | P90: [2026-10-14] 新增：2026-10-14 分支 p2-16-ota-rollout（worktree ../aibuddy-p216） [2026-10-14] 2026-10-14 用戶決定提前到第 2 階段，現在開始做 [2026-10-14] 測試方法修正：內容管理員讀取在 RLS 下是 200 + 0 行而非 42501，保護效果相同（看不到任何行），寫入一律 42501 [2026-10-14] commit 在分支 p2-16-ota-rollout（rebase 後 9f44e32 → 8675970），未合併到 dev、未部署 [2026-10-14] commit 再次 rebase 後為 c510e02（分支 p2-16-ota-rollout）。之後分支不再為追蹤表 commit rebase，hash 到合併時才會變
A91: P2-18 | B91: P2 | C91: 2 內測準備 | D91: 運維-OTA | E91: P2-16 ② 按 MAC 雜湊穩定分組決定哪台收到 ota | F91: 已完成 | G91: 通過 | H91: 2026-10-14 | I91: 現在 current 版本一次推給同板型全部設備，3,000 台出貨後一個壞版本會同時打到所有人。 | J91: frontend-nextjs/lib/ota.ts（recordReportAndDecide）、frontend-nextjs/app/api/generate_auth_token/route.ts | K91: 白名單階段只有名單內 MAC 拿到 ota；10%／50%／100% 按 MAC 雜湊（加版本作鹽）穩定分組，同一台重複請求結果不變，升階段時已在組內的不會掉出；暫停時一律不下發；每次下發與結果寫入 ① 的記錄；不用改韌體。 | L91: 單元測試：10,000 個隨機 MAC 在 10%／50% 的比例誤差 < 1 個百分點，同 MAC 重複呼叫結果一致；本機腳本模擬 20 台 POST /api/generate_auth_token：10% 階段約 2 台拿到 ota，重複請求名單不變，100% 全部拿到 | M91: P2-17 | N91: node --test lib/otaRollout.test.mjs 6/6：10,000 隨機 MAC 在 10%/50% 誤差 < 1 個百分點、同 MAC（含大小寫/空白）結果一致、升階段只增不減、白名單各階段都在、不同版本選不同的 10%。tsc --noEmit 通過。分支 dev server（3216）+ 本機 Supabase 模擬 20 台（板型 p218-sim，連跑兩次 9/9）：白名單階段只有 1 台、重複不變；10% 拿到的正是雜湊預測的那組（2–5 台含白名單），重複不變；50% 包含 10% 全部；暫停 → 0 台且下載映像 404，恢復 → 200；100% → 除已更新和已回滾的 2 台外 18 台；每台下發次數與記錄一致；運行中/已回滾正確標記；審計 6 筆對應 6 次變更。真 spotpear-ai-toy（預設 100%）回報 1.6.1 → 仍拿到 1.6.2。測試數據已清除 | O91: e57529d | P91: [2026-10-14] 新增 [2026-10-14] 2026-10-14 用戶決定提前到第 2 階段，現在開始做
A92: P2-19 | B92: P2 | C92: 2 內測準備 | D92: 運維-OTA | E92: P2-16 ③ 回滾過多時自動暫停推送 | F92: 已完成 | G92: 通過 | H92: 2026-10-14 | I92: 壞版本推到 10% 後沒人盯著就會繼續推；板子在試用期內斷電重啟會重試安裝（最多 2 次），伺服器要從同一台反覆下發看出問題。 | J92: frontend-nextjs/lib/ota.ts、① 的每台記錄 | K92: 已下發的設備中回滾率 > 5% 即自動暫停該版本並記下原因（台數少的階段第一台回滾就暫停）；暫停後其餘設備不再拿到 ota、映像不再提供下載；已在運行該版本的設備不受影響；自動暫停寫入審計記錄（操作者為空、paused_by 為空、原因以 Auto-paused 開頭）；只能由超級管理員恢復，恢復後要有新的回滾才會再判斷。 | L92: 本機模擬 20 台（分支 dev server + 本機 Supabase）：100% 階段 1 台回滾（5%）不暫停；第 2 台回滾（10%）→ 暫停、原因含回滾率，其餘 18 台不再拿到 ota；已運行新版的設備照常；審計多一筆、actor 為空；恢復後保持恢復，第 3 台回滾再暫停；白名單 2 台中 1 台回滾 → 立即暫停；anon 呼叫 ota_maybe_pause → 42501 | M92: P2-18 | N92: migration 20261014200000 BEGIN/ROLLBACK 套用兩次無錯並已套用本機。模擬 20 台連跑兩次 12/12：1/20 回滾不暫停、其餘 18 台照常；2/20 → 'Auto-paused: 2 of 20 boards rolled back (10%)'，其餘 0 台拿到 ota；已運行的設備記為 running 且不再下發；審計 1 筆 actor 空；恢復後 17 台拿到、保持恢復，第 3 台回滾 → 'Auto-paused: 3 of 20 (15%)'；白名單 2 台中 1 台回滾 → 50% 立即暫停、另一台不再下發；anon 呼叫 ota_maybe_pause → 401/42501。測試數據已清除，spotpear-ai-toy 1.6.2 仍 100% 未暫停 | O92: 9500d50 | P92: [2026-10-14] 新增 [2026-10-14] 2026-10-14 用戶決定提前到第 2 階段，現在開始做 [2026-10-14] 2026-10-14 用戶決定拿走「同一台下發/下載 3 次未確認即暫停」：實測中途斷開的下載 3 次有 1 次被當成完整下載（伺服器只知道寫進緩衝區），線上映像經 nginx 和 Cloudflare 會被整個先收下，伺服器永遠看到下載完成；按下發次數計會把網絡不穩（C3 TLS）誤判成壞版本。韌體已把崩潰和試用期內斷電重裝 2 次（OTA_MAX_TRIES）都回報成回滾，由回滾率規則處理。
A93: P2-20 | B93: P2 | C93: 2 內測準備 | D93: 運維-OTA | E93: P2-16 ④ 從後台上傳與發佈韌體（取代手貼 service key） | F93: 已完成 | G93: 通過 | H93: 2026-10-14 | I93: 發佈只能在 Mac 上跑 release_firmware.py，還要在 Terminal 貼伺服器上的 service key；多品牌後每套各要一次。 | J93: frontend-nextjs/app/api/admin/（新的上傳 route）、firmware storage bucket、firmware-arduino/tools/release_firmware.py | K93: 只有超級管理員能上傳；伺服器自己算 SHA-256 與大小，檢查是 ESP32 映像、大小不超過 app 分區（P2-12）、版本號沒發佈過、不是開發版；寫入 firmware storage 和 firmware_releases（含說明），上傳後狀態為草稿，不會下發；上傳、刪除草稿都寫審計記錄；release_firmware.py 照常可用。 | L93: 本機：超管上傳 spotpear-ai-toy build → firmware_releases 新行 SHA-256 與本地 shasum -a 256 一致，任何設備都還拿不到 ota；重複版本、超出分區、非 ESP32 檔、localall build 各被拒；內容管理員上傳 → 403；審計表有上傳記錄 | M93: P2-17, P1-10 | N93: node --test lib/firmwareImage.test.mjs 8/8（合成映像：dev build、無標記、未知板、晶片不符、非映像、截斷/損壞、超 4MB 拒；超 2MB 只警告）。分支 dev server + 本機 Supabase 端到端 16/16（GoTrue 真實登入的 cookie）：超管上傳 9.9.0 release build → 201 草稿（is_current f、rollout 0%），DB SHA-256 = 檔案、storage 原樣；審計 insert 記該超管；設備仍只拿到 current 1.6.2；已有 1.0.2 → 409；localall → 422 dev build；4MB+16 → 422；9MB → 413；PNG → 422；舊 1.6.1 映像（無標記）→ 422 指向 release_firmware.py；內容管理員上傳/刪除 → 403；未登入 → 401；刪 current → 409；超管刪草稿 → 行和映像都刪、審計 delete 記該超管。release_firmware.py list 照常。測試帳號與數據已清除 | O93: ebe8dc9 | P93: [2026-10-14] 新增 [2026-10-14] 2026-10-14 用戶決定提前到第 2 階段，現在開始做 [2026-10-14] 做法：韌體 OTA.cpp 加 BUILD_INFO 字串（kind=release/dev;board;version），伺服器從映像讀板型和版本，不用手填；DEV_MODE/LOCAL_WS_HOST/LOCAL_BACKEND_HOST/AUDIO_SELFTEST 為 dev。只有加了標記之後編譯的韌體能從後台上傳，之前的仍用 release_firmware.py。部署注意：① 網頁的 nginx location 很可能仍是預設 1MB 上限（/supabase-api/ 已改 16m），上傳 1.6MB 映像會 413，部署時要加 client_max_body_size 16m 並用 curl 驗證 ② 依賴 P1-10 的審計表（本機已有，線上隨 10-14 release 部署）
A94: P2-21 | B94: P2 | C94: 2 內測準備 | D94: 運維-OTA | E94: P2-16 ⑤ 後台 OTA 頁換成真實數據與操作 | F94: 已完成 | G94: 通過 | H94: 2026-10-15 | I94: OTA 頁現在是示例數據（OtaPreview），看不到哪個版本推到哪、誰回滾了。 | J94: frontend-nextjs/app/components/Admin/preview/OtaPreview.tsx → 新的 OtaTab.tsx、adminPages.ts（ota 改為 live） | K94: 按板型列出版本：狀態（草稿／推送中＋階段／暫停＋原因／現行／舊版）、已更新／目標台數、回滾台數、大小、發佈時間、說明；單一版本可編輯白名單、推進下一階段、暫停／恢復、撤下；回滾設備清單可點進設備頁；顯示 app 分區用量（P2-12）；每個操作要確認並寫審計記錄；只有超級管理員可見；375px 無橫向捲動。 | L94: 本機瀏覽器：上傳 → 白名單加 62:70 → 推進 10% → 50% → 100%，每步台數和模擬 20 台的結果一致；③ 觸發暫停後頁面顯示原因並可恢復；審計頁看到每次階段變更；內容管理員看不到該頁 | M94: P2-18, P2-19, P2-20, P2-14 | N94: 10-14 模擬 20 台全部通過（見上次）；2026-10-15 真機補做：OTA 頁對 1.7.1 白名單加 62:70（UI MAC 欄）→ 存檔確認框 → 『Narrow to Whitelist』確認 → Make current（用戶點）→ 62:70 安裝並確認，頁面顯示 Rolling out · Whitelist、運行 1、回滾 0；每步一筆審計。依賴 P2-14 已完成 | O94: e0d7ac6 | P94: [2026-10-14] 新增 [2026-10-14] 2026-10-14 用戶決定提前到第 2 階段，現在開始做 [2026-10-14] 未完成：依賴 P2-14 的真板測試未做；測試方法中『白名單加 62:70』以模擬設備代替，實機一步歸 P2-16 ④，等板子到手一起做
A95: P2-22 | B95: P2 | C95: 3 封閉內測 | D95: OTA/韌體 | E95: 改服務器網址也不失聯：語音網址由後端下發、後端網址可遷移、已確認韌體長期連不上時自救 | F95: 進行中 | G95: 部分通過 | I95: OTA 和取 token 都走後端（backend_server），語音伺服器網址（ws_server/ws_path，現為 elatoai.hkqft.com/fastapi/ws/esp32）寫死在韌體裡。日後改 FastAPI 網址就要先推新韌體，而新韌體在試用期內連不上新網址會被回滾；後端網址一改，現有板子連 OTA 都收不到，只能 USB 救。另一個缺口：已確認（過了試用期）的韌體如果之後一直連不上服務器但不崩潰，682f3b4 的連續崩溃切槽不會觸發，板子收不到修復。 | J95: firmware-arduino/src/Config.cpp（ws_server、ws_port、ws_path、backend_server、CF_CA_bundle）、src/OTA.cpp（otaBootCheck、usableOtherSlot）、取 token 的流程；frontend-nextjs 的 /api/generate_auth_token（回應加 voice_url / backend_url）；R-35 的 NVS 網址 | K95: ① /api/generate_auth_token 的回應帶 voice_url（wss 主機＋端口＋路徑，來自後端環境變數）；韌體用它連 /ws，並把最後一次成功的值存進 NVS；改 FastAPI 網址只改伺服器設定，不需新韌體 ② 回應沒有 voice_url（舊後端）或新網址連不上時，退回 NVS 上次成功的值，再退回出廠／編譯時的預設值 ③ 後端網址可遷移：回應可帶 backend_url；韌體先存為候選，下次開機用新網址取 token 成功才正式替換，失敗就繼續用舊網址；舊網址在遷移期內保持可用（runbook 寫明保留多久） ④ 已確認的韌體若連續 N 次開機（預設 10 次、跨度至少 24 小時，計數存 NVS）Wi-Fi 已拿到 IP 卻取不到 token：先依次試 NVS、出廠的後端網址；仍失敗且另一個槽可用，就切到另一個槽一次，並在下次連上時把本版本報為失敗 ⑤ 純斷網（拿不到 IP、路由器沒外網）不計入 ④ ⑥ 新網址的證書必須鏈到 CF_CA_bundle 裡的根（GTS Root R4、ISRG Root X1）；換主機或離開 Cloudflare 前先查證書鏈，runbook 寫明 ⑦ 只接受 https 的 backend_url 和 wss 的 voice_url，主機須在韌體內允許的網域後綴之下，防止後端被冒充時把板子引去別處 | L95: ① 62:70（-localall）：後端環境變數把 voice_url 改到另一個端口的語音伺服器，重開機 → 連上新的，不需刷機 ② 把 voice_url 改成連不上的地址 → 退回 NVS 上次成功的值，照常對話 ③ backend_url 指向第二個本地後端 → 下次開機在新後端取 token 成功並替換；指向不存在的地址 → 繼續用舊的，對話不中斷 ④ 停掉後端、保留 Wi-Fi，把 N 臨時調小（例如 3 次、跨度 0）→ 第 N 次開機切到另一個槽，恢復後端後該版本被記為失敗 ⑤ 路由器拔掉外網線重開 N 次 → 不切槽 ⑥ 一塊雲端板上用同樣流程驗證 ①（改 elatoai 那套的 voice_url）⑦ 下發不在允許網域後綴之下的網址 → 韌體拒用並在序列埠提示 | M95: R-35 | N95: 後端部分（分支 p2-22-server-urls）：node --test lib/deviceServerUrls.test.mjs 5/5、tsc 0 錯誤。worktree dev server 3222 + 本機 Supabase，兩塊假板（02:22:…:01/02）：已認領 200 帶 voice_url + backend_url；未認領 202 只帶 backend_url；DEVICE_VOICE_URL=ws://fastapi:7860/… → 不發、日誌記錯誤；兩個變數都不設 → 兩個欄位都不帶；生產值 → wss://elatoai.hkqft.com/fastapi/ws/esp32、https://elatoai.hkqft.com。測試數據已清除 | O95: c0f0e29 | P95: [2026-10-14] 新增 [2026-10-14] 2026-10-14 用戶要求：日後改 FastAPI 網址，板子仍要能 OTA 並連上。① 後端改動可隨時部署；②–⑦ 的韌體部分必須在 11/27 交 Spotpear 的出廠映像之前完成，出廠後才加的話，已出貨的板子靠 OTA 也能拿到，但前提是當時的網址還連得上。 [2026-10-15] 未完成：韌體部分（①② 使用 voice_url 並在 NVS 記上次成功的值、③ 候選 backend_url、④⑤ 連續 10 次開機連不上就切槽、⑦ 允許的網域後綴）未開始，要用 62:70 實機測；runbook（③ 舊網址保留多久、⑥ 證書鏈檢查）未寫。部署：.env.production 加 DEVICE_VOICE_URL、DEVICE_BACKEND_URL；舊韌體會忽略這兩個欄位，可以先上後端。分支未合併 dev、未推送 [2026-10-15] 2026-10-15（用戶決定只記備註、不另開任務）：開機時 tryConnect() 挑訊號最強的已存網絡，但不檢查能否到伺服器。若該網絡本身上不了網（熱點關了流動數據、要網頁登入的酒店 Wi-Fi、寬頻斷了），玩具每次開機都會卡在那裡，即使另一個已存網絡可用。做 ④ 時一併考慮：連上後取不到 token 就改試下一個已存網絡。62:70 連著到不了本機伺服器的 iPhone 熱點時出現過，但那是本機測試環境造成的，雲端不會。
A96: P2-23 | B96: P2 | C96: 3 封閉內測 | D96: OTA/韌體 | E96: 無感 OTA：閒置入睡前在背景下載，下次喚醒時生效 | F96: 未開始 | G96: 未測試 | I96: 現在 OTA 在開機時進行：開機取 token 時後端說要更新，板子就下載、重開，之後才開語音。2026-10-15 在 62:70 實測（本機 HTTP、1.52 MB），從開機到新版本能對話約 15 秒，其中下載 12.8 秒；雲端經 HTTPS／Cloudflare 未量，應更長。孩子按開機後要等這麼久玩具才說話，會覺得壞了。 | J96: firmware-arduino/src/OTA.cpp（otaCheckAndUpdate、installImage）、src/Audio.cpp（enterSleep、閒置睡眠 IDLE_SLEEP_SECONDS）、src/SupplyMonitor.cpp（低電判斷）；伺服器不用改（offer 仍隨 /api/generate_auth_token 回來） | K96: ① 開機只記下 offer，不下載、不重開；照常開 websocket 對話 ② 閒置準備入睡時（websocket 已關，C3 只有一條 TLS），如有未裝的 offer 就下載到另一個槽並校驗 SHA-256，成功後才入睡；下次喚醒的重開即進新版本，試用期與回滾照舊 ③ 下載中按 BOOT（孩子要說話）→ Update.abort，立即回到對話，下次入睡再試；不算失敗次數 ④ 電量低（supplyLow／電池低）不下載 ⑤ 已下載但未生效時再開機，不重複下載（slot 已設為下次啟動） ⑥ 有 offer 超過 N 天（預設 3 天）都沒機會在入睡時裝，就退回開機時安裝 ⑦ 下載期間 LED 和平時入睡一致，不播提示音 ⑧ 可選：映像 gzip 壓縮下載（10-15 實測 1,592,176 → 999,108 bytes），固件邊下邊解壓 | L96: 62:70（-localall）：① 發佈新版本後開機 → 串口記下 offer，3 秒內連上語音並播開場白，無下載 ② 閒置至入睡 → 串口顯示下載與 SHA-256 通過後才 Sleeping；按 BOOT 喚醒 → 新版本 on 新槽、probation，120 秒後 confirmed，從按鍵到開場白的時間和沒有更新時相差 ≤ 2 秒 ③ 入睡下載中按 BOOT → 1 秒內回到對話，新槽不生效，下次入睡重下成功 ④ 強制低電 build → 入睡時跳過下載 ⑤ 已下載未生效時拔電重開 → 進新版本、不重下 ⑥ 把 N 調成 0 → 開機即安裝（舊行為）⑦ 量一次雲端 HTTPS 下載時間（等雲端可測時） | M96: P2-16 | P96: [2026-10-15] 新增 [2026-10-15] 2026-10-15 用戶要求。最好趕上 11/27 交 Spotpear 的出廠映像；趕不上也能經 OTA 推出，只是那一次更新仍要開機時等。依賴 P2-16（分批推送，已完成）。
A97: P2-24 | B97: P2 | C97: 2 內測準備 | D97: 韌體-音訊 | E97: 麥克風上行改用 IMA ADPCM（減少 4 倍頻寬） | F97: 進行中 | G97: 部分通過 | I97: 上行仍是從上游 ElatoAI 沿用的未壓縮 16kHz PCM（256 kbps）。2026-10-13 在 51:16:c0 實測：iPhone 熱點上發送最長卡 330ms、說話時 heap 13–20KB、最低 788B、約 5 輪斷 3 次；同板在 HKQF - Guest 20 輪 0 斷、最低 40.9KB。內部測試的家庭有人會用手機熱點。 | J97: firmware-arduino/src/Audio.cpp（麥克風上行發送、websocketExtraHeaders）；server/fastapi/esp32_transport.py（RawPCMFrameSerializer 的輸入）、server.py（/ws/esp32 接受連線）；Python 3.11 內建 audioop，3.13+ 用 audioop-lts | K97: ① 新韌體上行用 IMA ADPCM（64 kbps），每幀帶解碼狀態（預測值＋步長索引），掉幀或重連後下一幀即可正確解碼 ② 連線時以 header 聲明編碼；伺服器據此解碼成 16kHz PCM 再交給 STT；沒有聲明的舊韌體照舊當 PCM ③ 韌體編碼與伺服器解碼位元一致（同一算法）④ 編碼 CPU < 2%、不增加延遲 ⑤ 語音辨識品質與 PCM 相當 | L97: ① C 編碼器與 Python audioop 交叉驗證：同一段 PCM，韌體算法編碼 → audioop 解碼 = audioop 自己編碼再解碼的結果 ② pytest：帶 header 的連線解碼正確、無 header 照舊 PCM、壞幀不崩潰 ③ 62:70（Guest）：粵語對話 10 輪，STT 文字與 PCM 版本相當；上行位元組數約為原來 1/4 ④ 雲端可測時：雲端板在 iPhone 熱點重跑 10/13 的量度（發送最長卡頓、說話時 heap、斷線次數），對照 PCM 版本 ⑤ 舊韌體（1.0.1）連新伺服器照常對話 | N97: ① pytest test_mic_adpcm 10 項：Mac 上編譯 firmware MicAdpcm.cpp，與 audioop 逐 byte 一致（改壞一個表值即失敗）；分塊解碼 = 連續流解碼；掉一塊只損失該塊；人聲段 SNR > 20dB；全套 275 passed ② 伺服器按 X-Mic-Codec 解碼，無 header 照舊 PCM（10:37 1.7.5 → mic=pcm，10:40 1.7.6 → mic=adpcm）③ 62:70 Guest（2026-10-15）：ADPCM 3 輪 Azure zh-HK 辨識通順完整（如『但係點解依家望到外邊係陰天嘅？』），STT 431–526ms，對照同場 PCM 560ms；上行 27,650B/3,370ms 與 16,625B/2,026ms = 8.2 B/ms（PCM 32），發送最長 3ms、最低 heap 55KB | O97: 1ed9d3b | P97: [2026-10-15] 新增 [2026-10-15] 未做：④ 雲端板在 iPhone 熱點重跑 10/13 量度（等雲端可測）；⑤ 舊韌體 1.0.1 連新伺服器（邏輯上無 header 即 PCM，pytest 已覆蓋，未實機）；用戶確認辨識文字與原話一致。分支 p2-24-adpcm-uplink 未合併、未推送。
A98: P2-25 | B98: P2 | C98: 2 內測準備 | D98: 韌體-網絡 | E98: C3 斷線後自救：TLS 握手超時縮短、連續失敗重設 Wi-Fi 或重開、修重試漏記憶體 | F98: 未開始 | G98: 未測試 | I98: 2026-10-13 在 51:16:c0（熱點）斷線後每次重連卡約 121 秒（TLS 握手超時），持續 26 分鐘不恢復；debug 版本顯示每次失敗的重連漏約 170B heap；韌體不會重設 Wi-Fi 或重開，孩子只見玩具不回應。 | J98: firmware-arduino/src/Audio.cpp（websocketSetup、networkTask 重連）、src/WifiManager.cpp；debug 分支 debug-1.0.1-iwdt 的 heap 記錄工具 | K98: ① websocket / HTTPS 的 TLS 握手超時約 15 秒（可調）② 連續 N 次（預設 5）連不上伺服器就重設 Wi-Fi 重連；再連續失敗就 ESP.restart()（試用期內的重開照 OTA 規則處理）③ 失敗的重連不再漏 heap：連續 50 次失敗前後 free heap 差 < 1KB ④ 已綁定設備的正常斷網重連行為不變（R-36 ④） | L98: ① 62:70：停掉語音伺服器 → 串口每次握手失敗 ≤ 15 秒，第 N 次後重設 Wi-Fi、再後重開，恢復伺服器後自動連上 ② 記錄 50 次失敗重連前後的 free heap ③ 雲端可測時在 iPhone 熱點重跑 10/13 情境，斷線後 1 分鐘內恢復對話 | M98: P2-24 | P98: [2026-10-15] 新增

Sheet 待確認問題
A1: 編號 | B1: 問題 | C1: 為什麼重要 | D1: 影響的任務 | E1: 狀態 | F1: 回答 | G1: 回答日期
A2: Q1 | B2: 目標市場與孩子的年齡層是？ | C2: 決定要符合香港 PDPO、內地 PIPL、美國 COPPA 還是歐盟 GDPR-K，以及需要哪些硬件認證。 | D2: P1-04, P1-05, P1-08 | E2: 已回覆 | F2: 首發香港（粵語）；第一階段做陪伴型 AI，之後再加學習類角色。孩子年齡層未定。 | G2: 2026-09-30
A3: Q2 | B3: elatoai.hkqft.com 目前有沒有真實家庭在使用？ | C3: 有的話全部 P0 要立即處理，並要考慮是否需要通知用戶。 | D3: P0-01（全部 P0 的緊急程度） | E3: 已回覆 | F3: 目前沒有真實家庭使用（2026-09-30 確認）。 | G3: 2026-09-30
A4: Q3 | B4: 韌體打算閉源商業銷售嗎？ | C4: 決定 GPL／LGPL 依賴要開源還是替換。 | D4: P1-06, P1-07 | E4: 待回覆
A5: Q4 | B5: 第一年計劃多少台設備？ | C5: 決定擴展與成本相關工作的優先次序。 | D5: P2-08, P2-09（優先次序） | E5: 已回覆 | F5: 3 個月內（約 2026 年底）小批量 100–500 台，用現成板換殼；板子在 Waveshare S3 Audio 與一塊未到貨、類似 xmini-c3 的新板之間選。收費方式未定。 | G5: 2026-09-30
A6: Q5 | B6: 孩子的目標年齡層是幾歲？ | C6: 決定角色的說話方式與話題範圍、內容審核的尺度，以及粵語評測要錄哪個年齡的聲音。 | D6: R-02, R-04, P1-01 | E6: 已回覆 | F6: 3–6 歲。 | G6: 2026-09-30
A7: Q6 | B7: 家長可以自己建立角色嗎？ | C7: 決定角色表的權限與內容安全的把關方式。 | D7: P0-15, R-02 | E7: 已回覆 | F7: v1 關閉，只用內容管理員管理的精選角色。 | G7: 2026-09-30
A8: Q7 | B8: 管理員能不能看孩子的對話和記憶？ | C8: 兒童資料的最小權限原則；決定管理端、資料庫權限和審核事件要記什麼。 | D8: P0-12, P1-01, P1-11 | E8: 已回覆 | F8: 完全不能：網頁管理端和資料庫權限都不給；審核事件只記類別，不記原文。 | G8: 2026-09-30
A9: Q8 | B9: 一個家庭帳號的結構？ | C9: 決定資料表和家長端的權限範圍。 | D9: P0-12 | E9: 已回覆 | F9: v1 維持 1 個家長帳號、1 個孩子、1 台設備。 | G9: 2026-09-30
A10: Q9 | B10: 管理員分幾種角色？ | C10: 最小權限：誰能改角色、誰能改系統設定、誰能動設備。 | D10: P0-12, R-11 | E10: 已回覆 | F10: v1 兩種：超級管理員、內容管理員。客服工具照做，暫由超級管理員使用；客服角色之後有需要再加。 | G10: 2026-09-30
A11: Q10 | B11: 燒錄和出廠自檢在哪裡做：板子供應商出貨前預燒、玩具廠設工位，還是我們自己做？ | C11: 決定出廠腳本、自檢工位和作業指導書按哪種場地準備（W8 要交工廠），以及設備密鑰會不會經過供應商。建議：Spotpear 燒共用、不含密鑰的韌體；玩具廠裝機芯盒工位用我方電腦寫密鑰、選品牌款式、開加密、自檢、登記。最遲 11/6 定。 | D11: R-10 | E11: 已回覆 | F11: 2026-10-12 用戶決定：燒共用韌體。Spotpear 出貨前代燒所有品牌共用、不含密鑰的出廠韌體，附每片 MAC 清單；每台的設備密鑰、品牌和款式、自檢、登記在玩具廠裝機芯盒工位，用我方電腦和腳本經序列埠完成。 | G11: 2026-10-12
A12: Q11 | B12: 馬會快活的賽馬日版和新春版各多少隻（共 2,500）？ | C12: 兩款的服裝和配件要分開訂料；11/20 前不知道，PP 樣和大貨單（11/27）會被拖慢。由馬會決定。 | D12: R-09, R-15 | E12: 待回覆
A13: Q12 | B13: 快活 App 的「會員綁定」是指甚麼：用我們自己的帳號（email 驗證碼），還是接馬會的會員帳號登入（SSO）？ | C13: 接馬會 SSO 的話，登入、帳號刪除和資料歸屬都要按馬會的介面重做，工作量和排期要另估，而且 W5（11/9–11/13）就要做快活 App 的綁定；用我們的帳號則和其他品牌共用同一套流程。由馬會決定，要盡早問。 | D13: P0-11, 快活 App（未入追蹤表） | E13: 待回覆
A14: Q13 | B14: 政協青年聯會版的角色、語言和內容由誰提供？什麼時候交？ | C14: 品牌 B 的用戶是成人會員，但角色、說話語言、內容規則都還沒有。最遲 11/13 要拿到，才趕得及內部測試和 App 頁面（W6）。 | D14: 品牌 B 的 App 頁面 | E14: 待回覆

Sheet 更新記錄
A1: 時間 | B1: 編號 | C1: 任務 / 問題 | D1: 舊狀態 | E1: 新狀態 | F1: 測試結果 | G1: 測試證據 | H1: Commit | I1: 備註
A2: 2026-09-30 09:17 | B2: — | C2: 建立追蹤表 | I2: 依據 2026-09-30 的生產就緒評估建立：31 項任務、4 個待確認問題
A3: 2026-09-30 11:35 | B3: Q1 | C3: 目標市場與孩子的年齡層是？ | D3: 待回覆 | E3: 已回覆 | I3: 首發香港（粵語）；第一階段做陪伴型 AI，之後再加學習類角色。孩子年齡層未定。
A4: 2026-09-30 11:35 | B4: Q2 | C4: elatoai.hkqft.com 目前有沒有真實家庭在使用？ | D4: 待回覆 | E4: 已回覆 | I4: 目前沒有真實家庭使用（2026-09-30 確認）。
A5: 2026-09-30 11:35 | B5: Q4 | C5: 第一年計劃多少台設備？ | D5: 待回覆 | E5: 已回覆 | I5: 3 個月內（約 2026 年底）小批量 100–500 台，用現成板換殼；板子在 Waveshare S3 Audio 與一塊未到貨、類似 xmini-c3 的新板之間選。收費方式未定。
A6: 2026-09-30 11:43 | B6: R-01 | C6: 選定量產板子 | E6: 未開始 | I6: 新增任務（從 seed.json 同步）
A7: 2026-09-30 11:43 | B7: R-02 | C7: 角色收窄到 5–8 個粵語陪伴角色 | E7: 未開始 | I7: 新增任務（從 seed.json 同步）
A8: 2026-09-30 11:43 | B8: R-03 | C8: 移除不用的 Deno／Cloudflare 後端與上游預設主機 | E8: 未開始 | I8: 新增任務（從 seed.json 同步）
A9: 2026-09-30 11:43 | B9: R-04 | C9: 粵語質量評測 | E9: 未開始 | I9: 新增任務（從 seed.json 同步）
A10: 2026-09-30 11:43 | B10: R-05 | C10: 內測版外殼（3D 打印 20 台） | E10: 未開始 | I10: 新增任務（從 seed.json 同步）
A11: 2026-09-30 11:43 | B11: R-06 | C11: 家長自助上手流程 | E11: 未開始 | I11: 新增任務（從 seed.json 同步）
A12: 2026-09-30 11:43 | B12: R-07 | C12: 20 個家庭封閉內測 | E12: 未開始 | I12: 新增任務（從 seed.json 同步）
A13: 2026-09-30 11:43 | B13: R-08 | C13: 第 8 週關卡決策 | E13: 未開始 | I13: 新增任務（從 seed.json 同步）
A14: 2026-09-30 11:43 | B14: R-09 | C14: 量產外殼（真空複模） | E14: 未開始 | I14: 新增任務（從 seed.json 同步）
A15: 2026-09-30 11:43 | B15: R-10 | C15: 出廠流程 | E15: 未開始 | I15: 新增任務（從 seed.json 同步）
A16: 2026-09-30 11:43 | B16: R-11 | C16: 售後：客服、保修與換機 | E16: 未開始 | I16: 新增任務（從 seed.json 同步）
A17: 2026-09-30 11:43 | B17: Q5 | C17: 孩子的目標年齡層是幾歲？ | E17: 待回覆 | I17: 新增待確認問題（從 seed.json 同步）
A18: 2026-09-30 11:43 | B18: — | C18: 同步表格 | I18: 版面更新到最新版；新增 11 項任務、1 個問題；為 31 項任務填入階段
A19: 2026-09-30 11:43 | B19: P0-01 | C19: 確認線上環境的暴露面 | D19: 未開始 | E19: 不適用 | I19: Q2：目前沒有真實家庭使用，緊急度已確定；線上驗證改為每項修復部署後各自做。
A20: 2026-09-30 11:43 | B20: P1-08 | C20: 硬件認證 | D20: 未開始 | E20: 未開始 | I20: 送測需要定案的板子和外殼樣品；修改了依賴→Q1, R-01, R-05
A21: 2026-09-30 11:43 | B21: P0-14 | C21: 韌體簽章、Secure Boot 與 Flash 加密 | D21: 未開始 | E21: 未開始 | I21: Secure Boot 要在定案的板子上驗證；修改了依賴→P0-13, R-01
A22: 2026-09-30 11:46 | B22: Q5 | C22: 孩子的目標年齡層是幾歲？ | D22: 待回覆 | E22: 已回覆 | I22: 3–6 歲。
A23: 2026-09-30 11:46 | B23: R-02 | C23: 角色收窄到 5–8 個粵語陪伴角色 | D23: 未開始 | E23: 未開始 | I23: Q5：3–6 歲；修改了驗收標準、測試方法
A24: 2026-09-30 11:46 | B24: R-04 | C24: 粵語質量評測 | D24: 未開始 | E24: 未開始 | I24: Q5：3–6 歲；3 歲發音較不清，字錯率門檻可能要按首輪結果再討論；修改了測試方法
A25: 2026-09-30 11:46 | B25: R-05 | C25: 內測版外殼（3D 打印 20 台） | D25: 未開始 | E25: 未開始 | I25: Q5：3–6 歲；修改了測試方法
A26: 2026-09-30 11:50 | B26: R-12 | C26: 家長控制：每日使用上限和休息時段 | E26: 未開始 | I26: 新增任務
A27: 2026-09-30 15:01 | B27: P0-15 | C27: 角色表權限：只有內容管理員能發佈，關閉家長自建角色 | E27: 未開始 | I27: 新增任務
A28: 2026-09-30 15:01 | B28: P0-16 | C28: 移除「醫生」身份與寫死的通關碼 | E28: 未開始 | I28: 新增任務
A29: 2026-09-30 15:01 | B29: P1-09 | C29: 家長鎖：孩子模式進設定要輸入 PIN | E29: 未開始 | I29: 新增任務
A30: 2026-09-30 15:01 | B30: P1-10 | C30: 管理操作審計記錄 | E30: 未開始 | I30: 新增任務
A31: 2026-09-30 15:01 | B31: P1-11 | C31: 伺服器與資料庫直接存取的管控 | E31: 未開始 | I31: 新增任務
A32: 2026-09-30 15:01 | B32: P0-12 | C32: 收緊 Admin 權限與路由保護 | D32: 未開始 | E32: 未開始 | I32: 權限設計討論後擴大範圍：見 Q7、Q9；修改了驗收標準、測試方法
A33: 2026-09-30 15:01 | B33: P1-01 | C33: 加入內容審核層（輸入與輸出） | D33: 未開始 | E33: 未開始 | I33: Q5：3–6 歲；Q7：事件不記原文；修改了驗收標準、測試方法
A34: 2026-09-30 15:01 | B34: R-07 | C34: 20 個家庭封閉內測 | D34: 未開始 | E34: 未開始 | I34: 新的權限項也要在內測前完成；修改了依賴→P0-02, P0-03, P0-04, P0-05, P0-06, P0-07, P0-08, P0-09, P0-10, P0-11, P0-12, P0-13, P1-01, P1-02, P2-09, R-01, R-02, R-04, R-05, R-06, P0-15, P0-16, P1-09, P1-11
A35: 2026-09-30 15:01 | B35: R-11 | C35: 售後：客服、保修與換機 | D35: 未開始 | E35: 未開始 | I35: v1 沒有客服角色，售後工具由超級管理員使用（Q9）
A36: 2026-09-30 15:01 | B36: Q6 | C36: 家長可以自己建立角色嗎？ | E36: 待回覆 | I36: 新增待確認問題
A37: 2026-09-30 15:01 | B37: Q6 | C37: 家長可以自己建立角色嗎？ | D37: 待回覆 | E37: 已回覆 | I37: v1 關閉，只用內容管理員管理的精選角色。
A38: 2026-09-30 15:01 | B38: Q7 | C38: 管理員能不能看孩子的對話和記憶？ | E38: 待回覆 | I38: 新增待確認問題
A39: 2026-09-30 15:01 | B39: Q7 | C39: 管理員能不能看孩子的對話和記憶？ | D39: 待回覆 | E39: 已回覆 | I39: 完全不能：網頁管理端和資料庫權限都不給；審核事件只記類別，不記原文。
A40: 2026-09-30 15:01 | B40: Q8 | C40: 一個家庭帳號的結構？ | E40: 待回覆 | I40: 新增待確認問題
A41: 2026-09-30 15:01 | B41: Q8 | C41: 一個家庭帳號的結構？ | D41: 待回覆 | E41: 已回覆 | I41: v1 維持 1 個家長帳號、1 個孩子、1 台設備。
A42: 2026-09-30 15:01 | B42: Q9 | C42: 管理員分幾種角色？ | E42: 待回覆 | I42: 新增待確認問題
A43: 2026-09-30 15:01 | B43: Q9 | C43: 管理員分幾種角色？ | D43: 待回覆 | E43: 已回覆 | I43: v1 兩種：超級管理員、內容管理員。客服工具照做，暫由超級管理員使用；客服角色之後有需要再加。
A44: 2026-10-05 09:40 | B44: — | C44: 同步表格 | I44: 版面更新到最新版；新增 0 項任務、0 個問題；為 0 項任務填入階段
A45: 2026-10-05 09:40 | B45: R-13 | C45: CP1 內測就緒檢查（10/30） | E45: 未開始 | I45: 新增任務
A46: 2026-10-05 09:40 | B46: R-14 | C46: 離線兒歌與故事 | E46: 未開始 | I46: 新增任務
A47: 2026-10-05 09:40 | B47: R-15 | C47: 農曆新年前交付（生產 1/15、送達 1/29） | E47: 未開始 | I47: 新增任務
A48: 2026-10-05 09:40 | B48: R-07 | C48: 20 個家庭封閉內測 | D48: 未開始 | E48: 未開始 | I48: 改為以 CP1（R-13）把關：R-13 已涵蓋原有全部依賴。；修改了依賴→R-13
A49: 2026-10-05 09:40 | B49: R-08 | C49: 第 8 週關卡決策 | D49: 未開始 | E49: 未開始 | I49: 2026-10-05：定為 CP2；收費方式已定為一次性付款、不收月費。；修改了驗收標準、依賴→R-07, P2-09, P1-08
A50: 2026-10-05 09:40 | B50: R-01 | C50: 選定量產板子 | D50: 未開始 | E50: 未開始 | I50: 2026-10-05：期限由「最遲 10/30」收緊為 10/16，外殼、認證、生產都在等這個決定。；修改了驗收標準
A51: 2026-10-05 16:58 | B51: R-01 | C51: 選定量產板子 | D51: 未開始 | E51: 進行中
A52: 2026-10-05 16:58 | B52: R-01 | C52: 選定量產板子 | D52: 進行中 | E52: 進行中 | I52: 2026-10-05：候選板 toy-ai-core-c3-1.54（ESP32-C3、16MB、無 PSRAM）已到貨並移植，env toy-ai-core-c3，引腳由原廠固件反彙編取得（不在小智官方倉庫），原廠固件已整片備份。實測：開機、ES8311 雙向、喇叭出聲、WS2812 狀態燈、SoftAP；WiFi 開啟後內部 RAM 空閒 73KB／最大塊 53KB（未對話）。評分表尚未測：①②⑤⑥⑦；③原廠固件無電池檢測代碼，可能沒有電池；④本版不休眠；⑧有 1.54 寸 ST7789 屏，本版未驅動。
A53: 2026-10-05 17:57 | B53: R-01 | C53: 選定量產板子 | D53: 進行中 | E53: 進行中 | I53: 2026-10-05 補充 toy-ai-core-c3 評分表③：板上已裝電池，但讀不到電量。原廠固件的 GetBatteryLevel 直接 return false；C3 能做 ADC 的腳只有 GPIO0–5，全被屏幕(0/1)、LED(2)、I2C(3/4)、I2S(5) 佔用，所以軟件無法讀電池電壓。要讀電量需改硬件：無屏版可把屏幕的 GPIO0/1 讓出來接分壓電阻，或在現有 I2C 上加電量計（如 MAX17048）。GPIO12/13 尚空，可能接了充電狀態腳，未探測。
A54: 2026-10-05 18:05 | B54: R-16 | C54: Spotpear 量產版加電池電壓檢測（GPIO0 分壓） | E54: 未開始 | I54: 新增任務
A55: 2026-10-05 18:05 | B55: R-01 | C55: 選定量產板子 | D55: 進行中 | E55: 進行中 | I55: 2026-10-05：用戶表示 Spotpear AI Toy（即 toy-ai-core-c3-1.54，env 改名 spotpear-ai-toy）大概率就是量產板；已和用戶跑通 app 綁定和完整對話。電池檢測的改板要求另立任務。
A56: 2026-10-06 15:21 | B56: R-16 | C56: Spotpear 量產版加電池電壓檢測（GPIO0 分壓） | D56: 未開始 | E56: 未開始 | I56: 2026-10-06：用戶表示不需要精確電量，快沒電時提醒即可，也無法自行焊接。改為軟件方案：讀芯片自身供電（GPIO0 內部上下拉分壓，SupplyMonitor.cpp），讀數跌破基準 95.5% 就亮紅燈並播廣東話提醒。已用強制低電量測試版驗證：提醒能播出、紅燈正常。本任務（硬件分壓）暫緩，等充滿再放電的實測：若提醒太遲或不觸發才向 Spotpear 提出。
A57: 2026-10-06 15:21 | B57: R-17 | C57: Spotpear 電池耗盡時插電能否正常開機（供電路徑） | E57: 未開始 | I57: 新增任務
A58: 2026-10-06 17:52 | B58: P2-03 | C58: 提交目前未提交的改動 | D58: 未開始 | E58: 已完成 | F58: 通過 | G58: git status --short → 0 行；3bc7119..b322375 按主題拆成 5 個 commit（50 檔：xmini-c3 電量、facts 記憶層、日期時間天氣、BEAM 評測、進度追蹤）；git ls-remote mygithub main = HEAD = b322375 | H58: b322375
A59: 2026-10-07 10:23 | B59: R-02 | C59: 角色收窄到 5–8 個粵語陪伴角色 | D59: 未開始 | E59: 未開始 | I59: 每個角色現可按語言設定 MiniMax 聲線（personalities.voices，admin 角色頁有廣東話/普通話欄；commit 9557ce5，per-language-voices branch，未 push、雲端 migration 未 apply）。選定角色時可給每個角色一把不同的 Cantonese_* 聲線；MiniMax 只有 6 把粵語聲（男聲僅 PlayfulMan、ProfessionalHost（M)）。本地 AI Hulk/Iron Man 已設粵語聲並實際合成成功。
A60: 2026-10-07 11:59 | B60: P0-15 | C60: 角色表權限：只有內容管理員能發佈，關閉家長自建角色 | D60: 未開始 | E60: 進行中
A61: 2026-10-07 11:59 | B61: P0-15 | C61: 角色表權限：只有內容管理員能發佈，關閉家長自建角色 | D61: 進行中 | E61: 進行中 | F61: 部分通過 | G61: ① 本機 BEGIN/ROLLBACK：修補前 authenticated INSERT creator_id NULL 成功；套 20261007140000 後 authenticated/anon INSERT、UPDATE、TRUNCATE 均 permission denied，SELECT 仍見 42 行，service_role 照常寫入。④ /home/create 改為 redirect /home、移除 + 與側欄入口（tsc 通過，未在瀏覽器驗證）。未做：② 隱藏/他人自建角色仍可讀（SELECT USING true）；③ 未經 has_role 把關（等 P0-12）；現有家長自建角色未設為隱藏。 | H61: 65ddb31 | I61: 分支 lock-character-writes（65ddb31 RLS、f3aafdd 撤 /home/create），未 merge、未套用到生產
A62: 2026-10-07 12:04 | B62: P0-15 | C62: 角色表權限：只有內容管理員能發佈，關閉家長自建角色 | D62: 進行中 | E62: 進行中 | I62: 2026-10-07 用戶決定：現有家長自建角色暫時保留，不設為隱藏，驗收標準相應修改；修改了驗收標準
A63: 2026-10-07 12:17 | B63: R-01 | C63: 選定量產板子 | D63: 進行中 | E63: 進行中 | I63: 2026-10-07：用戶定案 Spotpear AI Toy（toy-ai-core-c3-1.54，env spotpear-ai-toy）為量產板，不再等另一塊板。驗收改為在 Spotpear 上測完評分表，確認沒有否決性問題；仍缺 ①②⑥⑦。；修改了驗收標準
A64: 2026-10-07 12:17 | B64: P0-02 | C64: 收緊 conversations 表的 RLS | D64: 未開始 | E64: 進行中
A65: 2026-10-07 12:17 | B65: P0-03 | C65: 收緊 users 表的 RLS | D65: 未開始 | E65: 進行中
A66: 2026-10-07 12:17 | B66: P0-04 | C66: 收緊 devices 表的 RLS | D66: 未開始 | E66: 進行中
A67: 2026-10-07 12:17 | B67: P0-05 | C67: 撤銷敏感表的多餘授權 | D67: 未開始 | E67: 進行中
A68: 2026-10-07 12:31 | B68: P0-02 | C68: 收緊 conversations 表的 RLS | D68: 進行中 | E68: 進行中 | F68: 通過 | G68: 本機：pg_policies 只剩擁有者 SELECT/DELETE，無 qual=true；publishable key GET/INSERT conversations → 42501；GoTrue 用戶 A 讀自己 2 行、讀 B 0 行，INSERT/UPDATE → 42501；store.insert_conversation_turn（service_role）寫入 user/assistant 兩行成功 | I68: 2026-10-07：migration 20261007130000_lock_down_users_devices_conversations.sql 已寫好並在本機驗證通過，尚未提交。上線順序：先部署新前端（舊前端在新規則下無法建新用戶、無法認領）→ 再在線上 docker exec psql -1 套用 migration → 用線上前端實際的 anon key 重跑 anon GET/PATCH，通過後才標完成。
A69: 2026-10-07 12:31 | B69: P0-03 | C69: 收緊 users 表的 RLS | D69: 進行中 | E69: 進行中 | F69: 通過 | G69: 本機：anon GET/PATCH users → 42501；A 讀 B、改 B 均 0 行；A 改自己的 is_premium/email/device_id → 42501；網頁實測（publishable key）：首次登入建行成功，設定頁保存姓名/年齡/描述 → DB 已更新；用別人 email 建行 → RLS 拒絕 | I69: 2026-10-07：migration 20261007130000_lock_down_users_devices_conversations.sql 已寫好並在本機驗證通過，尚未提交。上線順序：先部署新前端（舊前端在新規則下無法建新用戶、無法認領）→ 再在線上 docker exec psql -1 套用 migration → 用線上前端實際的 anon key 重跑 anon GET/PATCH，通過後才標完成。
A70: 2026-10-07 12:31 | B70: P0-04 | C70: 收緊 devices 表的 RLS | D70: 進行中 | E70: 進行中 | F70: 通過 | G70: 本機：anon GET/PATCH devices → 42501；A 改 B 的 user_id、直接認領無主設備、INSERT → 42501；網頁實測：無主清單 Claim → devices.user_id 與 users.device_id 已寫入，音量 70→3，Unbind 清空，輸入配對碼綁定成功 | I70: 2026-10-07：migration 20261007130000_lock_down_users_devices_conversations.sql 已寫好並在本機驗證通過，尚未提交。上線順序：先部署新前端（舊前端在新規則下無法建新用戶、無法認領）→ 再在線上 docker exec psql -1 套用 migration → 用線上前端實際的 anon key 重跑 anon GET/PATCH，通過後才標完成。
A71: 2026-10-07 12:31 | B71: P0-05 | C71: 撤銷敏感表的多餘授權 | D71: 進行中 | E71: 進行中 | F71: 通過 | G71: 本機 role_table_grants：anon 對三表 0 筆；authenticated＝users SELECT＋欄位級 INSERT/UPDATE、devices SELECT＋UPDATE(volume,is_reset,is_ota)、conversations SELECT/DELETE，三表都沒有 TRUNCATE | I71: 2026-10-07：migration 20261007130000_lock_down_users_devices_conversations.sql 已寫好並在本機驗證通過，尚未提交。上線順序：先部署新前端（舊前端在新規則下無法建新用戶、無法認領）→ 再在線上 docker exec psql -1 套用 migration → 用線上前端實際的 anon key 重跑 anon GET/PATCH，通過後才標完成。
A72: 2026-10-07 12:31 | B72: P0-11 | C72: 設備認領要求持有證明 | D72: 未開始 | E72: 未開始 | I72: 2026-10-07：addUserToDevice（輸入配對碼）沒有限制 user_id IS NULL，知道配對碼就能把已有主人的設備轉到自己帳號；P0-04 只把它搬到 service_role，行為未改，留給本項處理。
A73: 2026-10-07 12:31 | B73: P0-16 | C73: 移除「醫生」身份與寫死的通關碼 | D73: 未開始 | E73: 未開始 | I73: 2026-10-07：P0-04 的 migration 讓 authenticated 仍可改 users.user_info，只因 Onboarding/AppSettings 還在那裡寫 doctor 身份；移除 doctor 後，同時從 GRANT UPDATE 拿掉 user_info。
A74: 2026-10-07 12:31 | B74: P0-17 | C74: 前端的 anon key 必須是公開 key，不可是 secret／service_role | E74: 未開始 | I74: 新增任務
A75: 2026-10-07 12:45 | B75: P0-17 | C75: 前端的 anon key 必須是公開 key，不可是 secret／service_role | D75: 未開始 | E75: 進行中
A76: 2026-10-07 12:45 | B76: P0-17 | C76: 前端的 anon key 必須是公開 key，不可是 secret／service_role | D76: 進行中 | E76: 進行中 | F76: 部分通過 | G76: ① 線上 /login 引用的 12 個 JS + HTML：無 sb_secret_，唯一的 key 是 role=anon 的 JWT ③ 本機 .env.local 原為 sb_secret_（已備份 .env.local.bak-p017），換成 kong 的 sb_publishable_ 後 anon GET /rest/v1/users → 42501。② 未做：線上 RLS 尚未套用，現在讀 users 會讀到全部家庭資料 | I76: 2026-10-07：線上沒有外洩 secret key，無需輪換。② 要等 P0-02～P0-05 的 migration 在線上套用後再測。
A77: 2026-10-07 12:45 | B77: P0-02 | C77: 收緊 conversations 表的 RLS | D77: 進行中 | E77: 進行中 | H77: e3dfb35
A78: 2026-10-07 12:45 | B78: P0-03 | C78: 收緊 users 表的 RLS | D78: 進行中 | E78: 進行中 | H78: e3dfb35
A79: 2026-10-07 12:45 | B79: P0-04 | C79: 收緊 devices 表的 RLS | D79: 進行中 | E79: 進行中 | H79: e3dfb35
A80: 2026-10-07 12:45 | B80: P0-05 | C80: 撤銷敏感表的多餘授權 | D80: 進行中 | E80: 進行中 | H80: e3dfb35
A81: 2026-10-07 13:03 | B81: P0-06 | C81: 停止憑 MAC 發放永久用戶 JWT | D81: 未開始 | E81: 進行中
A82: 2026-10-07 13:03 | B82: P0-08 | C82: 語音伺服器驗證設備身份（/ws/esp32） | D82: 未開始 | E82: 進行中
A83: 2026-10-07 13:03 | B83: P0-06 | C83: 停止憑 MAC 發放永久用戶 JWT | D83: 進行中 | E83: 進行中 | F83: 部分通過 | G83: 本機 API（SKIP=False）：GET → 410；新 MAC 首次 POST → 202＋43 字元密鑰；只帶 MAC 或錯誤密鑰 → 401，last_seen_at 不變；持密鑰未認領 → 202；認領後 → 200 token（typ=device，24h，無 role/email）；設備 token 讀 users/conversations/devices → PostgREST 401；device_secrets 只存 sha256。④實機：localall 韌體已燒到開發板，等 WiFi 設定後測 | I83: 2026-10-07：實作＝device_secrets 表（20261007150000）＋lib/deviceAuth.ts＋generate_auth_token 改 POST＋韌體密鑰存 NVS「device」、token 只放 RAM、斷線時續期。上線必須三者一起：前端、語音伺服器、韌體；兩邊 env 都要先設同一個 DEVICE_JWT_SECRET；雲端已配對的測試板要重燒。NVS 被清的板子要刪 device_secrets 那行才能重新領密鑰。
A84: 2026-10-07 13:03 | B84: P0-08 | C84: 語音伺服器驗證設備身份（/ws/esp32） | D84: 進行中 | E84: 進行中 | F84: 部分通過 | G84: pytest tests/test_device_auth.py 30 項通過（含 jsonwebtoken 簽的 token、alg none/HS512、改 payload、過期、/ws/esp32 偽造 MAC→4401、header 謊報 MAC 被忽略）；本機 7861 實測：無 token／過期／Supabase secret 簽的 → 4401，有效 token → 收到 auth。③真實設備待測 | I84: 2026-10-07：device_auth.py 用標準庫 hmac 驗 HS256（venv 無 PyJWT），每次呼叫才讀 DEVICE_JWT_SECRET（bot.py 的 load_dotenv 在 import 之後）。未設 secret 時所有設備被拒。
A85: 2026-10-07 13:03 | B85: P0-11 | C85: 設備認領要求持有證明 | D85: 未開始 | E85: 未開始 | I85: 2026-10-07：P0-06 之後配對碼只回給持有設備密鑰的請求（只知 MAC → 401），驗收第一條在本機已成立；仍缺：不再列出全球未認領設備、輸錯上限、addUserToDevice 搶已綁定設備。
A86: 2026-10-07 14:39 | B86: P0-06 | C86: 停止憑 MAC 發放永久用戶 JWT | D86: 進行中 | E86: 進行中 | F86: 通過 | G86: 本機 API：只帶 MAC 或錯誤密鑰 → 401、GET → 410；設備 token 讀 users/conversations/devices → PostgREST 401；過期 token 在 ws 與 reset 路由都被拒。實機（開發板 63:64，localall 韌體）：首次聯絡領到密鑰存 NVS、換到 24h token、連上 7861、對話「你聽唔聽到我講嘢？」與回覆寫入 conversations | H86: da98048 | I86: 2026-10-07：本機全部驗收通過（commit da98048），仍保持進行中：線上尚未部署。上線順序：兩邊 env 設同一個 DEVICE_JWT_SECRET → 套用 20261007150000 → 部署前端與語音伺服器 → 重燒雲端測試板。
A87: 2026-10-07 14:39 | B87: P0-08 | C87: 語音伺服器驗證設備身份（/ws/esp32） | D87: 進行中 | E87: 進行中 | F87: 通過 | G87: pytest test_device_auth.py 30 項通過；本機：偽造 MAC、過期、Supabase secret 簽的 token → 4401；實機 token 被拒時韌體偵測到「auth 之前被關閉」，斷線期間續期（拒 22 次、換 3 次 token、0 panic），密鑰改回後自動恢復；伺服器日誌身份取自 token（device=9fe8d112…） | H87: da98048 | I87: 2026-10-07：本機全部驗收通過（commit da98048），仍保持進行中：線上尚未部署。上線順序：兩邊 env 設同一個 DEVICE_JWT_SECRET → 套用 20261007150000 → 部署前端與語音伺服器 → 重燒雲端測試板。
A88: 2026-10-07 15:05 | B88: P0-02 | C88: 收緊 conversations 表的 RLS | D88: 進行中 | E88: 進行中 | I88: 2026-10-07：用戶決定延後部署，與後續任務合併成一批上線。mygithub/main 與 GHCR :latest 已是新版（da98048 起），主機在跑 runbook 前不可 docker compose pull。
A89: 2026-10-07 15:05 | B89: P0-03 | C89: 收緊 users 表的 RLS | D89: 進行中 | E89: 進行中 | I89: 2026-10-07：用戶決定延後部署，與後續任務合併成一批上線。mygithub/main 與 GHCR :latest 已是新版（da98048 起），主機在跑 runbook 前不可 docker compose pull。
A90: 2026-10-07 15:05 | B90: P0-04 | C90: 收緊 devices 表的 RLS | D90: 進行中 | E90: 進行中 | I90: 2026-10-07：用戶決定延後部署，與後續任務合併成一批上線。mygithub/main 與 GHCR :latest 已是新版（da98048 起），主機在跑 runbook 前不可 docker compose pull。
A91: 2026-10-07 15:05 | B91: P0-05 | C91: 撤銷敏感表的多餘授權 | D91: 進行中 | E91: 進行中 | I91: 2026-10-07：用戶決定延後部署，與後續任務合併成一批上線。mygithub/main 與 GHCR :latest 已是新版（da98048 起），主機在跑 runbook 前不可 docker compose pull。
A92: 2026-10-07 15:05 | B92: P0-06 | C92: 停止憑 MAC 發放永久用戶 JWT | D92: 進行中 | E92: 進行中 | I92: 2026-10-07：用戶決定延後部署，與後續任務合併成一批上線。mygithub/main 與 GHCR :latest 已是新版（da98048 起），主機在跑 runbook 前不可 docker compose pull。
A93: 2026-10-07 15:05 | B93: P0-08 | C93: 語音伺服器驗證設備身份（/ws/esp32） | D93: 進行中 | E93: 進行中 | I93: 2026-10-07：用戶決定延後部署，與後續任務合併成一批上線。mygithub/main 與 GHCR :latest 已是新版（da98048 起），主機在跑 runbook 前不可 docker compose pull。
A94: 2026-10-07 15:06 | B94: P2-01 | C94: 修好後端測試環境 | D94: 未開始 | E94: 進行中
A95: 2026-10-07 15:07 | B95: P2-01 | C95: 修好後端測試環境 | D95: 進行中 | E95: 已完成 | F95: 通過 | G95: cd server/fastapi && .venv/bin/python -m pytest -q → 173 passed（原本 60 個 async 測試報「not natively supported」）；pyproject dev group 加 pytest>=9,<10、pytest-asyncio>=1.4,<2，asyncio_mode=auto；pip install --dry-run --group dev 可解析 | H95: 6641fa8 | I95: 2026-10-07：pytest-asyncio 其實已裝，問題是 strict 模式略過沒有 marker 的 async 測試。剩 10 個 warning 是 pipecat/fastapi 棄用提示與兩個 memory_processors 測試沒啟動 processor，不影響結果。
A96: 2026-10-07 15:12 | B96: P0-10 | C96: 生產環境關閉 /browser 測試頁與 /ws/browser | D96: 未開始 | E96: 進行中
A97: 2026-10-07 15:12 | B97: P0-16 | C97: 移除「醫生」身份與寫死的通關碼 | D97: 未開始 | E97: 進行中
A98: 2026-10-07 15:13 | B98: P0-10 | C98: 生產環境關閉 /browser 測試頁與 /ws/browser | D98: 進行中 | E98: 進行中 | F98: 通過 | G98: pytest test_browser_test_routes.py 9 項通過（旗標未設/空/false/0/no → /browser 404、/ 404、/ws/browser 拒絕、/healthz 200；true/1/yes/TRUE → 頁面與路由恢復）；全套 182 passed。本機以生產設定實跑 uvicorn：GET / 404、/browser 404、/healthz 200、ws /ws/browser → HTTP 403 | H98: d0cfbb8 | I98: 2026-10-07：本機 server/fastapi/.env 加 ENABLE_BROWSER_TEST=true 方便開發；線上不設。保持進行中：要隨下一批部署後在線上複測（GET https://elatoai.hkqft.com/fastapi/browser → 404）。
A99: 2026-10-07 15:22 | B99: P0-16 | C99: 移除「醫生」身份與寫死的通關碼 | D99: 進行中 | E99: 進行中 | F99: 通過 | G99: ① grep checkDoctorAction/kiwi-subtle-emu/=== "doctor" → 0（以 staged 內容的乾淨 worktree 驗證）② tsc 通過；eslint(next/core-web-vitals) 改動檔 0 error（4 個 warning 為原有 hook 依賴）③ 本機新帳號實測：首頁只剩 Story/Children、無醫療/Santa/patient 字樣；onboarding 保存→ users 已更新、PATCH 204；設定頁正常。migration 20261007160000 本機：4 個 is_doctor 內建角色 is_hidden=true，authenticated UPDATE 欄位不再含 user_info | H99: 3897269 | I99: 2026-10-07：專案沒有 ESLint 設定（next lint 會停在互動設定），以臨時 config 只檢查改動檔，正式 lint 屬 P2-02。migration 必須在新前端上線後才套用（舊前端每次保存都寫 user_info）。Santa Claus 原本也被標成 is_doctor，一起隱藏；需要時可在 admin 取消隱藏。保持進行中：隨下一批部署。
A100: 2026-10-07 15:29 | B100: R-03 | C100: 移除不用的 Deno／Cloudflare 後端與上游預設主機 | D100: 未開始 | E100: 進行中
...
